Workbook

Sheet Validation
A1: CaseID | B1: Individual | C1: Classes | D1: #Classes | E1: Class #1 | F1: Hallucinated class #1 | H1: Class #2 | I1: Hallucinated class #2 | J1: Class #3 | K1: Hallucinated class #3 | L1: ObjectProperties | M1: DataProperties | N1: Annotations | O1: MissingType | P1: WrongClasses | Q1: WrongProperties | R1: Define source | S1: Related concept | T1: Group of concepts | U1: Unsolicited | V1: Hallucination_any | W1: Hallucination_Structural | X1: Hallucination_Semantic | Y1: Hallucination_Contextual | Z1: Hallucination_Evidence | AA1: Explanation_Generated
A2: UC1-F1-P1-S1-M1 | B2: BTD_BiotinTreatment_AnnualCost | C2: CostParameter | D2: =IF(ISBLANK(C2),0,LEN(C2)-LEN(SUBSTITUTE(C2,";",""))+1) -> 1 | E2: =IF(D2<2,C2,LEFT(C2,FIND(";",C2)-1)) -> CostParameter | F2: =IF(D2<1,FALSE,ISERROR(MATCH(E2,'Ontology and concepts per UC'!$A$2:$A$62,0))) -> TRUE | G2: =IF(D2<2,"",MID(C2,LEN(E2)+3,LEN(C2)-FIND(";",C2)-1)) | H2: =IF(D2<3,G2,LEFT(G2,FIND(";",G2)-1)) | I2: =IF(D2<2,FALSE,ISERROR(MATCH(H2,'Ontology and concepts per UC'!$A$2:$A$62,0))) -> FALSE | J2: =IF(D2<3,"",RIGHT(G2,LEN(G2)-FIND(";",G2)-1)) | K2: =IF(D2<3,FALSE,ISERROR(MATCH(J2,'Ontology and concepts per UC'!$A$2:$A$62,0))) -> FALSE | M2: hasDescription:"Coste anual del tratamiento con biotina (5-10 mg/día)"; hasUnit:"EUR"; hasExpectedValue:"730"; | O2: FALSE | P2: 1 | Q2: 0 | R2: =NOT(ISERROR(SEARCH("hasSource",M2))) -> FALSE | S2: Coste tratamiento | T2: =IF(S2="","",VLOOKUP(S2,'Ontology and concepts per UC'!$F$2:$J$46,5,FALSE)) -> Coste | U2: {=(INDEX('Ontology and concepts per UC'!$G$2:$I$46,MATCH($S2,'Ontology and concepts per UC'!$F$2:$F$46,0),MATCH(LEFT($A2,3),'Ontology and concepts per UC'!$G$1:$I$1,0))=0)} -> FALSE | V2: =COUNTIF(W2:Z2,TRUE)>0 -> TRUE | W2: TRUE | X2: FALSE | Y2: FALSE | Z2: FALSE | AA2: Class 'CostParameter' undefined
A3: UC1-F1-P1-S1-M1 | B3: BTD_DiagnosticTest_Cost | C3: CostParameter | D3: =IF(ISBLANK(C3),0,LEN(C3)-LEN(SUBSTITUTE(C3,";",""))+1) -> 1 | E3: =IF(D3<2,C3,LEFT(C3,FIND(";",C3)-1)) -> CostParameter | F3: =IF(D3<1,FALSE,ISERROR(MATCH(E3,'Ontology and concepts per UC'!$A$2:$A$62,0))) -> TRUE | G3: =IF(D3<2,"",MID(C3,LEN(E3)+3,LEN(C3)-FIND(";",C3)-1)) | H3: =IF(D3<3,G3,LEFT(G3,FIND(";",G3)-1)) | I3: =IF(D3<2,FALSE,ISERROR(MATCH(H3,'Ontology and concepts per UC'!$A$2:$A$62,0))) -> FALSE | J3: =IF(D3<3,"",RIGHT(G3,LEN(G3)-FIND(";",G3)-1)) | K3: =IF(D3<3,FALSE,ISERROR(MATCH(J3,'Ontology and concepts per UC'!$A$2:$A$62,0))) -> FALSE | M3: hasDescription:"Coste de la prueba diagnóstica confirmatoria"; hasExpectedValue:"150"; | O3: FALSE | P3: 1 | Q3: 0 | R3: =NOT(ISERROR(SEARCH("hasSource",M3))) -> FALSE | S3: Coste de diagnóstico | T3: =IF(S3="","",VLOOKUP(S3,'Ontology and concepts per UC'!$F$2:$J$46,5,FALSE)) -> Coste | U3: {=(INDEX('Ontology and concepts per UC'!$G$2:$I$46,MATCH($S3,'Ontology and concepts per UC'!$F$2:$F$46,0),MATCH(LEFT($A3,3),'Ontology and concepts per UC'!$G$1:$I$1,0))=0)} -> FALSE | V3: =COUNTIF(W3:Z3,TRUE)>0 -> TRUE | W3: TRUE | X3: FALSE | Y3: FALSE | Z3: FALSE | AA3: Class 'CostParameter' undefined
A4: UC1-F1-P1-S1-M1 | B4: BTD_Screening_Cost | C4: CostParameter | D4: =IF(ISBLANK(C4),0,LEN(C4)-LEN(SUBSTITUTE(C4,";",""))+1) -> 1 | E4: =IF(D4<2,C4,LEFT(C4,FIND(";",C4)-1)) -> CostParameter | F4: =IF(D4<1,FALSE,ISERROR(MATCH(E4,'Ontology and concepts per UC'!$A$2:$A$62,0))) -> TRUE | G4: =IF(D4<2,"",MID(C4,LEN(E4)+3,LEN(C4)-FIND(";",C4)-1)) | H4: =IF(D4<3,G4,LEFT(G4,FIND(";",G4)-1)) | I4: =IF(D4<2,FALSE,ISERROR(MATCH(H4,'Ontology and concepts per UC'!$A$2:$A$62,0))) -> FALSE | J4: =IF(D4<3,"",RIGHT(G4,LEN(G4)-FIND(";",G4)-1)) | K4: =IF(D4<3,FALSE,ISERROR(MATCH(J4,'Ontology and concepts per UC'!$A$2:$A$62,0))) -> FALSE | M4: hasExpectedValue:"3.50"; hasDescription:"Coste del cribado neonatal por recién nacido"; hasUnit:"EUR"; | O4: FALSE | P4: 1 | Q4: 0 | R4: =NOT(ISERROR(SEARCH("hasSource",M4))) -> FALSE | S4: Coste cribado | T4: =IF(S4="","",VLOOKUP(S4,'Ontology and concepts per UC'!$F$2:$J$46,5,FALSE)) -> Coste | U4: {=(INDEX('Ontology and concepts per UC'!$G$2:$I$46,MATCH($S4,'Ontology and concepts per UC'!$F$2:$F$46,0),MATCH(LEFT($A4,3),'Ontology and concepts per UC'!$G$1:$I$1,0))=0)} -> FALSE | V4: =COUNTIF(W4:Z4,TRUE)>0 -> TRUE | W4: TRUE | X4: FALSE | Y4: FALSE | Z4: FALSE | AA4: Class 'CostParameter' undefined
A5: UC1-F1-P1-S1-M1 | B5: BTD_Disease_Partial | C5: Disease | D5: =IF(ISBLANK(C5),0,LEN(C5)-LEN(SUBSTITUTE(C5,";",""))+1) -> 1 | E5: =IF(D5<2,C5,LEFT(C5,FIND(";",C5)-1)) -> Disease | F5: =IF(D5<1,FALSE,ISERROR(MATCH(E5,'Ontology and concepts per UC'!$A$2:$A$62,0))) -> FALSE | G5: =IF(D5<2,"",MID(C5,LEN(E5)+3,LEN(C5)-FIND(";",C5)-1)) | H5: =IF(D5<3,G5,LEFT(G5,FIND(";",G5)-1)) | I5: =IF(D5<2,FALSE,ISERROR(MATCH(H5,'Ontology and concepts per UC'!$A$2:$A$62,0))) -> FALSE | J5: =IF(D5<3,"",RIGHT(G5,LEN(G5)-FIND(";",G5)-1)) | K5: =IF(D5<3,FALSE,ISERROR(MATCH(J5,'Ontology and concepts per UC'!$A$2:$A$62,0))) -> FALSE | L5: isSubtypeOf:BTD_Disease; | M5: hasDescription:"Deficiencia parcial de biotinidasa (actividad enzimática 10-30% del valor normal)"; | O5: FALSE | P5: 0 | Q5: 1 | R5: =NOT(ISERROR(SEARCH("hasSource",M5))) -> FALSE | S5: Parcial | T5: =IF(S5="","",VLOOKUP(S5,'Ontology and concepts per UC'!$F$2:$J$46,5,FALSE)) -> Parcial | U5: {=(INDEX('Ontology and concepts per UC'!$G$2:$I$46,MATCH($S5,'Ontology and concepts per UC'!$F$2:$F$46,0),MATCH(LEFT($A5,3),'Ontology and concepts per UC'!$G$1:$I$1,0))=0)} -> FALSE | V5: =COUNTIF(W5:Z5,TRUE)>0 -> TRUE | W5: TRUE | X5: FALSE | Y5: FALSE | Z5: FALSE | AA5: ObjectProp 'isSubtypeOf' undefined
A6: UC1-F1-P1-S1-M1 | B6: BTD_Disease_Profound | C6: Disease | D6: =IF(ISBLANK(C6),0,LEN(C6)-LEN(SUBSTITUTE(C6,";",""))+1) -> 1 | E6: =IF(D6<2,C6,LEFT(C6,FIND(";",C6)-1)) -> Disease | F6: =IF(D6<1,FALSE,ISERROR(MATCH(E6,'Ontology and concepts per UC'!$A$2:$A$62,0))) -> FALSE | G6: =IF(D6<2,"",MID(C6,LEN(E6)+3,LEN(C6)-FIND(";",C6)-1)) | H6: =IF(D6<3,G6,LEFT(G6,FIND(";",G6)-1)) | I6: =IF(D6<2,FALSE,ISERROR(MATCH(H6,'Ontology and concepts per UC'!$A$2:$A$62,0))) -> FALSE | J6: =IF(D6<3,"",RIGHT(G6,LEN(G6)-FIND(";",G6)-1)) | K6: =IF(D6<3,FALSE,ISERROR(MATCH(J6,'Ontology and concepts per UC'!$A$2:$A$62,0))) -> FALSE | L6: hasFeature:BTD_Manif_OpticAtrophy; hasFeature:BTD_Manif_DevelopmentalDelay; hasFeature:BTD_Manif_Seizures; hasFeature:BTD_Manif_HearingLoss; hasFeature:BTD_Manif_SkinProblems; hasFeature:BTD_Manif_Hypotonia; isSubtypeOf:BTD_Disease; | M6: hasDescription:"Deficiencia profunda de biotinidasa (actividad enzimática menor del 10% del valor normal)"; | O6: FALSE | P6: 0 | Q6: 7 | R6: =NOT(ISERROR(SEARCH("hasSource",M6))) -> FALSE | S6: Enfermedad | T6: =IF(S6="","",VLOOKUP(S6,'Ontology and concepts per UC'!$F$2:$J$46,5,FALSE)) -> Modelo Conceptual | U6: {=(INDEX('Ontology and concepts per UC'!$G$2:$I$46,MATCH($S6,'Ontology and concepts per UC'!$F$2:$F$46,0),MATCH(LEFT($A6,3),'Ontology and concepts per UC'!$G$1:$I$1,0))=0)} -> FALSE | V6: =COUNTIF(W6:Z6,TRUE)>0 -> TRUE | W6: TRUE | X6: FALSE | Y6: FALSE | Z6: FALSE | AA6: ObjectProp 'hasFeature' undefined; ObjectProp 'isSubtypeOf' undefined
A7: UC1-F1-P1-S1-M1 | B7: BTD_FollowUp_AnnualMonitoring | C7: FollowUpStrategy | D7: =IF(ISBLANK(C7),0,LEN(C7)-LEN(SUBSTITUTE(C7,";",""))+1) -> 1 | E7: =IF(D7<2,C7,LEFT(C7,FIND(";",C7)-1)) -> FollowUpStrategy | F7: =IF(D7<1,FALSE,ISERROR(MATCH(E7,'Ontology and concepts per UC'!$A$2:$A$62,0))) -> FALSE | G7: =IF(D7<2,"",MID(C7,LEN(E7)+3,LEN(C7)-FIND(";",C7)-1)) | H7: =IF(D7<3,G7,LEFT(G7,FIND(";",G7)-1)) | I7: =IF(D7<2,FALSE,ISERROR(MATCH(H7,'Ontology and concepts per UC'!$A$2:$A$62,0))) -> FALSE | J7: =IF(D7<3,"",RIGHT(G7,LEN(G7)-FIND(";",G7)-1)) | K7: =IF(D7<3,FALSE,ISERROR(MATCH(J7,'Ontology and concepts per UC'!$A$2:$A$62,0))) -> FALSE | O7: FALSE | P7: 0 | Q7: 0 | R7: =NOT(ISERROR(SEARCH("hasSource",M7))) -> FALSE | S7: Seguimiento | T7: =IF(S7="","",VLOOKUP(S7,'Ontology and concepts per UC'!$F$2:$J$46,5,FALSE)) -> Tratamiento/seguimiento | U7: {=(INDEX('Ontology and concepts per UC'!$G$2:$I$46,MATCH($S7,'Ontology and concepts per UC'!$F$2:$F$46,0),MATCH(LEFT($A7,3),'Ontology and concepts per UC'!$G$1:$I$1,0))=0)} -> FALSE | V7: =COUNTIF(W7:Z7,TRUE)>0 -> FALSE | W7: FALSE | X7: FALSE | Y7: FALSE | Z7: FALSE
A8: UC1-F1-P1-S1-M1 | B8: BTD_Intervention_BiotinTreatment | C8: Intervention | D8: =IF(ISBLANK(C8),0,LEN(C8)-LEN(SUBSTITUTE(C8,";",""))+1) -> 1 | E8: =IF(D8<2,C8,LEFT(C8,FIND(";",C8)-1)) -> Intervention | F8: =IF(D8<1,FALSE,ISERROR(MATCH(E8,'Ontology and concepts per UC'!$A$2:$A$62,0))) -> FALSE | G8: =IF(D8<2,"",MID(C8,LEN(E8)+3,LEN(C8)-FIND(";",C8)-1)) | H8: =IF(D8<3,G8,LEFT(G8,FIND(";",G8)-1)) | I8: =IF(D8<2,FALSE,ISERROR(MATCH(H8,'Ontology and concepts per UC'!$A$2:$A$62,0))) -> FALSE | J8: =IF(D8<3,"",RIGHT(G8,LEN(G8)-FIND(";",G8)-1)) | K8: =IF(D8<3,FALSE,ISERROR(MATCH(J8,'Ontology and concepts per UC'!$A$2:$A$62,0))) -> FALSE | L8: hasTreatmentCost:BTD_BiotinTreatment_AnnualCost; | M8: hasDescription:"Tratamiento con biotina oral (5-30 mg/día)"; | O8: FALSE | P8: 0 | Q8: 0 | R8: =NOT(ISERROR(SEARCH("hasSource",M8))) -> FALSE | S8: Tratamiento base | T8: =IF(S8="","",VLOOKUP(S8,'Ontology and concepts per UC'!$F$2:$J$46,5,FALSE)) -> Tratamiento/seguimiento | U8: {=(INDEX('Ontology and concepts per UC'!$G$2:$I$46,MATCH($S8,'Ontology and concepts per UC'!$F$2:$F$46,0),MATCH(LEFT($A8,3),'Ontology and concepts per UC'!$G$1:$I$1,0))=0)} -> FALSE | V8: =COUNTIF(W8:Z8,TRUE)>0 -> TRUE | W8: FALSE | X8: FALSE | Y8: FALSE | Z8: TRUE | AA8: Should not be an Intervention
A9: UC1-F1-P1-S1-M1 | B9: BTD_Intervention_ClinicalDiagnosis | C9: Intervention | D9: =IF(ISBLANK(C9),0,LEN(C9)-LEN(SUBSTITUTE(C9,";",""))+1) -> 1 | E9: =IF(D9<2,C9,LEFT(C9,FIND(";",C9)-1)) -> Intervention | F9: =IF(D9<1,FALSE,ISERROR(MATCH(E9,'Ontology and concepts per UC'!$A$2:$A$62,0))) -> FALSE | G9: =IF(D9<2,"",MID(C9,LEN(E9)+3,LEN(C9)-FIND(";",C9)-1)) | H9: =IF(D9<3,G9,LEFT(G9,FIND(";",G9)-1)) | I9: =IF(D9<2,FALSE,ISERROR(MATCH(H9,'Ontology and concepts per UC'!$A$2:$A$62,0))) -> FALSE | J9: =IF(D9<3,"",RIGHT(G9,LEN(G9)-FIND(";",G9)-1)) | K9: =IF(D9<3,FALSE,ISERROR(MATCH(J9,'Ontology and concepts per UC'!$A$2:$A$62,0))) -> FALSE | M9: hasDescription:"Detección clínica de la deficiencia de biotinidasa tras aparición de síntomas"; | O9: FALSE | P9: 0 | Q9: 0 | R9: =NOT(ISERROR(SEARCH("hasSource",M9))) -> FALSE | S9: Intervención: No cribado | T9: =IF(S9="","",VLOOKUP(S9,'Ontology and concepts per UC'!$F$2:$J$46,5,FALSE)) -> Modelo Conceptual | U9: {=(INDEX('Ontology and concepts per UC'!$G$2:$I$46,MATCH($S9,'Ontology and concepts per UC'!$F$2:$F$46,0),MATCH(LEFT($A9,3),'Ontology and concepts per UC'!$G$1:$I$1,0))=0)} -> FALSE | V9: =COUNTIF(W9:Z9,TRUE)>0 -> FALSE | W9: FALSE | X9: FALSE | Y9: FALSE | Z9: FALSE
A10: UC1-F1-P1-S1-M1 | B10: BTD_Intervention_Screening | C10: Intervention | D10: =IF(ISBLANK(C10),0,LEN(C10)-LEN(SUBSTITUTE(C10,";",""))+1) -> 1 | E10: =IF(D10<2,C10,LEFT(C10,FIND(";",C10)-1)) -> Intervention | F10: =IF(D10<1,FALSE,ISERROR(MATCH(E10,'Ontology and concepts per UC'!$A$2:$A$62,0))) -> FALSE | G10: =IF(D10<2,"",MID(C10,LEN(E10)+3,LEN(C10)-FIND(";",C10)-1)) | H10: =IF(D10<3,G10,LEFT(G10,FIND(";",G10)-1)) | I10: =IF(D10<2,FALSE,ISERROR(MATCH(H10,'Ontology and concepts per UC'!$A$2:$A$62,0))) -> FALSE | J10: =IF(D10<3,"",RIGHT(G10,LEN(G10)-FIND(";",G10)-1)) | K10: =IF(D10<3,FALSE,ISERROR(MATCH(J10,'Ontology and concepts per UC'!$A$2:$A$62,0))) -> FALSE | L10: modifies:BTD_Manif_HearingLoss_Prob_WithoutTreatment; | M10: hasDescription:"Cribado neonatal de la deficiencia de biotinidasa mediante ensayo enzimático o fluorimétrico semicuantitativo"; | O10: FALSE | P10: 0 | Q10: 0 | R10: =NOT(ISERROR(SEARCH("hasSource",M10))) -> FALSE | S10: Intervención: Cribado | T10: =IF(S10="","",VLOOKUP(S10,'Ontology and concepts per UC'!$F$2:$J$46,5,FALSE)) -> Modelo Conceptual | U10: {=(INDEX('Ontology and concepts per UC'!$G$2:$I$46,MATCH($S10,'Ontology and concepts per UC'!$F$2:$F$46,0),MATCH(LEFT($A10,3),'Ontology and concepts per UC'!$G$1:$I$1,0))=0)} -> FALSE | V10: =COUNTIF(W10:Z10,TRUE)>0 -> FALSE | W10: FALSE | X10: FALSE | Y10: FALSE | Z10: FALSE
A11: UC1-F1-P1-S1-M1 | B11: BTD_Manif_DevelopmentalDelay | C11: Manifestation | D11: =IF(ISBLANK(C11),0,LEN(C11)-LEN(SUBSTITUTE(C11,";",""))+1) -> 1 | E11: =IF(D11<2,C11,LEFT(C11,FIND(";",C11)-1)) -> Manifestation | F11: =IF(D11<1,FALSE,ISERROR(MATCH(E11,'Ontology and concepts per UC'!$A$2:$A$62,0))) -> FALSE | G11: =IF(D11<2,"",MID(C11,LEN(E11)+3,LEN(C11)-FIND(";",C11)-1)) | H11: =IF(D11<3,G11,LEFT(G11,FIND(";",G11)-1)) | I11: =IF(D11<2,FALSE,ISERROR(MATCH(H11,'Ontology and concepts per UC'!$A$2:$A$62,0))) -> FALSE | J11: =IF(D11<3,"",RIGHT(G11,LEN(G11)-FIND(";",G11)-1)) | K11: =IF(D11<3,FALSE,ISERROR(MATCH(J11,'Ontology and concepts per UC'!$A$2:$A$62,0))) -> FALSE | M11: hasDescription:"Retraso del desarrollo psicomotor"; | O11: FALSE | P11: 0 | Q11: 0 | R11: =NOT(ISERROR(SEARCH("hasSource",M11))) -> FALSE | S11: Manifestación: Retraso mental | T11: =IF(S11="","",VLOOKUP(S11,'Ontology and concepts per UC'!$F$2:$J$46,5,FALSE)) -> Modelo Conceptual | U11: {=(INDEX('Ontology and concepts per UC'!$G$2:$I$46,MATCH($S11,'Ontology and concepts per UC'!$F$2:$F$46,0),MATCH(LEFT($A11,3),'Ontology and concepts per UC'!$G$1:$I$1,0))=0)} -> FALSE | V11: =COUNTIF(W11:Z11,TRUE)>0 -> FALSE | W11: FALSE | X11: FALSE | Y11: FALSE | Z11: FALSE
A12: UC1-F1-P1-S1-M1 | B12: BTD_Manif_HearingLoss | C12: Manifestation | D12: =IF(ISBLANK(C12),0,LEN(C12)-LEN(SUBSTITUTE(C12,";",""))+1) -> 1 | E12: =IF(D12<2,C12,LEFT(C12,FIND(";",C12)-1)) -> Manifestation | F12: =IF(D12<1,FALSE,ISERROR(MATCH(E12,'Ontology and concepts per UC'!$A$2:$A$62,0))) -> FALSE | G12: =IF(D12<2,"",MID(C12,LEN(E12)+3,LEN(C12)-FIND(";",C12)-1)) | H12: =IF(D12<3,G12,LEFT(G12,FIND(";",G12)-1)) | I12: =IF(D12<2,FALSE,ISERROR(MATCH(H12,'Ontology and concepts per UC'!$A$2:$A$62,0))) -> FALSE | J12: =IF(D12<3,"",RIGHT(G12,LEN(G12)-FIND(";",G12)-1)) | K12: =IF(D12<3,FALSE,ISERROR(MATCH(J12,'Ontology and concepts per UC'!$A$2:$A$62,0))) -> FALSE | M12: hasDescription:"Pérdida auditiva neurosensorial"; | O12: FALSE | P12: 0 | Q12: 0 | R12: =NOT(ISERROR(SEARCH("hasSource",M12))) -> FALSE | S12: Manifestación: Problemas de audición | T12: =IF(S12="","",VLOOKUP(S12,'Ontology and concepts per UC'!$F$2:$J$46,5,FALSE)) -> Modelo Conceptual | U12: {=(INDEX('Ontology and concepts per UC'!$G$2:$I$46,MATCH($S12,'Ontology and concepts per UC'!$F$2:$F$46,0),MATCH(LEFT($A12,3),'Ontology and concepts per UC'!$G$1:$I$1,0))=0)} -> FALSE | V12: =COUNTIF(W12:Z12,TRUE)>0 -> FALSE | W12: FALSE | X12: FALSE | Y12: FALSE | Z12: FALSE
A13: UC1-F1-P1-S1-M1 | B13: BTD_Manif_Hypotonia | C13: Manifestation | D13: =IF(ISBLANK(C13),0,LEN(C13)-LEN(SUBSTITUTE(C13,";",""))+1) -> 1 | E13: =IF(D13<2,C13,LEFT(C13,FIND(";",C13)-1)) -> Manifestation | F13: =IF(D13<1,FALSE,ISERROR(MATCH(E13,'Ontology and concepts per UC'!$A$2:$A$62,0))) -> FALSE | G13: =IF(D13<2,"",MID(C13,LEN(E13)+3,LEN(C13)-FIND(";",C13)-1)) | H13: =IF(D13<3,G13,LEFT(G13,FIND(";",G13)-1)) | I13: =IF(D13<2,FALSE,ISERROR(MATCH(H13,'Ontology and concepts per UC'!$A$2:$A$62,0))) -> FALSE | J13: =IF(D13<3,"",RIGHT(G13,LEN(G13)-FIND(";",G13)-1)) | K13: =IF(D13<3,FALSE,ISERROR(MATCH(J13,'Ontology and concepts per UC'!$A$2:$A$62,0))) -> FALSE | M13: hasDescription:"Hipotonía muscular"; | O13: FALSE | P13: 0 | Q13: 0 | R13: =NOT(ISERROR(SEARCH("hasSource",M13))) -> FALSE | S13: Manifestación: Hipotonía | T13: =IF(S13="","",VLOOKUP(S13,'Ontology and concepts per UC'!$F$2:$J$46,5,FALSE)) -> Modelo Conceptual | U13: {=(INDEX('Ontology and concepts per UC'!$G$2:$I$46,MATCH($S13,'Ontology and concepts per UC'!$F$2:$F$46,0),MATCH(LEFT($A13,3),'Ontology and concepts per UC'!$G$1:$I$1,0))=0)} -> FALSE | V13: =COUNTIF(W13:Z13,TRUE)>0 -> FALSE | W13: FALSE | X13: FALSE | Y13: FALSE | Z13: FALSE
A14: UC1-F1-P1-S1-M1 | B14: BTD_Manif_OpticAtrophy | C14: Manifestation | D14: =IF(ISBLANK(C14),0,LEN(C14)-LEN(SUBSTITUTE(C14,";",""))+1) -> 1 | E14: =IF(D14<2,C14,LEFT(C14,FIND(";",C14)-1)) -> Manifestation | F14: =IF(D14<1,FALSE,ISERROR(MATCH(E14,'Ontology and concepts per UC'!$A$2:$A$62,0))) -> FALSE | G14: =IF(D14<2,"",MID(C14,LEN(E14)+3,LEN(C14)-FIND(";",C14)-1)) | H14: =IF(D14<3,G14,LEFT(G14,FIND(";",G14)-1)) | I14: =IF(D14<2,FALSE,ISERROR(MATCH(H14,'Ontology and concepts per UC'!$A$2:$A$62,0))) -> FALSE | J14: =IF(D14<3,"",RIGHT(G14,LEN(G14)-FIND(";",G14)-1)) | K14: =IF(D14<3,FALSE,ISERROR(MATCH(J14,'Ontology and concepts per UC'!$A$2:$A$62,0))) -> FALSE | M14: hasDescription:"Atrofia óptica"; | O14: FALSE | P14: 0 | Q14: 0 | R14: =NOT(ISERROR(SEARCH("hasSource",M14))) -> FALSE | S14: Manifestación: Pérdida de visión | T14: =IF(S14="","",VLOOKUP(S14,'Ontology and concepts per UC'!$F$2:$J$46,5,FALSE)) -> Modelo Conceptual | U14: {=(INDEX('Ontology and concepts per UC'!$G$2:$I$46,MATCH($S14,'Ontology and concepts per UC'!$F$2:$F$46,0),MATCH(LEFT($A14,3),'Ontology and concepts per UC'!$G$1:$I$1,0))=0)} -> FALSE | V14: =COUNTIF(W14:Z14,TRUE)>0 -> FALSE | W14: FALSE | X14: FALSE | Y14: FALSE | Z14: FALSE
A15: UC1-F1-P1-S1-M1 | B15: BTD_Manif_Seizures | C15: Manifestation | D15: =IF(ISBLANK(C15),0,LEN(C15)-LEN(SUBSTITUTE(C15,";",""))+1) -> 1 | E15: =IF(D15<2,C15,LEFT(C15,FIND(";",C15)-1)) -> Manifestation | F15: =IF(D15<1,FALSE,ISERROR(MATCH(E15,'Ontology and concepts per UC'!$A$2:$A$62,0))) -> FALSE | G15: =IF(D15<2,"",MID(C15,LEN(E15)+3,LEN(C15)-FIND(";",C15)-1)) | H15: =IF(D15<3,G15,LEFT(G15,FIND(";",G15)-1)) | I15: =IF(D15<2,FALSE,ISERROR(MATCH(H15,'Ontology and concepts per UC'!$A$2:$A$62,0))) -> FALSE | J15: =IF(D15<3,"",RIGHT(G15,LEN(G15)-FIND(";",G15)-1)) | K15: =IF(D15<3,FALSE,ISERROR(MATCH(J15,'Ontology and concepts per UC'!$A$2:$A$62,0))) -> FALSE | M15: hasDescription:"Convulsiones refractarias a tratamiento anticonvulsivo"; | O15: FALSE | P15: 0 | Q15: 0 | R15: =NOT(ISERROR(SEARCH("hasSource",M15))) -> FALSE | S15: Manifestación: Convulsiones | T15: =IF(S15="","",VLOOKUP(S15,'Ontology and concepts per UC'!$F$2:$J$46,5,FALSE)) -> Modelo Conceptual | U15: {=(INDEX('Ontology and concepts per UC'!$G$2:$I$46,MATCH($S15,'Ontology and concepts per UC'!$F$2:$F$46,0),MATCH(LEFT($A15,3),'Ontology and concepts per UC'!$G$1:$I$1,0))=0)} -> FALSE | V15: =COUNTIF(W15:Z15,TRUE)>0 -> FALSE | W15: FALSE | X15: FALSE | Y15: FALSE | Z15: FALSE
A16: UC1-F1-P1-S1-M1 | B16: BTD_Manif_SkinProblems | C16: Manifestation | D16: =IF(ISBLANK(C16),0,LEN(C16)-LEN(SUBSTITUTE(C16,";",""))+1) -> 1 | E16: =IF(D16<2,C16,LEFT(C16,FIND(";",C16)-1)) -> Manifestation | F16: =IF(D16<1,FALSE,ISERROR(MATCH(E16,'Ontology and concepts per UC'!$A$2:$A$62,0))) -> FALSE | G16: =IF(D16<2,"",MID(C16,LEN(E16)+3,LEN(C16)-FIND(";",C16)-1)) | H16: =IF(D16<3,G16,LEFT(G16,FIND(";",G16)-1)) | I16: =IF(D16<2,FALSE,ISERROR(MATCH(H16,'Ontology and concepts per UC'!$A$2:$A$62,0))) -> FALSE | J16: =IF(D16<3,"",RIGHT(G16,LEN(G16)-FIND(";",G16)-1)) | K16: =IF(D16<3,FALSE,ISERROR(MATCH(J16,'Ontology and concepts per UC'!$A$2:$A$62,0))) -> FALSE | M16: hasDescription:"Problemas cutáneos (erupciones, alopecia)"; | O16: FALSE | P16: 0 | Q16: 0 | R16: =NOT(ISERROR(SEARCH("hasSource",M16))) -> FALSE | S16: Manifestación: Problemas en la piel | T16: =IF(S16="","",VLOOKUP(S16,'Ontology and concepts per UC'!$F$2:$J$46,5,FALSE)) -> Modelo Conceptual | U16: {=(INDEX('Ontology and concepts per UC'!$G$2:$I$46,MATCH($S16,'Ontology and concepts per UC'!$F$2:$F$46,0),MATCH(LEFT($A16,3),'Ontology and concepts per UC'!$G$1:$I$1,0))=0)} -> FALSE | V16: =COUNTIF(W16:Z16,TRUE)>0 -> FALSE | W16: FALSE | X16: FALSE | Y16: FALSE | Z16: FALSE
A17: UC1-F1-P1-S1-M1 | B17: BTD_Manif_DevelopmentalDelay_Prob_LateTraeatment | C17: Parameter | D17: =IF(ISBLANK(C17),0,LEN(C17)-LEN(SUBSTITUTE(C17,";",""))+1) -> 1 | E17: =IF(D17<2,C17,LEFT(C17,FIND(";",C17)-1)) -> Parameter | F17: =IF(D17<1,FALSE,ISERROR(MATCH(E17,'Ontology and concepts per UC'!$A$2:$A$62,0))) -> FALSE | G17: =IF(D17<2,"",MID(C17,LEN(E17)+3,LEN(C17)-FIND(";",C17)-1)) | H17: =IF(D17<3,G17,LEFT(G17,FIND(";",G17)-1)) | I17: =IF(D17<2,FALSE,ISERROR(MATCH(H17,'Ontology and concepts per UC'!$A$2:$A$62,0))) -> FALSE | J17: =IF(D17<3,"",RIGHT(G17,LEN(G17)-FIND(";",G17)-1)) | K17: =IF(D17<3,FALSE,ISERROR(MATCH(J17,'Ontology and concepts per UC'!$A$2:$A$62,0))) -> FALSE | M17: hasSource:"Moslinger D et al. Clinical and neuropsychological outcome in 33 patients with biotinidase deficiency ascertained by nationwide newborn screening and family studies in Austria. Eur J Pediatr 2001;160:277-282"; hasDescription:"Probabilidad de retraso del desarrollo persistente con tratamiento tardío"; hasExpectedValue:"0.27"; | O17: FALSE | P17: 0 | Q17: 0 | R17: =NOT(ISERROR(SEARCH("hasSource",M17))) -> TRUE | S17: Riesgo: Retraso mental | T17: =IF(S17="","",VLOOKUP(S17,'Ontology and concepts per UC'!$F$2:$J$46,5,FALSE)) -> Parámetros de progresión | U17: {=(INDEX('Ontology and concepts per UC'!$G$2:$I$46,MATCH($S17,'Ontology and concepts per UC'!$F$2:$F$46,0),MATCH(LEFT($A17,3),'Ontology and concepts per UC'!$G$1:$I$1,0))=0)} -> FALSE | V17: =COUNTIF(W17:Z17,TRUE)>0 -> TRUE | W17: FALSE | X17: FALSE | Y17: FALSE | Z17: TRUE | AA17: Value not found in source
A18: UC1-F1-P1-S1-M1 | B18: BTD_Manif_DevelopmentalDelay_Prob_WithoutTreatment | C18: Parameter | D18: =IF(ISBLANK(C18),0,LEN(C18)-LEN(SUBSTITUTE(C18,";",""))+1) -> 1 | E18: =IF(D18<2,C18,LEFT(C18,FIND(";",C18)-1)) -> Parameter | F18: =IF(D18<1,FALSE,ISERROR(MATCH(E18,'Ontology and concepts per UC'!$A$2:$A$62,0))) -> FALSE | G18: =IF(D18<2,"",MID(C18,LEN(E18)+3,LEN(C18)-FIND(";",C18)-1)) | H18: =IF(D18<3,G18,LEFT(G18,FIND(";",G18)-1)) | I18: =IF(D18<2,FALSE,ISERROR(MATCH(H18,'Ontology and concepts per UC'!$A$2:$A$62,0))) -> FALSE | J18: =IF(D18<3,"",RIGHT(G18,LEN(G18)-FIND(";",G18)-1)) | K18: =IF(D18<3,FALSE,ISERROR(MATCH(J18,'Ontology and concepts per UC'!$A$2:$A$62,0))) -> FALSE | M18: hasDescription:"Probabilidad de desarrollar retraso del desarrollo sin tratamiento"; hasSource:"Moslinger D et al. Clinical and neuropsychological outcome in 33 patients with biotinidase deficiency ascertained by nationwide newborn screening and family studies in Austria. Eur J Pediatr 2001;160:277-282"; hasExpectedValue:"0.60"; | O18: FALSE | P18: 0 | Q18: 0 | R18: =NOT(ISERROR(SEARCH("hasSource",M18))) -> TRUE | S18: Riesgo: Retraso mental | T18: =IF(S18="","",VLOOKUP(S18,'Ontology and concepts per UC'!$F$2:$J$46,5,FALSE)) -> Parámetros de progresión | U18: {=(INDEX('Ontology and concepts per UC'!$G$2:$I$46,MATCH($S18,'Ontology and concepts per UC'!$F$2:$F$46,0),MATCH(LEFT($A18,3),'Ontology and concepts per UC'!$G$1:$I$1,0))=0)} -> FALSE | V18: =COUNTIF(W18:Z18,TRUE)>0 -> TRUE | W18: FALSE | X18: FALSE | Y18: FALSE | Z18: TRUE | AA18: Value not found in source
A19: UC1-F1-P1-S1-M1 | B19: BTD_Manif_HearingLoss_Prob_LateTraeatment | C19: Parameter | D19: =IF(ISBLANK(C19),0,LEN(C19)-LEN(SUBSTITUTE(C19,";",""))+1) -> 1 | E19: =IF(D19<2,C19,LEFT(C19,FIND(";",C19)-1)) -> Parameter | F19: =IF(D19<1,FALSE,ISERROR(MATCH(E19,'Ontology and concepts per UC'!$A$2:$A$62,0))) -> FALSE | G19: =IF(D19<2,"",MID(C19,LEN(E19)+3,LEN(C19)-FIND(";",C19)-1)) | H19: =IF(D19<3,G19,LEFT(G19,FIND(";",G19)-1)) | I19: =IF(D19<2,FALSE,ISERROR(MATCH(H19,'Ontology and concepts per UC'!$A$2:$A$62,0))) -> FALSE | J19: =IF(D19<3,"",RIGHT(G19,LEN(G19)-FIND(";",G19)-1)) | K19: =IF(D19<3,FALSE,ISERROR(MATCH(J19,'Ontology and concepts per UC'!$A$2:$A$62,0))) -> FALSE | M19: hasExpectedValue:"0.36"; hasDescription:"Probabilidad de pérdida auditiva persistente con tratamiento tardío"; hasSource:"Weber P et al. Outcome in patients with profound biotinidase deficiency: relevance of newborn screening. Dev Med Child Neurol 2004;46:481-4"; | O19: FALSE | P19: 0 | Q19: 0 | R19: =NOT(ISERROR(SEARCH("hasSource",M19))) -> TRUE | S19: Riesgo: Problemas de audición | T19: =IF(S19="","",VLOOKUP(S19,'Ontology and concepts per UC'!$F$2:$J$46,5,FALSE)) -> Parámetros de progresión | U19: {=(INDEX('Ontology and concepts per UC'!$G$2:$I$46,MATCH($S19,'Ontology and concepts per UC'!$F$2:$F$46,0),MATCH(LEFT($A19,3),'Ontology and concepts per UC'!$G$1:$I$1,0))=0)} -> FALSE | V19: =COUNTIF(W19:Z19,TRUE)>0 -> TRUE | W19: FALSE | X19: FALSE | Y19: FALSE | Z19: TRUE | AA19: Value not found in source
A20: UC1-F1-P1-S1-M1 | B20: BTD_Manif_HearingLoss_Prob_WithoutTreatment | C20: Parameter | D20: =IF(ISBLANK(C20),0,LEN(C20)-LEN(SUBSTITUTE(C20,";",""))+1) -> 1 | E20: =IF(D20<2,C20,LEFT(C20,FIND(";",C20)-1)) -> Parameter | F20: =IF(D20<1,FALSE,ISERROR(MATCH(E20,'Ontology and concepts per UC'!$A$2:$A$62,0))) -> FALSE | G20: =IF(D20<2,"",MID(C20,LEN(E20)+3,LEN(C20)-FIND(";",C20)-1)) | H20: =IF(D20<3,G20,LEFT(G20,FIND(";",G20)-1)) | I20: =IF(D20<2,FALSE,ISERROR(MATCH(H20,'Ontology and concepts per UC'!$A$2:$A$62,0))) -> FALSE | J20: =IF(D20<3,"",RIGHT(G20,LEN(G20)-FIND(";",G20)-1)) | K20: =IF(D20<3,FALSE,ISERROR(MATCH(J20,'Ontology and concepts per UC'!$A$2:$A$62,0))) -> FALSE | M20: hasDescription:"Probabilidad de desarrollar pérdida auditiva sin tratamiento"; hasExpectedValue:"0.55"; hasExpectedValue:"0.75"; hasSource:"Wolf B, Spencer R, Gleason T. Hearing loss is a common feature of symptomatic children with profound biotinidase deficiency. J Pediatr 2002;140:242-246"; hasSource:"Wolf B et al. Hearing loss is a common feature... J Pediatr 2002;140:242-246"; | O20: FALSE | P20: 0 | Q20: 0 | R20: =NOT(ISERROR(SEARCH("hasSource",M20))) -> TRUE | S20: Riesgo: Problemas de audición | T20: =IF(S20="","",VLOOKUP(S20,'Ontology and concepts per UC'!$F$2:$J$46,5,FALSE)) -> Parámetros de progresión | U20: {=(INDEX('Ontology and concepts per UC'!$G$2:$I$46,MATCH($S20,'Ontology and concepts per UC'!$F$2:$F$46,0),MATCH(LEFT($A20,3),'Ontology and concepts per UC'!$G$1:$I$1,0))=0)} -> FALSE | V20: =COUNTIF(W20:Z20,TRUE)>0 -> TRUE | W20: FALSE | X20: TRUE | Y20: FALSE | Z20: TRUE | AA20: Dataproperty used twice; one of them is incorrect
A21: UC1-F1-P1-S1-M1 | B21: BTD_Manif_OpticAtrophy_Prob_LateTraeatment | C21: Parameter | D21: =IF(ISBLANK(C21),0,LEN(C21)-LEN(SUBSTITUTE(C21,";",""))+1) -> 1 | E21: =IF(D21<2,C21,LEFT(C21,FIND(";",C21)-1)) -> Parameter | F21: =IF(D21<1,FALSE,ISERROR(MATCH(E21,'Ontology and concepts per UC'!$A$2:$A$62,0))) -> FALSE | G21: =IF(D21<2,"",MID(C21,LEN(E21)+3,LEN(C21)-FIND(";",C21)-1)) | H21: =IF(D21<3,G21,LEFT(G21,FIND(";",G21)-1)) | I21: =IF(D21<2,FALSE,ISERROR(MATCH(H21,'Ontology and concepts per UC'!$A$2:$A$62,0))) -> FALSE | J21: =IF(D21<3,"",RIGHT(G21,LEN(G21)-FIND(";",G21)-1)) | K21: =IF(D21<3,FALSE,ISERROR(MATCH(J21,'Ontology and concepts per UC'!$A$2:$A$62,0))) -> FALSE | M21: hasDescription:"Probabilidad de atrofia óptica persistente con tratamiento tardío"; hasSource:"Salbert BA, Astruc J, Wolf B. Ophthalmologic findings in biotinidase deficiency. Ophthalmologica 1993;206:177-181"; hasExpectedValue:"0.20"; | O21: FALSE | P21: 0 | Q21: 0 | R21: =NOT(ISERROR(SEARCH("hasSource",M21))) -> TRUE | S21: Riesgo: Pérdida de visión | T21: =IF(S21="","",VLOOKUP(S21,'Ontology and concepts per UC'!$F$2:$J$46,5,FALSE)) -> Parámetros de progresión | U21: {=(INDEX('Ontology and concepts per UC'!$G$2:$I$46,MATCH($S21,'Ontology and concepts per UC'!$F$2:$F$46,0),MATCH(LEFT($A21,3),'Ontology and concepts per UC'!$G$1:$I$1,0))=0)} -> FALSE | V21: =COUNTIF(W21:Z21,TRUE)>0 -> TRUE | W21: FALSE | X21: FALSE | Y21: FALSE | Z21: TRUE | AA21: Value not found in source
A22: UC1-F1-P1-S1-M1 | B22: BTD_Manif_OpticAtrophy_Prob_WithoutTreatment | C22: Parameter | D22: =IF(ISBLANK(C22),0,LEN(C22)-LEN(SUBSTITUTE(C22,";",""))+1) -> 1 | E22: =IF(D22<2,C22,LEFT(C22,FIND(";",C22)-1)) -> Parameter | F22: =IF(D22<1,FALSE,ISERROR(MATCH(E22,'Ontology and concepts per UC'!$A$2:$A$62,0))) -> FALSE | G22: =IF(D22<2,"",MID(C22,LEN(E22)+3,LEN(C22)-FIND(";",C22)-1)) | H22: =IF(D22<3,G22,LEFT(G22,FIND(";",G22)-1)) | I22: =IF(D22<2,FALSE,ISERROR(MATCH(H22,'Ontology and concepts per UC'!$A$2:$A$62,0))) -> FALSE | J22: =IF(D22<3,"",RIGHT(G22,LEN(G22)-FIND(";",G22)-1)) | K22: =IF(D22<3,FALSE,ISERROR(MATCH(J22,'Ontology and concepts per UC'!$A$2:$A$62,0))) -> FALSE | M22: hasDescription:"Probabilidad de desarrollar atrofia óptica sin tratamiento"; hasExpectedValue:"0.30"; hasSource:"Salbert BA, Astruc J, Wolf B. Ophthalmologic findings in biotinidase deficiency. Ophthalmologica 1993;206:177-181"; | O22: FALSE | P22: 0 | Q22: 0 | R22: =NOT(ISERROR(SEARCH("hasSource",M22))) -> TRUE | S22: Riesgo: Pérdida de visión | T22: =IF(S22="","",VLOOKUP(S22,'Ontology and concepts per UC'!$F$2:$J$46,5,FALSE)) -> Parámetros de progresión | U22: {=(INDEX('Ontology and concepts per UC'!$G$2:$I$46,MATCH($S22,'Ontology and concepts per UC'!$F$2:$F$46,0),MATCH(LEFT($A22,3),'Ontology and concepts per UC'!$G$1:$I$1,0))=0)} -> FALSE | V22: =COUNTIF(W22:Z22,TRUE)>0 -> TRUE | W22: FALSE | X22: FALSE | Y22: FALSE | Z22: TRUE | AA22: Value not found in source
A23: UC1-F1-P1-S1-M1 | B23: BTD_Manif_Seizures_Prob_WithoutTreatment | C23: Parameter | D23: =IF(ISBLANK(C23),0,LEN(C23)-LEN(SUBSTITUTE(C23,";",""))+1) -> 1 | E23: =IF(D23<2,C23,LEFT(C23,FIND(";",C23)-1)) -> Parameter | F23: =IF(D23<1,FALSE,ISERROR(MATCH(E23,'Ontology and concepts per UC'!$A$2:$A$62,0))) -> FALSE | G23: =IF(D23<2,"",MID(C23,LEN(E23)+3,LEN(C23)-FIND(";",C23)-1)) | H23: =IF(D23<3,G23,LEFT(G23,FIND(";",G23)-1)) | I23: =IF(D23<2,FALSE,ISERROR(MATCH(H23,'Ontology and concepts per UC'!$A$2:$A$62,0))) -> FALSE | J23: =IF(D23<3,"",RIGHT(G23,LEN(G23)-FIND(";",G23)-1)) | K23: =IF(D23<3,FALSE,ISERROR(MATCH(J23,'Ontology and concepts per UC'!$A$2:$A$62,0))) -> FALSE | M23: hasExpectedValue:"0.70"; hasSource:"Weber P et al. Outcome in patients with profound biotinidase deficiency: relevance of newborn screening. Dev Med Child Neurol 2004;46:481-4"; hasDescription:"Probabilidad de desarrollar convulsiones sin tratamiento"; | O23: FALSE | P23: 0 | Q23: 0 | R23: =NOT(ISERROR(SEARCH("hasSource",M23))) -> TRUE | S23: Riesgo: Convulsiones | T23: =IF(S23="","",VLOOKUP(S23,'Ontology and concepts per UC'!$F$2:$J$46,5,FALSE)) -> Parámetros de progresión | U23: {=(INDEX('Ontology and concepts per UC'!$G$2:$I$46,MATCH($S23,'Ontology and concepts per UC'!$F$2:$F$46,0),MATCH(LEFT($A23,3),'Ontology and concepts per UC'!$G$1:$I$1,0))=0)} -> FALSE | V23: =COUNTIF(W23:Z23,TRUE)>0 -> TRUE | W23: FALSE | X23: FALSE | Y23: FALSE | Z23: TRUE | AA23: Value not found in source
A24: UC1-F1-P1-S1-M1 | B24: BTD_Screening_Specificity | C24: Parameter | D24: =IF(ISBLANK(C24),0,LEN(C24)-LEN(SUBSTITUTE(C24,";",""))+1) -> 1 | E24: =IF(D24<2,C24,LEFT(C24,FIND(";",C24)-1)) -> Parameter | F24: =IF(D24<1,FALSE,ISERROR(MATCH(E24,'Ontology and concepts per UC'!$A$2:$A$62,0))) -> FALSE | G24: =IF(D24<2,"",MID(C24,LEN(E24)+3,LEN(C24)-FIND(";",C24)-1)) | H24: =IF(D24<3,G24,LEFT(G24,FIND(";",G24)-1)) | I24: =IF(D24<2,FALSE,ISERROR(MATCH(H24,'Ontology and concepts per UC'!$A$2:$A$62,0))) -> FALSE | J24: =IF(D24<3,"",RIGHT(G24,LEN(G24)-FIND(";",G24)-1)) | K24: =IF(D24<3,FALSE,ISERROR(MATCH(J24,'Ontology and concepts per UC'!$A$2:$A$62,0))) -> FALSE | M24: hasExpectedValue:"0.998"; hasDescription:"Especificidad del cribado neonatal para la deficiencia de biotinidasa"; | O24: FALSE | P24: 0 | Q24: 0 | R24: =NOT(ISERROR(SEARCH("hasSource",M24))) -> FALSE | S24: Especificidad | T24: =IF(S24="","",VLOOKUP(S24,'Ontology and concepts per UC'!$F$2:$J$46,5,FALSE)) -> Parámetros de intervención | U24: {=(INDEX('Ontology and concepts per UC'!$G$2:$I$46,MATCH($S24,'Ontology and concepts per UC'!$F$2:$F$46,0),MATCH(LEFT($A24,3),'Ontology and concepts per UC'!$G$1:$I$1,0))=0)} -> FALSE | V24: =COUNTIF(W24:Z24,TRUE)>0 -> FALSE | W24: FALSE | X24: FALSE | Y24: FALSE | Z24: FALSE
A25: UC1-F1-P1-S1-M1 | B25: BTD_Screening_Sensitivity | C25: Parameter; DeterministicParameter | D25: =IF(ISBLANK(C25),0,LEN(C25)-LEN(SUBSTITUTE(C25,";",""))+1) -> 2 | E25: =IF(D25<2,C25,LEFT(C25,FIND(";",C25)-1)) -> Parameter | F25: =IF(D25<1,FALSE,ISERROR(MATCH(E25,'Ontology and concepts per UC'!$A$2:$A$62,0))) -> FALSE | G25: =IF(D25<2,"",MID(C25,LEN(E25)+3,LEN(C25)-FIND(";",C25)-1)) -> DeterministicParameter | H25: =IF(D25<3,G25,LEFT(G25,FIND(";",G25)-1)) -> DeterministicParameter | I25: =IF(D25<2,FALSE,ISERROR(MATCH(H25,'Ontology and concepts per UC'!$A$2:$A$62,0))) -> FALSE | J25: =IF(D25<3,"",RIGHT(G25,LEN(G25)-FIND(";",G25)-1)) | K25: =IF(D25<3,FALSE,ISERROR(MATCH(J25,'Ontology and concepts per UC'!$A$2:$A$62,0))) -> FALSE | M25: hasExpectedValue:"0.99"; hasDescription:"Sensibilidad del cribado neonatal para la deficiencia de biotinidasa"; | O25: FALSE | P25: 0 | Q25: 0 | R25: =NOT(ISERROR(SEARCH("hasSource",M25))) -> FALSE | S25: Caracterización cribado | T25: =IF(S25="","",VLOOKUP(S25,'Ontology and concepts per UC'!$F$2:$J$46,5,FALSE)) -> Parámetros de intervención | U25: {=(INDEX('Ontology and concepts per UC'!$G$2:$I$46,MATCH($S25,'Ontology and concepts per UC'!$F$2:$F$46,0),MATCH(LEFT($A25,3),'Ontology and concepts per UC'!$G$1:$I$1,0))=0)} -> FALSE | V25: =COUNTIF(W25:Z25,TRUE)>0 -> FALSE | W25: FALSE | X25: FALSE | Y25: FALSE | Z25: FALSE
A26: UC1-F1-P1-S1-M1 | B26: BTD_Population_Newborns_ES | C26: Population | D26: =IF(ISBLANK(C26),0,LEN(C26)-LEN(SUBSTITUTE(C26,";",""))+1) -> 1 | E26: =IF(D26<2,C26,LEFT(C26,FIND(";",C26)-1)) -> Population | F26: =IF(D26<1,FALSE,ISERROR(MATCH(E26,'Ontology and concepts per UC'!$A$2:$A$62,0))) -> FALSE | G26: =IF(D26<2,"",MID(C26,LEN(E26)+3,LEN(C26)-FIND(";",C26)-1)) | H26: =IF(D26<3,G26,LEFT(G26,FIND(";",G26)-1)) | I26: =IF(D26<2,FALSE,ISERROR(MATCH(H26,'Ontology and concepts per UC'!$A$2:$A$62,0))) -> FALSE | J26: =IF(D26<3,"",RIGHT(G26,LEN(G26)-FIND(";",G26)-1)) | K26: =IF(D26<3,FALSE,ISERROR(MATCH(J26,'Ontology and concepts per UC'!$A$2:$A$62,0))) -> FALSE | L26: hasSubpopulation:GeneralPopulation; | M26: hasDescription:"Recién nacidos en España durante un año natural"; hasMaxAge:"1"; hasMinAge:"0"; hasGeographicalContext:"España"; | O26: FALSE | P26: 0 | Q26: 0 | R26: =NOT(ISERROR(SEARCH("hasSource",M26))) -> FALSE | S26: Población | T26: =IF(S26="","",VLOOKUP(S26,'Ontology and concepts per UC'!$F$2:$J$46,5,FALSE)) -> Modelo Conceptual | U26: {=(INDEX('Ontology and concepts per UC'!$G$2:$I$46,MATCH($S26,'Ontology and concepts per UC'!$F$2:$F$46,0),MATCH(LEFT($A26,3),'Ontology and concepts per UC'!$G$1:$I$1,0))=0)} -> FALSE | V26: =COUNTIF(W26:Z26,TRUE)>0 -> TRUE | W26: TRUE | X26: FALSE | Y26: FALSE | Z26: FALSE | AA26: Makes reference to an undefined individual
A27: UC1-F1-P1-S1-M1 | B27: BTD_Disease | C27: RareDisease; Disease | D27: =IF(ISBLANK(C27),0,LEN(C27)-LEN(SUBSTITUTE(C27,";",""))+1) -> 2 | E27: =IF(D27<2,C27,LEFT(C27,FIND(";",C27)-1)) -> RareDisease | F27: =IF(D27<1,FALSE,ISERROR(MATCH(E27,'Ontology and concepts per UC'!$A$2:$A$62,0))) -> FALSE | G27: =IF(D27<2,"",MID(C27,LEN(E27)+3,LEN(C27)-FIND(";",C27)-1)) -> Disease | H27: =IF(D27<3,G27,LEFT(G27,FIND(";",G27)-1)) -> Disease | I27: =IF(D27<2,FALSE,ISERROR(MATCH(H27,'Ontology and concepts per UC'!$A$2:$A$62,0))) -> FALSE | J27: =IF(D27<3,"",RIGHT(G27,LEN(G27)-FIND(";",G27)-1)) | K27: =IF(D27<3,FALSE,ISERROR(MATCH(J27,'Ontology and concepts per UC'!$A$2:$A$62,0))) -> FALSE | L27: hasFollowUpStrategy:BTD_FollowUp_AnnualMonitoring; hasDisutilityCombinationMethod:AdditiveDisutility; hasEpidemiologicalParameter:BTD_Incidence; | M27: hasDescription:"Deficiencia de biotinidasa"; hasSource:"Wolf B. Disorders of biotin metabolism. In: Scriver CR et al., eds. The metabolic and molecular bases of inherited disease, 7th ed. 2001"; | O27: FALSE | P27: 0 | Q27: 1 | R27: =NOT(ISERROR(SEARCH("hasSource",M27))) -> TRUE | S27: Enfermedad | T27: =IF(S27="","",VLOOKUP(S27,'Ontology and concepts per UC'!$F$2:$J$46,5,FALSE)) -> Modelo Conceptual | U27: {=(INDEX('Ontology and concepts per UC'!$G$2:$I$46,MATCH($S27,'Ontology and concepts per UC'!$F$2:$F$46,0),MATCH(LEFT($A27,3),'Ontology and concepts per UC'!$G$1:$I$1,0))=0)} -> FALSE | V27: =COUNTIF(W27:Z27,TRUE)>0 -> TRUE | W27: TRUE | X27: FALSE | Y27: FALSE | Z27: FALSE | AA27: ObjectProp 'hasDisutilityCombinationMethod' undefined
A28: UC1-F1-P1-S1-M1 | B28: BTD_Incidence | C28: SecondOrderUncertaintyParameter; EpidemiologicalParameter | D28: =IF(ISBLANK(C28),0,LEN(C28)-LEN(SUBSTITUTE(C28,";",""))+1) -> 2 | E28: =IF(D28<2,C28,LEFT(C28,FIND(";",C28)-1)) -> SecondOrderUncertaintyParameter | F28: =IF(D28<1,FALSE,ISERROR(MATCH(E28,'Ontology and concepts per UC'!$A$2:$A$62,0))) -> FALSE | G28: =IF(D28<2,"",MID(C28,LEN(E28)+3,LEN(C28)-FIND(";",C28)-1)) -> EpidemiologicalParameter | H28: =IF(D28<3,G28,LEFT(G28,FIND(";",G28)-1)) -> EpidemiologicalParameter | I28: =IF(D28<2,FALSE,ISERROR(MATCH(H28,'Ontology and concepts per UC'!$A$2:$A$62,0))) -> FALSE | J28: =IF(D28<3,"",RIGHT(G28,LEN(G28)-FIND(";",G28)-1)) | K28: =IF(D28<3,FALSE,ISERROR(MATCH(J28,'Ontology and concepts per UC'!$A$2:$A$62,0))) -> FALSE | M28: hasDescription:"Incidencia de la deficiencia profunda de biotinidasa"; hasSource:"Wolf B. Worldwide survey of neonatal screening for biotinidase deficiency. J Inherit Metab Dis 1991;14:923-927"; hasExpectedValue:"0.0000125"; | O28: FALSE | P28: 0 | Q28: 0 | R28: =NOT(ISERROR(SEARCH("hasSource",M28))) -> TRUE | S28: Prevalencia al nacimiento | T28: =IF(S28="","",VLOOKUP(S28,'Ontology and concepts per UC'!$F$2:$J$46,5,FALSE)) -> Parámetro epidemiológico | U28: {=(INDEX('Ontology and concepts per UC'!$G$2:$I$46,MATCH($S28,'Ontology and concepts per UC'!$F$2:$F$46,0),MATCH(LEFT($A28,3),'Ontology and concepts per UC'!$G$1:$I$1,0))=0)} -> FALSE | V28: =COUNTIF(W28:Z28,TRUE)>0 -> FALSE | W28: FALSE | X28: FALSE | Y28: FALSE | Z28: FALSE
A29: UC1-F1-P1-S1-M1 | B29: BTD_Manif_Combined_U | C29: UtilityParameter | D29: =IF(ISBLANK(C29),0,LEN(C29)-LEN(SUBSTITUTE(C29,";",""))+1) -> 1 | E29: =IF(D29<2,C29,LEFT(C29,FIND(";",C29)-1)) -> UtilityParameter | F29: =IF(D29<1,FALSE,ISERROR(MATCH(E29,'Ontology and concepts per UC'!$A$2:$A$62,0))) -> TRUE | G29: =IF(D29<2,"",MID(C29,LEN(E29)+3,LEN(C29)-FIND(";",C29)-1)) | H29: =IF(D29<3,G29,LEFT(G29,FIND(";",G29)-1)) | I29: =IF(D29<2,FALSE,ISERROR(MATCH(H29,'Ontology and concepts per UC'!$A$2:$A$62,0))) -> FALSE | J29: =IF(D29<3,"",RIGHT(G29,LEN(G29)-FIND(";",G29)-1)) | K29: =IF(D29<3,FALSE,ISERROR(MATCH(J29,'Ontology and concepts per UC'!$A$2:$A$62,0))) -> FALSE | M29: hasDescription:"Desutilidad anual para casos graves con múltiples síntomas"; appliesOneTime:"false"; hasExpectedValue:"0.49"; | O29: FALSE | P29: 1 | Q29: 0 | R29: =NOT(ISERROR(SEARCH("hasSource",M29))) -> FALSE | S29: Utilidad: Otras | T29: =IF(S29="","",VLOOKUP(S29,'Ontology and concepts per UC'!$F$2:$J$46,5,FALSE)) -> Utilidad | U29: {=(INDEX('Ontology and concepts per UC'!$G$2:$I$46,MATCH($S29,'Ontology and concepts per UC'!$F$2:$F$46,0),MATCH(LEFT($A29,3),'Ontology and concepts per UC'!$G$1:$I$1,0))=0)} -> FALSE | V29: =COUNTIF(W29:Z29,TRUE)>0 -> TRUE | W29: TRUE | X29: FALSE | Y29: FALSE | Z29: FALSE | AA29: Class 'UtilityParameter' undefined
A30: UC1-F1-P1-S1-M1 | B30: BTD_Manif_DevelopmentalDelay_U | C30: UtilityParameter | D30: =IF(ISBLANK(C30),0,LEN(C30)-LEN(SUBSTITUTE(C30,";",""))+1) -> 1 | E30: =IF(D30<2,C30,LEFT(C30,FIND(";",C30)-1)) -> UtilityParameter | F30: =IF(D30<1,FALSE,ISERROR(MATCH(E30,'Ontology and concepts per UC'!$A$2:$A$62,0))) -> TRUE | G30: =IF(D30<2,"",MID(C30,LEN(E30)+3,LEN(C30)-FIND(";",C30)-1)) | H30: =IF(D30<3,G30,LEFT(G30,FIND(";",G30)-1)) | I30: =IF(D30<2,FALSE,ISERROR(MATCH(H30,'Ontology and concepts per UC'!$A$2:$A$62,0))) -> FALSE | J30: =IF(D30<3,"",RIGHT(G30,LEN(G30)-FIND(";",G30)-1)) | K30: =IF(D30<3,FALSE,ISERROR(MATCH(J30,'Ontology and concepts per UC'!$A$2:$A$62,0))) -> FALSE | M30: hasExpectedValue:"0.29"; appliesOneTime:"false"; hasDescription:"Desutilidad anual asociada a retraso del desarrollo"; | O30: FALSE | P30: 1 | Q30: 0 | R30: =NOT(ISERROR(SEARCH("hasSource",M30))) -> FALSE | S30: Utilidad: Retraso mental | T30: =IF(S30="","",VLOOKUP(S30,'Ontology and concepts per UC'!$F$2:$J$46,5,FALSE)) -> Utilidad | U30: {=(INDEX('Ontology and concepts per UC'!$G$2:$I$46,MATCH($S30,'Ontology and concepts per UC'!$F$2:$F$46,0),MATCH(LEFT($A30,3),'Ontology and concepts per UC'!$G$1:$I$1,0))=0)} -> FALSE | V30: =COUNTIF(W30:Z30,TRUE)>0 -> TRUE | W30: TRUE | X30: FALSE | Y30: FALSE | Z30: FALSE | AA30: Class 'UtilityParameter' undefined
A31: UC1-F1-P1-S1-M1 | B31: BTD_Manif_HearingLoss_U | C31: UtilityParameter | D31: =IF(ISBLANK(C31),0,LEN(C31)-LEN(SUBSTITUTE(C31,";",""))+1) -> 1 | E31: =IF(D31<2,C31,LEFT(C31,FIND(";",C31)-1)) -> UtilityParameter | F31: =IF(D31<1,FALSE,ISERROR(MATCH(E31,'Ontology and concepts per UC'!$A$2:$A$62,0))) -> TRUE | G31: =IF(D31<2,"",MID(C31,LEN(E31)+3,LEN(C31)-FIND(";",C31)-1)) | H31: =IF(D31<3,G31,LEFT(G31,FIND(";",G31)-1)) | I31: =IF(D31<2,FALSE,ISERROR(MATCH(H31,'Ontology and concepts per UC'!$A$2:$A$62,0))) -> FALSE | J31: =IF(D31<3,"",RIGHT(G31,LEN(G31)-FIND(";",G31)-1)) | K31: =IF(D31<3,FALSE,ISERROR(MATCH(J31,'Ontology and concepts per UC'!$A$2:$A$62,0))) -> FALSE | M31: hasExpectedValue:"0.18"; hasDescription:"Desutilidad anual asociada a pérdida auditiva neurosensorial"; appliesOneTime:"false"; | O31: FALSE | P31: 1 | Q31: 0 | R31: =NOT(ISERROR(SEARCH("hasSource",M31))) -> FALSE | S31: Utilidad: Problemas de audición | T31: =IF(S31="","",VLOOKUP(S31,'Ontology and concepts per UC'!$F$2:$J$46,5,FALSE)) -> Utilidad | U31: {=(INDEX('Ontology and concepts per UC'!$G$2:$I$46,MATCH($S31,'Ontology and concepts per UC'!$F$2:$F$46,0),MATCH(LEFT($A31,3),'Ontology and concepts per UC'!$G$1:$I$1,0))=0)} -> FALSE | V31: =COUNTIF(W31:Z31,TRUE)>0 -> TRUE | W31: TRUE | X31: FALSE | Y31: FALSE | Z31: FALSE | AA31: Class 'UtilityParameter' undefined
A32: UC1-F1-P1-S1-M1 | B32: BTD_Manif_OpticAtrophy_U | C32: UtilityParameter | D32: =IF(ISBLANK(C32),0,LEN(C32)-LEN(SUBSTITUTE(C32,";",""))+1) -> 1 | E32: =IF(D32<2,C32,LEFT(C32,FIND(";",C32)-1)) -> UtilityParameter | F32: =IF(D32<1,FALSE,ISERROR(MATCH(E32,'Ontology and concepts per UC'!$A$2:$A$62,0))) -> TRUE | G32: =IF(D32<2,"",MID(C32,LEN(E32)+3,LEN(C32)-FIND(";",C32)-1)) | H32: =IF(D32<3,G32,LEFT(G32,FIND(";",G32)-1)) | I32: =IF(D32<2,FALSE,ISERROR(MATCH(H32,'Ontology and concepts per UC'!$A$2:$A$62,0))) -> FALSE | J32: =IF(D32<3,"",RIGHT(G32,LEN(G32)-FIND(";",G32)-1)) | K32: =IF(D32<3,FALSE,ISERROR(MATCH(J32,'Ontology and concepts per UC'!$A$2:$A$62,0))) -> FALSE | M32: hasExpectedValue:"0.23"; hasDescription:"Desutilidad anual asociada a atrofia óptica"; appliesOneTime:"false"; | O32: FALSE | P32: 1 | Q32: 0 | R32: =NOT(ISERROR(SEARCH("hasSource",M32))) -> FALSE | S32: Utilidad: Pérdida de visión | T32: =IF(S32="","",VLOOKUP(S32,'Ontology and concepts per UC'!$F$2:$J$46,5,FALSE)) -> Utilidad | U32: {=(INDEX('Ontology and concepts per UC'!$G$2:$I$46,MATCH($S32,'Ontology and concepts per UC'!$F$2:$F$46,0),MATCH(LEFT($A32,3),'Ontology and concepts per UC'!$G$1:$I$1,0))=0)} -> FALSE | V32: =COUNTIF(W32:Z32,TRUE)>0 -> TRUE | W32: TRUE | X32: FALSE | Y32: FALSE | Z32: FALSE | AA32: Class 'UtilityParameter' undefined
A33: UC1-F1-P1-S1-M1 | B33: BTD_Manif_Seizures_U | C33: UtilityParameter | D33: =IF(ISBLANK(C33),0,LEN(C33)-LEN(SUBSTITUTE(C33,";",""))+1) -> 1 | E33: =IF(D33<2,C33,LEFT(C33,FIND(";",C33)-1)) -> UtilityParameter | F33: =IF(D33<1,FALSE,ISERROR(MATCH(E33,'Ontology and concepts per UC'!$A$2:$A$62,0))) -> TRUE | G33: =IF(D33<2,"",MID(C33,LEN(E33)+3,LEN(C33)-FIND(";",C33)-1)) | H33: =IF(D33<3,G33,LEFT(G33,FIND(";",G33)-1)) | I33: =IF(D33<2,FALSE,ISERROR(MATCH(H33,'Ontology and concepts per UC'!$A$2:$A$62,0))) -> FALSE | J33: =IF(D33<3,"",RIGHT(G33,LEN(G33)-FIND(";",G33)-1)) | K33: =IF(D33<3,FALSE,ISERROR(MATCH(J33,'Ontology and concepts per UC'!$A$2:$A$62,0))) -> FALSE | M33: hasDescription:"Desutilidad anual asociada a convulsiones refractarias"; appliesOneTime:"false"; hasExpectedValue:"0.32"; | O33: FALSE | P33: 1 | Q33: 0 | R33: =NOT(ISERROR(SEARCH("hasSource",M33))) -> FALSE | S33: Utilidad: Convulsiones | T33: =IF(S33="","",VLOOKUP(S33,'Ontology and concepts per UC'!$F$2:$J$46,5,FALSE)) -> Utilidad | U33: {=(INDEX('Ontology and concepts per UC'!$G$2:$I$46,MATCH($S33,'Ontology and concepts per UC'!$F$2:$F$46,0),MATCH(LEFT($A33,3),'Ontology and concepts per UC'!$G$1:$I$1,0))=0)} -> FALSE | V33: =COUNTIF(W33:Z33,TRUE)>0 -> TRUE | W33: TRUE | X33: FALSE | Y33: FALSE | Z33: FALSE | AA33: Class 'UtilityParameter' undefined
A34: UC1-F1-P1-S1-M1 | B34: BTD_Normal_U | C34: UtilityParameter | D34: =IF(ISBLANK(C34),0,LEN(C34)-LEN(SUBSTITUTE(C34,";",""))+1) -> 1 | E34: =IF(D34<2,C34,LEFT(C34,FIND(";",C34)-1)) -> UtilityParameter | F34: =IF(D34<1,FALSE,ISERROR(MATCH(E34,'Ontology and concepts per UC'!$A$2:$A$62,0))) -> TRUE | G34: =IF(D34<2,"",MID(C34,LEN(E34)+3,LEN(C34)-FIND(";",C34)-1)) | H34: =IF(D34<3,G34,LEFT(G34,FIND(";",G34)-1)) | I34: =IF(D34<2,FALSE,ISERROR(MATCH(H34,'Ontology and concepts per UC'!$A$2:$A$62,0))) -> FALSE | J34: =IF(D34<3,"",RIGHT(G34,LEN(G34)-FIND(";",G34)-1)) | K34: =IF(D34<3,FALSE,ISERROR(MATCH(J34,'Ontology and concepts per UC'!$A$2:$A$62,0))) -> FALSE | M34: hasDescription:"Utilidad de vida normal sin síntomas"; hasExpectedValue:"1.0"; | O34: FALSE | P34: 1 | Q34: 0 | R34: =NOT(ISERROR(SEARCH("hasSource",M34))) -> FALSE | S34: Población: utilidad | T34: =IF(S34="","",VLOOKUP(S34,'Ontology and concepts per UC'!$F$2:$J$46,5,FALSE)) -> Modelo Conceptual | U34: {=(INDEX('Ontology and concepts per UC'!$G$2:$I$46,MATCH($S34,'Ontology and concepts per UC'!$F$2:$F$46,0),MATCH(LEFT($A34,3),'Ontology and concepts per UC'!$G$1:$I$1,0))=0)} -> FALSE | V34: =COUNTIF(W34:Z34,TRUE)>0 -> TRUE | W34: TRUE | X34: FALSE | Y34: FALSE | Z34: FALSE | AA34: Class 'UtilityParameter' undefined
A35: UC1-F1-P1-S1-M1 | B35: AdditiveDisutility | D35: =IF(ISBLANK(C35),0,LEN(C35)-LEN(SUBSTITUTE(C35,";",""))+1) -> 0 | E35: =IF(D35<2,C35,LEFT(C35,FIND(";",C35)-1)) -> 0 | F35: =IF(D35<1,FALSE,ISERROR(MATCH(E35,'Ontology and concepts per UC'!$A$2:$A$62,0))) -> FALSE | G35: =IF(D35<2,"",MID(C35,LEN(E35)+3,LEN(C35)-FIND(";",C35)-1)) | H35: =IF(D35<3,G35,LEFT(G35,FIND(";",G35)-1)) | I35: =IF(D35<2,FALSE,ISERROR(MATCH(H35,'Ontology and concepts per UC'!$A$2:$A$62,0))) -> FALSE | J35: =IF(D35<3,"",RIGHT(G35,LEN(G35)-FIND(";",G35)-1)) | K35: =IF(D35<3,FALSE,ISERROR(MATCH(J35,'Ontology and concepts per UC'!$A$2:$A$62,0))) -> FALSE | O35: TRUE | P35: 0 | Q35: 0 | R35: =NOT(ISERROR(SEARCH("hasSource",M35))) -> FALSE | S35: Otros | T35: =IF(S35="","",VLOOKUP(S35,'Ontology and concepts per UC'!$F$2:$J$46,5,FALSE)) -> Otros | U35: {=(INDEX('Ontology and concepts per UC'!$G$2:$I$46,MATCH($S35,'Ontology and concepts per UC'!$F$2:$F$46,0),MATCH(LEFT($A35,3),'Ontology and concepts per UC'!$G$1:$I$1,0))=0)} -> TRUE | V35: =COUNTIF(W35:Z35,TRUE)>0 -> TRUE | W35: TRUE | X35: FALSE | Y35: FALSE | Z35: FALSE | AA35: No Class assigned
A36: UC1-F1-P1-S1-M1 | B36: GeneralPopulation | D36: =IF(ISBLANK(C36),0,LEN(C36)-LEN(SUBSTITUTE(C36,";",""))+1) -> 0 | E36: =IF(D36<2,C36,LEFT(C36,FIND(";",C36)-1)) -> 0 | F36: =IF(D36<1,FALSE,ISERROR(MATCH(E36,'Ontology and concepts per UC'!$A$2:$A$62,0))) -> FALSE | G36: =IF(D36<2,"",MID(C36,LEN(E36)+3,LEN(C36)-FIND(";",C36)-1)) | H36: =IF(D36<3,G36,LEFT(G36,FIND(";",G36)-1)) | I36: =IF(D36<2,FALSE,ISERROR(MATCH(H36,'Ontology and concepts per UC'!$A$2:$A$62,0))) -> FALSE | J36: =IF(D36<3,"",RIGHT(G36,LEN(G36)-FIND(";",G36)-1)) | K36: =IF(D36<3,FALSE,ISERROR(MATCH(J36,'Ontology and concepts per UC'!$A$2:$A$62,0))) -> FALSE | O36: TRUE | P36: 0 | Q36: 0 | R36: =NOT(ISERROR(SEARCH("hasSource",M36))) -> FALSE | S36: Población | T36: =IF(S36="","",VLOOKUP(S36,'Ontology and concepts per UC'!$F$2:$J$46,5,FALSE)) -> Modelo Conceptual | U36: {=(INDEX('Ontology and concepts per UC'!$G$2:$I$46,MATCH($S36,'Ontology and concepts per UC'!$F$2:$F$46,0),MATCH(LEFT($A36,3),'Ontology and concepts per UC'!$G$1:$I$1,0))=0)} -> FALSE | V36: =COUNTIF(W36:Z36,TRUE)>0 -> TRUE | W36: TRUE | X36: FALSE | Y36: FALSE | Z36: FALSE | AA36: No Class assigned
A37: UC1-F1-P1-S2-M1 | B37: Manif_Convulsiones | C37: AcuteManifestation | D37: =IF(ISBLANK(C37),0,LEN(C37)-LEN(SUBSTITUTE(C37,";",""))+1) -> 1 | E37: =IF(D37<2,C37,LEFT(C37,FIND(";",C37)-1)) -> AcuteManifestation | F37: =IF(D37<1,FALSE,ISERROR(MATCH(E37,'Ontology and concepts per UC'!$A$2:$A$62,0))) -> FALSE | G37: =IF(D37<2,"",MID(C37,LEN(E37)+3,LEN(C37)-FIND(";",C37)-1)) | H37: =IF(D37<3,G37,LEFT(G37,FIND(";",G37)-1)) | I37: =IF(D37<2,FALSE,ISERROR(MATCH(H37,'Ontology and concepts per UC'!$A$2:$A$62,0))) -> FALSE | J37: =IF(D37<3,"",RIGHT(G37,LEN(G37)-FIND(";",G37)-1)) | K37: =IF(D37<3,FALSE,ISERROR(MATCH(J37,'Ontology and concepts per UC'!$A$2:$A$62,0))) -> FALSE | O37: FALSE | P37: 0 | Q37: 0 | R37: =NOT(ISERROR(SEARCH("hasSource",M37))) -> FALSE | S37: Manifestación: Convulsiones | T37: =IF(S37="","",VLOOKUP(S37,'Ontology and concepts per UC'!$F$2:$J$46,5,FALSE)) -> Modelo Conceptual | U37: {=(INDEX('Ontology and concepts per UC'!$G$2:$I$46,MATCH($S37,'Ontology and concepts per UC'!$F$2:$F$46,0),MATCH(LEFT($A37,3),'Ontology and concepts per UC'!$G$1:$I$1,0))=0)} -> FALSE | V37: =COUNTIF(W37:Z37,TRUE)>0 -> FALSE | W37: FALSE | X37: FALSE | Y37: FALSE | Z37: FALSE
A38: UC1-F1-P1-S2-M1 | B38: Manif_ErupcionCutanea | C38: ChronicManifestation | D38: =IF(ISBLANK(C38),0,LEN(C38)-LEN(SUBSTITUTE(C38,";",""))+1) -> 1 | E38: =IF(D38<2,C38,LEFT(C38,FIND(";",C38)-1)) -> ChronicManifestation | F38: =IF(D38<1,FALSE,ISERROR(MATCH(E38,'Ontology and concepts per UC'!$A$2:$A$62,0))) -> FALSE | G38: =IF(D38<2,"",MID(C38,LEN(E38)+3,LEN(C38)-FIND(";",C38)-1)) | H38: =IF(D38<3,G38,LEFT(G38,FIND(";",G38)-1)) | I38: =IF(D38<2,FALSE,ISERROR(MATCH(H38,'Ontology and concepts per UC'!$A$2:$A$62,0))) -> FALSE | J38: =IF(D38<3,"",RIGHT(G38,LEN(G38)-FIND(";",G38)-1)) | K38: =IF(D38<3,FALSE,ISERROR(MATCH(J38,'Ontology and concepts per UC'!$A$2:$A$62,0))) -> FALSE | O38: FALSE | P38: 0 | Q38: 0 | R38: =NOT(ISERROR(SEARCH("hasSource",M38))) -> FALSE | S38: Manifestación: Problemas en la piel | T38: =IF(S38="","",VLOOKUP(S38,'Ontology and concepts per UC'!$F$2:$J$46,5,FALSE)) -> Modelo Conceptual | U38: {=(INDEX('Ontology and concepts per UC'!$G$2:$I$46,MATCH($S38,'Ontology and concepts per UC'!$F$2:$F$46,0),MATCH(LEFT($A38,3),'Ontology and concepts per UC'!$G$1:$I$1,0))=0)} -> FALSE | V38: =COUNTIF(W38:Z38,TRUE)>0 -> FALSE | W38: FALSE | X38: FALSE | Y38: FALSE | Z38: FALSE
A39: UC1-F1-P1-S2-M1 | B39: CosteCribadoUnitario | C39: Cost | D39: =IF(ISBLANK(C39),0,LEN(C39)-LEN(SUBSTITUTE(C39,";",""))+1) -> 1 | E39: =IF(D39<2,C39,LEFT(C39,FIND(";",C39)-1)) -> Cost | F39: =IF(D39<1,FALSE,ISERROR(MATCH(E39,'Ontology and concepts per UC'!$A$2:$A$62,0))) -> FALSE | G39: =IF(D39<2,"",MID(C39,LEN(E39)+3,LEN(C39)-FIND(";",C39)-1)) | H39: =IF(D39<3,G39,LEFT(G39,FIND(";",G39)-1)) | I39: =IF(D39<2,FALSE,ISERROR(MATCH(H39,'Ontology and concepts per UC'!$A$2:$A$62,0))) -> FALSE | J39: =IF(D39<3,"",RIGHT(G39,LEN(G39)-FIND(";",G39)-1)) | K39: =IF(D39<3,FALSE,ISERROR(MATCH(J39,'Ontology and concepts per UC'!$A$2:$A$62,0))) -> FALSE | M39: hasExpectedValue:"25.5"; | O39: FALSE | P39: 0 | Q39: 0 | R39: =NOT(ISERROR(SEARCH("hasSource",M39))) -> FALSE | S39: Coste cribado | T39: =IF(S39="","",VLOOKUP(S39,'Ontology and concepts per UC'!$F$2:$J$46,5,FALSE)) -> Coste | U39: {=(INDEX('Ontology and concepts per UC'!$G$2:$I$46,MATCH($S39,'Ontology and concepts per UC'!$F$2:$F$46,0),MATCH(LEFT($A39,3),'Ontology and concepts per UC'!$G$1:$I$1,0))=0)} -> FALSE | V39: =COUNTIF(W39:Z39,TRUE)>0 -> TRUE | W39: FALSE | X39: FALSE | Y39: FALSE | Z39: TRUE | AA39: Unsuitable value for property
A40: UC1-F1-P1-S2-M1 | B40: CosteDiagnostico | C40: Cost | D40: =IF(ISBLANK(C40),0,LEN(C40)-LEN(SUBSTITUTE(C40,";",""))+1) -> 1 | E40: =IF(D40<2,C40,LEFT(C40,FIND(";",C40)-1)) -> Cost | F40: =IF(D40<1,FALSE,ISERROR(MATCH(E40,'Ontology and concepts per UC'!$A$2:$A$62,0))) -> FALSE | G40: =IF(D40<2,"",MID(C40,LEN(E40)+3,LEN(C40)-FIND(";",C40)-1)) | H40: =IF(D40<3,G40,LEFT(G40,FIND(";",G40)-1)) | I40: =IF(D40<2,FALSE,ISERROR(MATCH(H40,'Ontology and concepts per UC'!$A$2:$A$62,0))) -> FALSE | J40: =IF(D40<3,"",RIGHT(G40,LEN(G40)-FIND(";",G40)-1)) | K40: =IF(D40<3,FALSE,ISERROR(MATCH(J40,'Ontology and concepts per UC'!$A$2:$A$62,0))) -> FALSE | M40: hasExpectedValue:"150.0"; | O40: FALSE | P40: 0 | Q40: 0 | R40: =NOT(ISERROR(SEARCH("hasSource",M40))) -> FALSE | S40: Coste de diagnóstico | T40: =IF(S40="","",VLOOKUP(S40,'Ontology and concepts per UC'!$F$2:$J$46,5,FALSE)) -> Coste | U40: {=(INDEX('Ontology and concepts per UC'!$G$2:$I$46,MATCH($S40,'Ontology and concepts per UC'!$F$2:$F$46,0),MATCH(LEFT($A40,3),'Ontology and concepts per UC'!$G$1:$I$1,0))=0)} -> FALSE | V40: =COUNTIF(W40:Z40,TRUE)>0 -> FALSE | W40: FALSE | X40: FALSE | Y40: FALSE | Z40: FALSE
A41: UC1-F1-P1-S2-M1 | B41: Param_EspecificidadCribado | C41: DeterministicParameter | D41: =IF(ISBLANK(C41),0,LEN(C41)-LEN(SUBSTITUTE(C41,";",""))+1) -> 1 | E41: =IF(D41<2,C41,LEFT(C41,FIND(";",C41)-1)) -> DeterministicParameter | F41: =IF(D41<1,FALSE,ISERROR(MATCH(E41,'Ontology and concepts per UC'!$A$2:$A$62,0))) -> FALSE | G41: =IF(D41<2,"",MID(C41,LEN(E41)+3,LEN(C41)-FIND(";",C41)-1)) | H41: =IF(D41<3,G41,LEFT(G41,FIND(";",G41)-1)) | I41: =IF(D41<2,FALSE,ISERROR(MATCH(H41,'Ontology and concepts per UC'!$A$2:$A$62,0))) -> FALSE | J41: =IF(D41<3,"",RIGHT(G41,LEN(G41)-FIND(";",G41)-1)) | K41: =IF(D41<3,FALSE,ISERROR(MATCH(J41,'Ontology and concepts per UC'!$A$2:$A$62,0))) -> FALSE | M41: hasExpectedValue:"0.995"; | O41: FALSE | P41: 0 | Q41: 0 | R41: =NOT(ISERROR(SEARCH("hasSource",M41))) -> FALSE | S41: Especificidad | T41: =IF(S41="","",VLOOKUP(S41,'Ontology and concepts per UC'!$F$2:$J$46,5,FALSE)) -> Parámetros de intervención | U41: {=(INDEX('Ontology and concepts per UC'!$G$2:$I$46,MATCH($S41,'Ontology and concepts per UC'!$F$2:$F$46,0),MATCH(LEFT($A41,3),'Ontology and concepts per UC'!$G$1:$I$1,0))=0)} -> FALSE | V41: =COUNTIF(W41:Z41,TRUE)>0 -> FALSE | W41: FALSE | X41: FALSE | Y41: FALSE | Z41: FALSE
A42: UC1-F1-P1-S2-M1 | B42: Param_SensibilidadCribado | C42: DeterministicParameter | D42: =IF(ISBLANK(C42),0,LEN(C42)-LEN(SUBSTITUTE(C42,";",""))+1) -> 1 | E42: =IF(D42<2,C42,LEFT(C42,FIND(";",C42)-1)) -> DeterministicParameter | F42: =IF(D42<1,FALSE,ISERROR(MATCH(E42,'Ontology and concepts per UC'!$A$2:$A$62,0))) -> FALSE | G42: =IF(D42<2,"",MID(C42,LEN(E42)+3,LEN(C42)-FIND(";",C42)-1)) | H42: =IF(D42<3,G42,LEFT(G42,FIND(";",G42)-1)) | I42: =IF(D42<2,FALSE,ISERROR(MATCH(H42,'Ontology and concepts per UC'!$A$2:$A$62,0))) -> FALSE | J42: =IF(D42<3,"",RIGHT(G42,LEN(G42)-FIND(";",G42)-1)) | K42: =IF(D42<3,FALSE,ISERROR(MATCH(J42,'Ontology and concepts per UC'!$A$2:$A$62,0))) -> FALSE | M42: hasExpectedValue:"0.998"; | O42: FALSE | P42: 0 | Q42: 0 | R42: =NOT(ISERROR(SEARCH("hasSource",M42))) -> FALSE | S42: Caracterización cribado | T42: =IF(S42="","",VLOOKUP(S42,'Ontology and concepts per UC'!$F$2:$J$46,5,FALSE)) -> Parámetros de intervención | U42: {=(INDEX('Ontology and concepts per UC'!$G$2:$I$46,MATCH($S42,'Ontology and concepts per UC'!$F$2:$F$46,0),MATCH(LEFT($A42,3),'Ontology and concepts per UC'!$G$1:$I$1,0))=0)} -> FALSE | V42: =COUNTIF(W42:Z42,TRUE)>0 -> FALSE | W42: FALSE | X42: FALSE | Y42: FALSE | Z42: FALSE
A43: UC1-F1-P1-S2-M1 | B43: DeteccionClinicaBiotinidasa | C43: DiagnosisIntervention | D43: =IF(ISBLANK(C43),0,LEN(C43)-LEN(SUBSTITUTE(C43,";",""))+1) -> 1 | E43: =IF(D43<2,C43,LEFT(C43,FIND(";",C43)-1)) -> DiagnosisIntervention | F43: =IF(D43<1,FALSE,ISERROR(MATCH(E43,'Ontology and concepts per UC'!$A$2:$A$62,0))) -> FALSE | G43: =IF(D43<2,"",MID(C43,LEN(E43)+3,LEN(C43)-FIND(";",C43)-1)) | H43: =IF(D43<3,G43,LEFT(G43,FIND(";",G43)-1)) | I43: =IF(D43<2,FALSE,ISERROR(MATCH(H43,'Ontology and concepts per UC'!$A$2:$A$62,0))) -> FALSE | J43: =IF(D43<3,"",RIGHT(G43,LEN(G43)-FIND(";",G43)-1)) | K43: =IF(D43<3,FALSE,ISERROR(MATCH(J43,'Ontology and concepts per UC'!$A$2:$A$62,0))) -> FALSE | O43: FALSE | P43: 0 | Q43: 0 | R43: =NOT(ISERROR(SEARCH("hasSource",M43))) -> FALSE | S43: Intervención: No cribado | T43: =IF(S43="","",VLOOKUP(S43,'Ontology and concepts per UC'!$F$2:$J$46,5,FALSE)) -> Modelo Conceptual | U43: {=(INDEX('Ontology and concepts per UC'!$G$2:$I$46,MATCH($S43,'Ontology and concepts per UC'!$F$2:$F$46,0),MATCH(LEFT($A43,3),'Ontology and concepts per UC'!$G$1:$I$1,0))=0)} -> FALSE | V43: =COUNTIF(W43:Z43,TRUE)>0 -> FALSE | W43: FALSE | X43: FALSE | Y43: FALSE | Z43: FALSE
A44: UC1-F1-P1-S2-M1 | B44: Param_Prevalencia | C44: EpidemiologicalParameter | D44: =IF(ISBLANK(C44),0,LEN(C44)-LEN(SUBSTITUTE(C44,";",""))+1) -> 1 | E44: =IF(D44<2,C44,LEFT(C44,FIND(";",C44)-1)) -> EpidemiologicalParameter | F44: =IF(D44<1,FALSE,ISERROR(MATCH(E44,'Ontology and concepts per UC'!$A$2:$A$62,0))) -> FALSE | G44: =IF(D44<2,"",MID(C44,LEN(E44)+3,LEN(C44)-FIND(";",C44)-1)) | H44: =IF(D44<3,G44,LEFT(G44,FIND(";",G44)-1)) | I44: =IF(D44<2,FALSE,ISERROR(MATCH(H44,'Ontology and concepts per UC'!$A$2:$A$62,0))) -> FALSE | J44: =IF(D44<3,"",RIGHT(G44,LEN(G44)-FIND(";",G44)-1)) | K44: =IF(D44<3,FALSE,ISERROR(MATCH(J44,'Ontology and concepts per UC'!$A$2:$A$62,0))) -> FALSE | M44: hasExpectedValue:"1.0E-4"; hasSource:"Wolf B. (1991) J Inherit Metab Dis 14(4):513-26"; | O44: FALSE | P44: 0 | Q44: 0 | R44: =NOT(ISERROR(SEARCH("hasSource",M44))) -> TRUE | S44: Prevalencia al nacimiento | T44: =IF(S44="","",VLOOKUP(S44,'Ontology and concepts per UC'!$F$2:$J$46,5,FALSE)) -> Parámetro epidemiológico | U44: {=(INDEX('Ontology and concepts per UC'!$G$2:$I$46,MATCH($S44,'Ontology and concepts per UC'!$F$2:$F$46,0),MATCH(LEFT($A44,3),'Ontology and concepts per UC'!$G$1:$I$1,0))=0)} -> FALSE | V44: =COUNTIF(W44:Z44,TRUE)>0 -> FALSE | W44: FALSE | X44: FALSE | Y44: FALSE | Z44: FALSE
A45: UC1-F1-P1-S2-M1 | B45: PrevalenciaBiotinidasa | C45: EpidemiologicalParameter | D45: =IF(ISBLANK(C45),0,LEN(C45)-LEN(SUBSTITUTE(C45,";",""))+1) -> 1 | E45: =IF(D45<2,C45,LEFT(C45,FIND(";",C45)-1)) -> EpidemiologicalParameter | F45: =IF(D45<1,FALSE,ISERROR(MATCH(E45,'Ontology and concepts per UC'!$A$2:$A$62,0))) -> FALSE | G45: =IF(D45<2,"",MID(C45,LEN(E45)+3,LEN(C45)-FIND(";",C45)-1)) | H45: =IF(D45<3,G45,LEFT(G45,FIND(";",G45)-1)) | I45: =IF(D45<2,FALSE,ISERROR(MATCH(H45,'Ontology and concepts per UC'!$A$2:$A$62,0))) -> FALSE | J45: =IF(D45<3,"",RIGHT(G45,LEN(G45)-FIND(";",G45)-1)) | K45: =IF(D45<3,FALSE,ISERROR(MATCH(J45,'Ontology and concepts per UC'!$A$2:$A$62,0))) -> FALSE | O45: FALSE | P45: 0 | Q45: 0 | R45: =NOT(ISERROR(SEARCH("hasSource",M45))) -> FALSE | S45: Prevalencia al nacimiento | T45: =IF(S45="","",VLOOKUP(S45,'Ontology and concepts per UC'!$F$2:$J$46,5,FALSE)) -> Parámetro epidemiológico | U45: {=(INDEX('Ontology and concepts per UC'!$G$2:$I$46,MATCH($S45,'Ontology and concepts per UC'!$F$2:$F$46,0),MATCH(LEFT($A45,3),'Ontology and concepts per UC'!$G$1:$I$1,0))=0)} -> FALSE | V45: =COUNTIF(W45:Z45,TRUE)>0 -> FALSE | W45: FALSE | X45: FALSE | Y45: FALSE | Z45: FALSE
A46: UC1-F1-P1-S2-M1 | B46: PoblacionRecienNacidosEspaña | C46: Population | D46: =IF(ISBLANK(C46),0,LEN(C46)-LEN(SUBSTITUTE(C46,";",""))+1) -> 1 | E46: =IF(D46<2,C46,LEFT(C46,FIND(";",C46)-1)) -> Population | F46: =IF(D46<1,FALSE,ISERROR(MATCH(E46,'Ontology and concepts per UC'!$A$2:$A$62,0))) -> FALSE | G46: =IF(D46<2,"",MID(C46,LEN(E46)+3,LEN(C46)-FIND(";",C46)-1)) | H46: =IF(D46<3,G46,LEFT(G46,FIND(";",G46)-1)) | I46: =IF(D46<2,FALSE,ISERROR(MATCH(H46,'Ontology and concepts per UC'!$A$2:$A$62,0))) -> FALSE | J46: =IF(D46<3,"",RIGHT(G46,LEN(G46)-FIND(";",G46)-1)) | K46: =IF(D46<3,FALSE,ISERROR(MATCH(J46,'Ontology and concepts per UC'!$A$2:$A$62,0))) -> FALSE | M46: hasGeographicalContext:"España"; hasSize:"450000"; | O46: FALSE | P46: 0 | Q46: 0 | R46: =NOT(ISERROR(SEARCH("hasSource",M46))) -> FALSE | S46: Población | T46: =IF(S46="","",VLOOKUP(S46,'Ontology and concepts per UC'!$F$2:$J$46,5,FALSE)) -> Modelo Conceptual | U46: {=(INDEX('Ontology and concepts per UC'!$G$2:$I$46,MATCH($S46,'Ontology and concepts per UC'!$F$2:$F$46,0),MATCH(LEFT($A46,3),'Ontology and concepts per UC'!$G$1:$I$1,0))=0)} -> FALSE | V46: =COUNTIF(W46:Z46,TRUE)>0 -> FALSE | W46: FALSE | X46: FALSE | Y46: FALSE | Z46: FALSE
A47: UC1-F1-P1-S2-M1 | B47: DeficienciaBiotinidasa | C47: RareDisease | D47: =IF(ISBLANK(C47),0,LEN(C47)-LEN(SUBSTITUTE(C47,";",""))+1) -> 1 | E47: =IF(D47<2,C47,LEFT(C47,FIND(";",C47)-1)) -> RareDisease | F47: =IF(D47<1,FALSE,ISERROR(MATCH(E47,'Ontology and concepts per UC'!$A$2:$A$62,0))) -> FALSE | G47: =IF(D47<2,"",MID(C47,LEN(E47)+3,LEN(C47)-FIND(";",C47)-1)) | H47: =IF(D47<3,G47,LEFT(G47,FIND(";",G47)-1)) | I47: =IF(D47<2,FALSE,ISERROR(MATCH(H47,'Ontology and concepts per UC'!$A$2:$A$62,0))) -> FALSE | J47: =IF(D47<3,"",RIGHT(G47,LEN(G47)-FIND(";",G47)-1)) | K47: =IF(D47<3,FALSE,ISERROR(MATCH(J47,'Ontology and concepts per UC'!$A$2:$A$62,0))) -> FALSE | L47: hasManifestation:Manif_Convulsiones; hasManifestation:Manif_ErupcionCutanea; hasEpidemiologicalParameter:Param_Prevalencia; hasDiagnosisCost:CosteDiagnostico; | M47: hasRefToSNOMED:"253260006"; | O47: FALSE | P47: 0 | Q47: 0 | R47: =NOT(ISERROR(SEARCH("hasSource",M47))) -> FALSE | S47: Enfermedad | T47: =IF(S47="","",VLOOKUP(S47,'Ontology and concepts per UC'!$F$2:$J$46,5,FALSE)) -> Modelo Conceptual | U47: {=(INDEX('Ontology and concepts per UC'!$G$2:$I$46,MATCH($S47,'Ontology and concepts per UC'!$F$2:$F$46,0),MATCH(LEFT($A47,3),'Ontology and concepts per UC'!$G$1:$I$1,0))=0)} -> FALSE | V47: =COUNTIF(W47:Z47,TRUE)>0 -> TRUE | W47: FALSE | X47: FALSE | Y47: FALSE | Z47: TRUE | AA47: Unsuitable value for property
A48: UC1-F1-P1-S2-M1 | B48: CribadoNeonatalBiotinidasa | C48: ScreeningIntervention | D48: =IF(ISBLANK(C48),0,LEN(C48)-LEN(SUBSTITUTE(C48,";",""))+1) -> 1 | E48: =IF(D48<2,C48,LEFT(C48,FIND(";",C48)-1)) -> ScreeningIntervention | F48: =IF(D48<1,FALSE,ISERROR(MATCH(E48,'Ontology and concepts per UC'!$A$2:$A$62,0))) -> FALSE | G48: =IF(D48<2,"",MID(C48,LEN(E48)+3,LEN(C48)-FIND(";",C48)-1)) | H48: =IF(D48<3,G48,LEFT(G48,FIND(";",G48)-1)) | I48: =IF(D48<2,FALSE,ISERROR(MATCH(H48,'Ontology and concepts per UC'!$A$2:$A$62,0))) -> FALSE | J48: =IF(D48<3,"",RIGHT(G48,LEN(G48)-FIND(";",G48)-1)) | K48: =IF(D48<3,FALSE,ISERROR(MATCH(J48,'Ontology and concepts per UC'!$A$2:$A$62,0))) -> FALSE | L48: hasSpecificity:Param_EspecificidadCribado; hasSensitivity:Param_SensibilidadCribado; hasCost:CosteCribadoUnitario; | O48: FALSE | P48: 0 | Q48: 0 | R48: =NOT(ISERROR(SEARCH("hasSource",M48))) -> FALSE | S48: Intervención: Cribado | T48: =IF(S48="","",VLOOKUP(S48,'Ontology and concepts per UC'!$F$2:$J$46,5,FALSE)) -> Modelo Conceptual | U48: {=(INDEX('Ontology and concepts per UC'!$G$2:$I$46,MATCH($S48,'Ontology and concepts per UC'!$F$2:$F$46,0),MATCH(LEFT($A48,3),'Ontology and concepts per UC'!$G$1:$I$1,0))=0)} -> FALSE | V48: =COUNTIF(W48:Z48,TRUE)>0 -> FALSE | W48: FALSE | X48: FALSE | Y48: FALSE | Z48: FALSE
A49: UC1-F1-P1-S2-M1 | B49: Utilidad_Convulsiones | C49: Utility | D49: =IF(ISBLANK(C49),0,LEN(C49)-LEN(SUBSTITUTE(C49,";",""))+1) -> 1 | E49: =IF(D49<2,C49,LEFT(C49,FIND(";",C49)-1)) -> Utility | F49: =IF(D49<1,FALSE,ISERROR(MATCH(E49,'Ontology and concepts per UC'!$A$2:$A$62,0))) -> FALSE | G49: =IF(D49<2,"",MID(C49,LEN(E49)+3,LEN(C49)-FIND(";",C49)-1)) | H49: =IF(D49<3,G49,LEFT(G49,FIND(";",G49)-1)) | I49: =IF(D49<2,FALSE,ISERROR(MATCH(H49,'Ontology and concepts per UC'!$A$2:$A$62,0))) -> FALSE | J49: =IF(D49<3,"",RIGHT(G49,LEN(G49)-FIND(";",G49)-1)) | K49: =IF(D49<3,FALSE,ISERROR(MATCH(J49,'Ontology and concepts per UC'!$A$2:$A$62,0))) -> FALSE | M49: hasExpectedValue:"-0.35"; | O49: FALSE | P49: 0 | Q49: 0 | R49: =NOT(ISERROR(SEARCH("hasSource",M49))) -> FALSE | S49: Utilidad: Convulsiones | T49: =IF(S49="","",VLOOKUP(S49,'Ontology and concepts per UC'!$F$2:$J$46,5,FALSE)) -> Utilidad | U49: {=(INDEX('Ontology and concepts per UC'!$G$2:$I$46,MATCH($S49,'Ontology and concepts per UC'!$F$2:$F$46,0),MATCH(LEFT($A49,3),'Ontology and concepts per UC'!$G$1:$I$1,0))=0)} -> FALSE | V49: =COUNTIF(W49:Z49,TRUE)>0 -> FALSE | W49: FALSE | X49: FALSE | Y49: FALSE | Z49: FALSE
A50: UC1-F1-P1-S2-M1 | B50: Utilidad_ErupcionCutanea | C50: Utility | D50: =IF(ISBLANK(C50),0,LEN(C50)-LEN(SUBSTITUTE(C50,";",""))+1) -> 1 | E50: =IF(D50<2,C50,LEFT(C50,FIND(";",C50)-1)) -> Utility | F50: =IF(D50<1,FALSE,ISERROR(MATCH(E50,'Ontology and concepts per UC'!$A$2:$A$62,0))) -> FALSE | G50: =IF(D50<2,"",MID(C50,LEN(E50)+3,LEN(C50)-FIND(";",C50)-1)) | H50: =IF(D50<3,G50,LEFT(G50,FIND(";",G50)-1)) | I50: =IF(D50<2,FALSE,ISERROR(MATCH(H50,'Ontology and concepts per UC'!$A$2:$A$62,0))) -> FALSE | J50: =IF(D50<3,"",RIGHT(G50,LEN(G50)-FIND(";",G50)-1)) | K50: =IF(D50<3,FALSE,ISERROR(MATCH(J50,'Ontology and concepts per UC'!$A$2:$A$62,0))) -> FALSE | M50: hasExpectedValue:"-0.15"; | O50: FALSE | P50: 0 | Q50: 0 | R50: =NOT(ISERROR(SEARCH("hasSource",M50))) -> FALSE | S50: Utilidad: Problemas en la piel | T50: =IF(S50="","",VLOOKUP(S50,'Ontology and concepts per UC'!$F$2:$J$46,5,FALSE)) -> Utilidad | U50: {=(INDEX('Ontology and concepts per UC'!$G$2:$I$46,MATCH($S50,'Ontology and concepts per UC'!$F$2:$F$46,0),MATCH(LEFT($A50,3),'Ontology and concepts per UC'!$G$1:$I$1,0))=0)} -> FALSE | V50: =COUNTIF(W50:Z50,TRUE)>0 -> FALSE | W50: FALSE | X50: FALSE | Y50: FALSE | Z50: FALSE
A51: UC1-F1-P2-S1-M1 | B51: BD_Manif_HipoacusiaNeurosensorial | C51: ChronicManifestation | D51: =IF(ISBLANK(C51),0,LEN(C51)-LEN(SUBSTITUTE(C51,";",""))+1) -> 1 | E51: =IF(D51<2,C51,LEFT(C51,FIND(";",C51)-1)) -> ChronicManifestation | F51: =IF(D51<1,FALSE,ISERROR(MATCH(E51,'Ontology and concepts per UC'!$A$2:$A$62,0))) -> FALSE | G51: =IF(D51<2,"",MID(C51,LEN(E51)+3,LEN(C51)-FIND(";",C51)-1)) | H51: =IF(D51<3,G51,LEFT(G51,FIND(";",G51)-1)) | I51: =IF(D51<2,FALSE,ISERROR(MATCH(H51,'Ontology and concepts per UC'!$A$2:$A$62,0))) -> FALSE | J51: =IF(D51<3,"",RIGHT(G51,LEN(G51)-FIND(";",G51)-1)) | K51: =IF(D51<3,FALSE,ISERROR(MATCH(J51,'Ontology and concepts per UC'!$A$2:$A$62,0))) -> FALSE | M51: hasDescription:"Hipoacusia neurosensorial bilateral irreversible, presente en 55% de casos sintomáticos"; hasSource:"Genc et al. 2007[4]; Wolf et al. 2002[5]; Weber et al. 2004[2]"; | O51: FALSE | P51: 0 | Q51: 0 | R51: =NOT(ISERROR(SEARCH("hasSource",M51))) -> TRUE | S51: Manifestación: Problemas de audición | T51: =IF(S51="","",VLOOKUP(S51,'Ontology and concepts per UC'!$F$2:$J$46,5,FALSE)) -> Modelo Conceptual | U51: {=(INDEX('Ontology and concepts per UC'!$G$2:$I$46,MATCH($S51,'Ontology and concepts per UC'!$F$2:$F$46,0),MATCH(LEFT($A51,3),'Ontology and concepts per UC'!$G$1:$I$1,0))=0)} -> FALSE | V51: =COUNTIF(W51:Z51,TRUE)>0 -> FALSE | W51: FALSE | X51: FALSE | Y51: FALSE | Z51: FALSE
A52: UC1-F1-P2-S1-M1 | B52: BD_Manif_Leucoencefalopatia | C52: ChronicManifestation | D52: =IF(ISBLANK(C52),0,LEN(C52)-LEN(SUBSTITUTE(C52,";",""))+1) -> 1 | E52: =IF(D52<2,C52,LEFT(C52,FIND(";",C52)-1)) -> ChronicManifestation | F52: =IF(D52<1,FALSE,ISERROR(MATCH(E52,'Ontology and concepts per UC'!$A$2:$A$62,0))) -> FALSE | G52: =IF(D52<2,"",MID(C52,LEN(E52)+3,LEN(C52)-FIND(";",C52)-1)) | H52: =IF(D52<3,G52,LEFT(G52,FIND(";",G52)-1)) | I52: =IF(D52<2,FALSE,ISERROR(MATCH(H52,'Ontology and concepts per UC'!$A$2:$A$62,0))) -> FALSE | J52: =IF(D52<3,"",RIGHT(G52,LEN(G52)-FIND(";",G52)-1)) | K52: =IF(D52<3,FALSE,ISERROR(MATCH(J52,'Ontology and concepts per UC'!$A$2:$A$62,0))) -> FALSE | M52: hasSource:"Grünewald et al. 2003[3]; Couce et al. 2011[1]"; hasDescription:"Alteraciones difusas de la sustancia blanca en resonancia magnética"; | O52: FALSE | P52: 0 | Q52: 0 | R52: =NOT(ISERROR(SEARCH("hasSource",M52))) -> TRUE | S52: Manifestación: Hipotonía | T52: =IF(S52="","",VLOOKUP(S52,'Ontology and concepts per UC'!$F$2:$J$46,5,FALSE)) -> Modelo Conceptual | U52: {=(INDEX('Ontology and concepts per UC'!$G$2:$I$46,MATCH($S52,'Ontology and concepts per UC'!$F$2:$F$46,0),MATCH(LEFT($A52,3),'Ontology and concepts per UC'!$G$1:$I$1,0))=0)} -> FALSE | V52: =COUNTIF(W52:Z52,TRUE)>0 -> FALSE | W52: FALSE | X52: FALSE | Y52: FALSE | Z52: FALSE
A53: UC1-F1-P2-S1-M1 | B53: BD_Manif_AtrofiaOptica | C53: ChronicManifestation; ManifestacionClinica | D53: =IF(ISBLANK(C53),0,LEN(C53)-LEN(SUBSTITUTE(C53,";",""))+1) -> 2 | E53: =IF(D53<2,C53,LEFT(C53,FIND(";",C53)-1)) -> ChronicManifestation | F53: =IF(D53<1,FALSE,ISERROR(MATCH(E53,'Ontology and concepts per UC'!$A$2:$A$62,0))) -> FALSE | G53: =IF(D53<2,"",MID(C53,LEN(E53)+3,LEN(C53)-FIND(";",C53)-1)) -> ManifestacionClinica | H53: =IF(D53<3,G53,LEFT(G53,FIND(";",G53)-1)) -> ManifestacionClinica | I53: =IF(D53<2,FALSE,ISERROR(MATCH(H53,'Ontology and concepts per UC'!$A$2:$A$62,0))) -> TRUE | J53: =IF(D53<3,"",RIGHT(G53,LEN(G53)-FIND(";",G53)-1)) | K53: =IF(D53<3,FALSE,ISERROR(MATCH(J53,'Ontology and concepts per UC'!$A$2:$A$62,0))) -> FALSE | L53: affectsUtility:BD_Manif_AtrofiaOptica_U; | M53: hasSource:"Salbert et al. 1993[5]; Weber et al. 2004[2]"; hasSource:"Salbert et al. 1993[5]; Ye et al. 2009[6]"; hasSource:"Salbert et al. 1993[5]; Ye et al. 2009[7]"; hasDescription:"Atrofia óptica bilateral progresiva con pérdida aguda de visión"; hasDescription:"Atrofia óptica progresiva con pérdida de agudeza visual"; hasProbability:"0.36"; | O53: FALSE | P53: 1 | Q53: 2 | R53: =NOT(ISERROR(SEARCH("hasSource",M53))) -> TRUE | S53: Manifestación: Pérdida de visión | T53: =IF(S53="","",VLOOKUP(S53,'Ontology and concepts per UC'!$F$2:$J$46,5,FALSE)) -> Modelo Conceptual | U53: {=(INDEX('Ontology and concepts per UC'!$G$2:$I$46,MATCH($S53,'Ontology and concepts per UC'!$F$2:$F$46,0),MATCH(LEFT($A53,3),'Ontology and concepts per UC'!$G$1:$I$1,0))=0)} -> FALSE | V53: =COUNTIF(W53:Z53,TRUE)>0 -> TRUE | W53: TRUE | X53: FALSE | Y53: FALSE | Z53: TRUE | AA53: Class 'ManifestacionClinica' undefined; ObjectProp 'affectsUtility' undefined; DataProp 'hasProbability' undefined; unsuitable sources
A54: UC1-F1-P2-S1-M1 | B54: BD_Progresion_Temporal | C54: DiseaseProgressionModel | D54: =IF(ISBLANK(C54),0,LEN(C54)-LEN(SUBSTITUTE(C54,";",""))+1) -> 1 | E54: =IF(D54<2,C54,LEFT(C54,FIND(";",C54)-1)) -> DiseaseProgressionModel | F54: =IF(D54<1,FALSE,ISERROR(MATCH(E54,'Ontology and concepts per UC'!$A$2:$A$62,0))) -> TRUE | G54: =IF(D54<2,"",MID(C54,LEN(E54)+3,LEN(C54)-FIND(";",C54)-1)) | H54: =IF(D54<3,G54,LEFT(G54,FIND(";",G54)-1)) | I54: =IF(D54<2,FALSE,ISERROR(MATCH(H54,'Ontology and concepts per UC'!$A$2:$A$62,0))) -> FALSE | J54: =IF(D54<3,"",RIGHT(G54,LEN(G54)-FIND(";",G54)-1)) | K54: =IF(D54<3,FALSE,ISERROR(MATCH(J54,'Ontology and concepts per UC'!$A$2:$A$62,0))) -> FALSE | L54: hasAcutePhase:BD_Param_Tiempo_ManifAgudas; hasChronicPhase:BD_Manif_HipoacusiaCronica; | O54: FALSE | P54: 1 | Q54: 2 | R54: =NOT(ISERROR(SEARCH("hasSource",M54))) -> FALSE | S54: Otros | T54: =IF(S54="","",VLOOKUP(S54,'Ontology and concepts per UC'!$F$2:$J$46,5,FALSE)) -> Otros | U54: {=(INDEX('Ontology and concepts per UC'!$G$2:$I$46,MATCH($S54,'Ontology and concepts per UC'!$F$2:$F$46,0),MATCH(LEFT($A54,3),'Ontology and concepts per UC'!$G$1:$I$1,0))=0)} -> TRUE | V54: =COUNTIF(W54:Z54,TRUE)>0 -> TRUE | W54: TRUE | X54: FALSE | Y54: FALSE | Z54: FALSE | AA54: Class 'DiseaseProgressionModel' undefined; ObjectProp 'hasAcutePhase' undefined; ObjectProp 'hasChronicPhase' undefined
A55: UC1-F1-P2-S1-M1 | B55: BD_Manif_AtrofiaOptica_U | C55: DisutilityParameter | D55: =IF(ISBLANK(C55),0,LEN(C55)-LEN(SUBSTITUTE(C55,";",""))+1) -> 1 | E55: =IF(D55<2,C55,LEFT(C55,FIND(";",C55)-1)) -> DisutilityParameter | F55: =IF(D55<1,FALSE,ISERROR(MATCH(E55,'Ontology and concepts per UC'!$A$2:$A$62,0))) -> TRUE | G55: =IF(D55<2,"",MID(C55,LEN(E55)+3,LEN(C55)-FIND(";",C55)-1)) | H55: =IF(D55<3,G55,LEFT(G55,FIND(";",G55)-1)) | I55: =IF(D55<2,FALSE,ISERROR(MATCH(H55,'Ontology and concepts per UC'!$A$2:$A$62,0))) -> FALSE | J55: =IF(D55<3,"",RIGHT(G55,LEN(G55)-FIND(";",G55)-1)) | K55: =IF(D55<3,FALSE,ISERROR(MATCH(J55,'Ontology and concepts per UC'!$A$2:$A$62,0))) -> FALSE | M55: hasSource:"Salbert et al. 1993[5]; Weber et al. 2004[2]"; hasExpectedValue:"0.55"; | O55: FALSE | P55: 1 | Q55: 0 | R55: =NOT(ISERROR(SEARCH("hasSource",M55))) -> TRUE | S55: Utilidad: Pérdida de visión | T55: =IF(S55="","",VLOOKUP(S55,'Ontology and concepts per UC'!$F$2:$J$46,5,FALSE)) -> Utilidad | U55: {=(INDEX('Ontology and concepts per UC'!$G$2:$I$46,MATCH($S55,'Ontology and concepts per UC'!$F$2:$F$46,0),MATCH(LEFT($A55,3),'Ontology and concepts per UC'!$G$1:$I$1,0))=0)} -> FALSE | V55: =COUNTIF(W55:Z55,TRUE)>0 -> TRUE | W55: TRUE | X55: FALSE | Y55: FALSE | Z55: TRUE | AA55: Class 'DisutilityParameter' undefined; unsuitable value for property
A56: UC1-F1-P2-S1-M1 | B56: BD_Manif_Dermatitis_U | C56: DisutilityParameter | D56: =IF(ISBLANK(C56),0,LEN(C56)-LEN(SUBSTITUTE(C56,";",""))+1) -> 1 | E56: =IF(D56<2,C56,LEFT(C56,FIND(";",C56)-1)) -> DisutilityParameter | F56: =IF(D56<1,FALSE,ISERROR(MATCH(E56,'Ontology and concepts per UC'!$A$2:$A$62,0))) -> TRUE | G56: =IF(D56<2,"",MID(C56,LEN(E56)+3,LEN(C56)-FIND(";",C56)-1)) | H56: =IF(D56<3,G56,LEFT(G56,FIND(";",G56)-1)) | I56: =IF(D56<2,FALSE,ISERROR(MATCH(H56,'Ontology and concepts per UC'!$A$2:$A$62,0))) -> FALSE | J56: =IF(D56<3,"",RIGHT(G56,LEN(G56)-FIND(";",G56)-1)) | K56: =IF(D56<3,FALSE,ISERROR(MATCH(J56,'Ontology and concepts per UC'!$A$2:$A$62,0))) -> FALSE | M56: hasSource:"Salbert et al. 1993[5]; Wolf et al. 2002[6]"; hasExpectedValue:"0.30"; | O56: FALSE | P56: 1 | Q56: 0 | R56: =NOT(ISERROR(SEARCH("hasSource",M56))) -> TRUE | S56: Utilidad: Problemas en la piel | T56: =IF(S56="","",VLOOKUP(S56,'Ontology and concepts per UC'!$F$2:$J$46,5,FALSE)) -> Utilidad | U56: {=(INDEX('Ontology and concepts per UC'!$G$2:$I$46,MATCH($S56,'Ontology and concepts per UC'!$F$2:$F$46,0),MATCH(LEFT($A56,3),'Ontology and concepts per UC'!$G$1:$I$1,0))=0)} -> FALSE | V56: =COUNTIF(W56:Z56,TRUE)>0 -> TRUE | W56: TRUE | X56: FALSE | Y56: FALSE | Z56: TRUE | AA56: Class 'DisutilityParameter' undefined; unsuitable value for property
A57: UC1-F1-P2-S1-M1 | B57: BD_Manif_RetrasoDesarrollo_U | C57: DisutilityParameter | D57: =IF(ISBLANK(C57),0,LEN(C57)-LEN(SUBSTITUTE(C57,";",""))+1) -> 1 | E57: =IF(D57<2,C57,LEFT(C57,FIND(";",C57)-1)) -> DisutilityParameter | F57: =IF(D57<1,FALSE,ISERROR(MATCH(E57,'Ontology and concepts per UC'!$A$2:$A$62,0))) -> TRUE | G57: =IF(D57<2,"",MID(C57,LEN(E57)+3,LEN(C57)-FIND(";",C57)-1)) | H57: =IF(D57<3,G57,LEFT(G57,FIND(";",G57)-1)) | I57: =IF(D57<2,FALSE,ISERROR(MATCH(H57,'Ontology and concepts per UC'!$A$2:$A$62,0))) -> FALSE | J57: =IF(D57<3,"",RIGHT(G57,LEN(G57)-FIND(";",G57)-1)) | K57: =IF(D57<3,FALSE,ISERROR(MATCH(J57,'Ontology and concepts per UC'!$A$2:$A$62,0))) -> FALSE | M57: hasExpectedValue:"0.70"; hasSource:"Joshi et al. 1999[7]; Couce et al. 2011[1]"; | O57: FALSE | P57: 1 | Q57: 0 | R57: =NOT(ISERROR(SEARCH("hasSource",M57))) -> TRUE | S57: Utilidad: Retraso mental | T57: =IF(S57="","",VLOOKUP(S57,'Ontology and concepts per UC'!$F$2:$J$46,5,FALSE)) -> Utilidad | U57: {=(INDEX('Ontology and concepts per UC'!$G$2:$I$46,MATCH($S57,'Ontology and concepts per UC'!$F$2:$F$46,0),MATCH(LEFT($A57,3),'Ontology and concepts per UC'!$G$1:$I$1,0))=0)} -> FALSE | V57: =COUNTIF(W57:Z57,TRUE)>0 -> TRUE | W57: TRUE | X57: FALSE | Y57: FALSE | Z57: TRUE | AA57: Class 'DisutilityParameter' undefined; unsuitable value for property
A58: UC1-F1-P2-S1-M1 | B58: BD_Manif_Hipoacusia_U | C58: DisutilityParameter; UtilityParameter | D58: =IF(ISBLANK(C58),0,LEN(C58)-LEN(SUBSTITUTE(C58,";",""))+1) -> 2 | E58: =IF(D58<2,C58,LEFT(C58,FIND(";",C58)-1)) -> DisutilityParameter | F58: =IF(D58<1,FALSE,ISERROR(MATCH(E58,'Ontology and concepts per UC'!$A$2:$A$62,0))) -> TRUE | G58: =IF(D58<2,"",MID(C58,LEN(E58)+3,LEN(C58)-FIND(";",C58)-1)) -> UtilityParameter | H58: =IF(D58<3,G58,LEFT(G58,FIND(";",G58)-1)) -> UtilityParameter | I58: =IF(D58<2,FALSE,ISERROR(MATCH(H58,'Ontology and concepts per UC'!$A$2:$A$62,0))) -> TRUE | J58: =IF(D58<3,"",RIGHT(G58,LEN(G58)-FIND(";",G58)-1)) | K58: =IF(D58<3,FALSE,ISERROR(MATCH(J58,'Ontology and concepts per UC'!$A$2:$A$62,0))) -> FALSE | M58: hasExpectedValue:"0.45"; hasSource:"Genc et al. 2007[4]; Wolf et al. 2002[5]"; hasSource:"Genc et al. 2007[4]; Wolf et al. 2002[6]"; | O58: FALSE | P58: 2 | Q58: 0 | R58: =NOT(ISERROR(SEARCH("hasSource",M58))) -> TRUE | S58: Utilidad: Problemas de audición | T58: =IF(S58="","",VLOOKUP(S58,'Ontology and concepts per UC'!$F$2:$J$46,5,FALSE)) -> Utilidad | U58: {=(INDEX('Ontology and concepts per UC'!$G$2:$I$46,MATCH($S58,'Ontology and concepts per UC'!$F$2:$F$46,0),MATCH(LEFT($A58,3),'Ontology and concepts per UC'!$G$1:$I$1,0))=0)} -> FALSE | V58: =COUNTIF(W58:Z58,TRUE)>0 -> TRUE | W58: TRUE | X58: FALSE | Y58: FALSE | Z58: TRUE | AA58: Class 'DisutilityParameter' undefined; Class 'UtilityParameter' undefined; unsuitable value for property
A59: UC1-F1-P2-S1-M1 | B59: BD_Intervencion_Biotina_Efectividad | C59: EfficacyParameter | D59: =IF(ISBLANK(C59),0,LEN(C59)-LEN(SUBSTITUTE(C59,";",""))+1) -> 1 | E59: =IF(D59<2,C59,LEFT(C59,FIND(";",C59)-1)) -> EfficacyParameter | F59: =IF(D59<1,FALSE,ISERROR(MATCH(E59,'Ontology and concepts per UC'!$A$2:$A$62,0))) -> TRUE | G59: =IF(D59<2,"",MID(C59,LEN(E59)+3,LEN(C59)-FIND(";",C59)-1)) | H59: =IF(D59<3,G59,LEFT(G59,FIND(";",G59)-1)) | I59: =IF(D59<2,FALSE,ISERROR(MATCH(H59,'Ontology and concepts per UC'!$A$2:$A$62,0))) -> FALSE | J59: =IF(D59<3,"",RIGHT(G59,LEN(G59)-FIND(";",G59)-1)) | K59: =IF(D59<3,FALSE,ISERROR(MATCH(J59,'Ontology and concepts per UC'!$A$2:$A$62,0))) -> FALSE | M59: hasSource:"Grünewald et al. 2003[6]; Wolf et al. 2002[5]"; hasExpectedValue:"Resolución síntomas en 1-4 semanas (Genc et al. 2007[7])"; | O59: FALSE | P59: 1 | Q59: 0 | R59: =NOT(ISERROR(SEARCH("hasSource",M59))) -> TRUE | S59: Efecto de la intervención cribado | T59: =IF(S59="","",VLOOKUP(S59,'Ontology and concepts per UC'!$F$2:$J$46,5,FALSE)) -> Parámetros de intervención | U59: {=(INDEX('Ontology and concepts per UC'!$G$2:$I$46,MATCH($S59,'Ontology and concepts per UC'!$F$2:$F$46,0),MATCH(LEFT($A59,3),'Ontology and concepts per UC'!$G$1:$I$1,0))=0)} -> FALSE | V59: =COUNTIF(W59:Z59,TRUE)>0 -> TRUE | W59: TRUE | X59: FALSE | Y59: FALSE | Z59: TRUE | AA59: Class 'EfficacyParameter' undefined; the individual cannot be used
A60: UC1-F1-P2-S1-M1 | B60: BD_Parcial_Enfermedad | C60: Enfermedad | D60: =IF(ISBLANK(C60),0,LEN(C60)-LEN(SUBSTITUTE(C60,";",""))+1) -> 1 | E60: =IF(D60<2,C60,LEFT(C60,FIND(";",C60)-1)) -> Enfermedad | F60: =IF(D60<1,FALSE,ISERROR(MATCH(E60,'Ontology and concepts per UC'!$A$2:$A$62,0))) -> TRUE | G60: =IF(D60<2,"",MID(C60,LEN(E60)+3,LEN(C60)-FIND(";",C60)-1)) | H60: =IF(D60<3,G60,LEFT(G60,FIND(";",G60)-1)) | I60: =IF(D60<2,FALSE,ISERROR(MATCH(H60,'Ontology and concepts per UC'!$A$2:$A$62,0))) -> FALSE | J60: =IF(D60<3,"",RIGHT(G60,LEN(G60)-FIND(";",G60)-1)) | K60: =IF(D60<3,FALSE,ISERROR(MATCH(J60,'Ontology and concepts per UC'!$A$2:$A$62,0))) -> FALSE | L60: hasManifestation:BD_Parcial_Alopecia; hasManifestation:BD_Parcial_Dermatitis; hasManifestation:BD_Parcial_Hipoacusia; hasManifestation:BD_Parcial_Convulsiones; | M60: hasDescription:"Deficiencia parcial de biotinidasa (actividad enzimática 10-30%)"; hasSource:"Couce et al. 2011[1]; Mslinger et al. 2003[6]"; | O60: FALSE | P60: 1 | Q60: 0 | R60: =NOT(ISERROR(SEARCH("hasSource",M60))) -> TRUE | S60: Parcial | T60: =IF(S60="","",VLOOKUP(S60,'Ontology and concepts per UC'!$F$2:$J$46,5,FALSE)) -> Parcial | U60: {=(INDEX('Ontology and concepts per UC'!$G$2:$I$46,MATCH($S60,'Ontology and concepts per UC'!$F$2:$F$46,0),MATCH(LEFT($A60,3),'Ontology and concepts per UC'!$G$1:$I$1,0))=0)} -> FALSE | V60: =COUNTIF(W60:Z60,TRUE)>0 -> TRUE | W60: TRUE | X60: FALSE | Y60: FALSE | Z60: FALSE | AA60: Class 'Enfermedad' undefined
A61: UC1-F1-P2-S1-M1 | B61: BD_Enfermedad | C61: Enfermedad; EnfermedadMetabolica | D61: =IF(ISBLANK(C61),0,LEN(C61)-LEN(SUBSTITUTE(C61,";",""))+1) -> 2 | E61: =IF(D61<2,C61,LEFT(C61,FIND(";",C61)-1)) -> Enfermedad | F61: =IF(D61<1,FALSE,ISERROR(MATCH(E61,'Ontology and concepts per UC'!$A$2:$A$62,0))) -> TRUE | G61: =IF(D61<2,"",MID(C61,LEN(E61)+3,LEN(C61)-FIND(";",C61)-1)) -> EnfermedadMetabolica | H61: =IF(D61<3,G61,LEFT(G61,FIND(";",G61)-1)) -> EnfermedadMetabolica | I61: =IF(D61<2,FALSE,ISERROR(MATCH(H61,'Ontology and concepts per UC'!$A$2:$A$62,0))) -> TRUE | J61: =IF(D61<3,"",RIGHT(G61,LEN(G61)-FIND(";",G61)-1)) | K61: =IF(D61<3,FALSE,ISERROR(MATCH(J61,'Ontology and concepts per UC'!$A$2:$A$62,0))) -> FALSE | L61: hasManifestation:BD_Manif_Convulsiones; hasManifestation:BD_Manif_HipoacusiaCronica; hasManifestation:BD_Manif_Dermatitis; hasManifestation:BD_Manif_EstridorLaríngeo; hasManifestation:BD_Manif_AtrofiaOptica; hasManifestation:BD_Manif_Hipotonia; hasManifestation:BD_Manif_DermatitisExudativa; hasManifestation:BD_Manif_ConvulsionesAgudas; hasManifestation:BD_Manif_RetrasoDesarrollo; hasManifestation:BD_Manif_ConvulsionesMioclonicas; hasManifestation:BD_Manif_Hipoacusia; hasManifestation:BD_Manif_HipoacusiaNeurosensorial; hasManifestation:BD_Manif_Leucoencefalopatia; hasDiseaseStage:BD_Parcial_Enfermedad; | M61: hasDescription:"Deficiencia profunda de biotinidasa (OMIM 253260), trastorno autosómico recesivo del metabolismo de la biotina"; hasOMIM:"253260"; hasInheritance:"Autosómica recesiva"; | O61: FALSE | P61: 2 | Q61: 3 | R61: =NOT(ISERROR(SEARCH("hasSource",M61))) -> FALSE | S61: Enfermedad | T61: =IF(S61="","",VLOOKUP(S61,'Ontology and concepts per UC'!$F$2:$J$46,5,FALSE)) -> Modelo Conceptual | U61: {=(INDEX('Ontology and concepts per UC'!$G$2:$I$46,MATCH($S61,'Ontology and concepts per UC'!$F$2:$F$46,0),MATCH(LEFT($A61,3),'Ontology and concepts per UC'!$G$1:$I$1,0))=0)} -> FALSE | V61: =COUNTIF(W61:Z61,TRUE)>0 -> TRUE | W61: TRUE | X61: FALSE | Y61: FALSE | Z61: FALSE | AA61: Class 'Enfermedad' undefined; Class 'EnfermedadMetabolica' undefined; ObjectProp 'hasDiseaseStage' undefined; DataProp 'hasOMIM' undefined; DataProp 'hasInheritance' undefined
A62: UC1-F1-P2-S1-M1 | B62: BD_Epid_Incidencia | C62: EpidemiologicalParameter | D62: =IF(ISBLANK(C62),0,LEN(C62)-LEN(SUBSTITUTE(C62,";",""))+1) -> 1 | E62: =IF(D62<2,C62,LEFT(C62,FIND(";",C62)-1)) -> EpidemiologicalParameter | F62: =IF(D62<1,FALSE,ISERROR(MATCH(E62,'Ontology and concepts per UC'!$A$2:$A$62,0))) -> FALSE | G62: =IF(D62<2,"",MID(C62,LEN(E62)+3,LEN(C62)-FIND(";",C62)-1)) | H62: =IF(D62<3,G62,LEFT(G62,FIND(";",G62)-1)) | I62: =IF(D62<2,FALSE,ISERROR(MATCH(H62,'Ontology and concepts per UC'!$A$2:$A$62,0))) -> FALSE | J62: =IF(D62<3,"",RIGHT(G62,LEN(G62)-FIND(";",G62)-1)) | K62: =IF(D62<3,FALSE,ISERROR(MATCH(J62,'Ontology and concepts per UC'!$A$2:$A$62,0))) -> FALSE | M62: hasSource:"Wolf 1995[4]; Baykal et al. 1998[3]"; hasExpectedValue:"1:60000"; | O62: FALSE | P62: 0 | Q62: 0 | R62: =NOT(ISERROR(SEARCH("hasSource",M62))) -> TRUE | S62: Prevalencia al nacimiento | T62: =IF(S62="","",VLOOKUP(S62,'Ontology and concepts per UC'!$F$2:$J$46,5,FALSE)) -> Parámetro epidemiológico | U62: {=(INDEX('Ontology and concepts per UC'!$G$2:$I$46,MATCH($S62,'Ontology and concepts per UC'!$F$2:$F$46,0),MATCH(LEFT($A62,3),'Ontology and concepts per UC'!$G$1:$I$1,0))=0)} -> FALSE | V62: =COUNTIF(W62:Z62,TRUE)>0 -> FALSE | W62: FALSE | X62: FALSE | Y62: FALSE | Z62: FALSE
A63: UC1-F1-P2-S1-M1 | B63: BD_Epid_IncidenciaGlobal | C63: EpidemiologicalParameter | D63: =IF(ISBLANK(C63),0,LEN(C63)-LEN(SUBSTITUTE(C63,";",""))+1) -> 1 | E63: =IF(D63<2,C63,LEFT(C63,FIND(";",C63)-1)) -> EpidemiologicalParameter | F63: =IF(D63<1,FALSE,ISERROR(MATCH(E63,'Ontology and concepts per UC'!$A$2:$A$62,0))) -> FALSE | G63: =IF(D63<2,"",MID(C63,LEN(E63)+3,LEN(C63)-FIND(";",C63)-1)) | H63: =IF(D63<3,G63,LEFT(G63,FIND(";",G63)-1)) | I63: =IF(D63<2,FALSE,ISERROR(MATCH(H63,'Ontology and concepts per UC'!$A$2:$A$62,0))) -> FALSE | J63: =IF(D63<3,"",RIGHT(G63,LEN(G63)-FIND(";",G63)-1)) | K63: =IF(D63<3,FALSE,ISERROR(MATCH(J63,'Ontology and concepts per UC'!$A$2:$A$62,0))) -> FALSE | M63: hasSource:"Couce et al. 2011[1]; Wolf 1995[4]"; hasExpectedValue:"1:60000"; | O63: FALSE | P63: 0 | Q63: 0 | R63: =NOT(ISERROR(SEARCH("hasSource",M63))) -> TRUE | S63: Prevalencia al nacimiento | T63: =IF(S63="","",VLOOKUP(S63,'Ontology and concepts per UC'!$F$2:$J$46,5,FALSE)) -> Parámetro epidemiológico | U63: {=(INDEX('Ontology and concepts per UC'!$G$2:$I$46,MATCH($S63,'Ontology and concepts per UC'!$F$2:$F$46,0),MATCH(LEFT($A63,3),'Ontology and concepts per UC'!$G$1:$I$1,0))=0)} -> FALSE | V63: =COUNTIF(W63:Z63,TRUE)>0 -> FALSE | W63: FALSE | X63: FALSE | Y63: FALSE | Z63: FALSE
A64: UC1-F1-P2-S1-M1 | B64: BD_Manif_Hipoacusia_Incidencia | C64: EpidemiologicalParameter | D64: =IF(ISBLANK(C64),0,LEN(C64)-LEN(SUBSTITUTE(C64,";",""))+1) -> 1 | E64: =IF(D64<2,C64,LEFT(C64,FIND(";",C64)-1)) -> EpidemiologicalParameter | F64: =IF(D64<1,FALSE,ISERROR(MATCH(E64,'Ontology and concepts per UC'!$A$2:$A$62,0))) -> FALSE | G64: =IF(D64<2,"",MID(C64,LEN(E64)+3,LEN(C64)-FIND(";",C64)-1)) | H64: =IF(D64<3,G64,LEFT(G64,FIND(";",G64)-1)) | I64: =IF(D64<2,FALSE,ISERROR(MATCH(H64,'Ontology and concepts per UC'!$A$2:$A$62,0))) -> FALSE | J64: =IF(D64<3,"",RIGHT(G64,LEN(G64)-FIND(";",G64)-1)) | K64: =IF(D64<3,FALSE,ISERROR(MATCH(J64,'Ontology and concepts per UC'!$A$2:$A$62,0))) -> FALSE | M64: hasSource:"Genc et al. 2007[4]; Wolf et al. 2002[7]"; hasExpectedValue:"0.55"; | O64: FALSE | P64: 0 | Q64: 0 | R64: =NOT(ISERROR(SEARCH("hasSource",M64))) -> TRUE | S64: Riesgo: Problemas de audición | T64: =IF(S64="","",VLOOKUP(S64,'Ontology and concepts per UC'!$F$2:$J$46,5,FALSE)) -> Parámetros de progresión | U64: {=(INDEX('Ontology and concepts per UC'!$G$2:$I$46,MATCH($S64,'Ontology and concepts per UC'!$F$2:$F$46,0),MATCH(LEFT($A64,3),'Ontology and concepts per UC'!$G$1:$I$1,0))=0)} -> FALSE | V64: =COUNTIF(W64:Z64,TRUE)>0 -> FALSE | W64: FALSE | X64: FALSE | Y64: FALSE | Z64: FALSE
A65: UC1-F1-P2-S1-M1 | B65: BD_Parcial_Incidencia | C65: EpidemiologicalParameter | D65: =IF(ISBLANK(C65),0,LEN(C65)-LEN(SUBSTITUTE(C65,";",""))+1) -> 1 | E65: =IF(D65<2,C65,LEFT(C65,FIND(";",C65)-1)) -> EpidemiologicalParameter | F65: =IF(D65<1,FALSE,ISERROR(MATCH(E65,'Ontology and concepts per UC'!$A$2:$A$62,0))) -> FALSE | G65: =IF(D65<2,"",MID(C65,LEN(E65)+3,LEN(C65)-FIND(";",C65)-1)) | H65: =IF(D65<3,G65,LEFT(G65,FIND(";",G65)-1)) | I65: =IF(D65<2,FALSE,ISERROR(MATCH(H65,'Ontology and concepts per UC'!$A$2:$A$62,0))) -> FALSE | J65: =IF(D65<3,"",RIGHT(G65,LEN(G65)-FIND(";",G65)-1)) | K65: =IF(D65<3,FALSE,ISERROR(MATCH(J65,'Ontology and concepts per UC'!$A$2:$A$62,0))) -> FALSE | M65: hasExpectedValue:"1:43,575"; hasSource:"Couce et al. 2011[1]"; | O65: FALSE | P65: 0 | Q65: 0 | R65: =NOT(ISERROR(SEARCH("hasSource",M65))) -> TRUE | S65: Parcial | T65: =IF(S65="","",VLOOKUP(S65,'Ontology and concepts per UC'!$F$2:$J$46,5,FALSE)) -> Parcial | U65: {=(INDEX('Ontology and concepts per UC'!$G$2:$I$46,MATCH($S65,'Ontology and concepts per UC'!$F$2:$F$46,0),MATCH(LEFT($A65,3),'Ontology and concepts per UC'!$G$1:$I$1,0))=0)} -> FALSE | V65: =COUNTIF(W65:Z65,TRUE)>0 -> FALSE | W65: FALSE | X65: FALSE | Y65: FALSE | Z65: FALSE
A66: UC1-F1-P2-S1-M1 | B66: BD_Profunda_Incidencia | C66: EpidemiologicalParameter | D66: =IF(ISBLANK(C66),0,LEN(C66)-LEN(SUBSTITUTE(C66,";",""))+1) -> 1 | E66: =IF(D66<2,C66,LEFT(C66,FIND(";",C66)-1)) -> EpidemiologicalParameter | F66: =IF(D66<1,FALSE,ISERROR(MATCH(E66,'Ontology and concepts per UC'!$A$2:$A$62,0))) -> FALSE | G66: =IF(D66<2,"",MID(C66,LEN(E66)+3,LEN(C66)-FIND(";",C66)-1)) | H66: =IF(D66<3,G66,LEFT(G66,FIND(";",G66)-1)) | I66: =IF(D66<2,FALSE,ISERROR(MATCH(H66,'Ontology and concepts per UC'!$A$2:$A$62,0))) -> FALSE | J66: =IF(D66<3,"",RIGHT(G66,LEN(G66)-FIND(";",G66)-1)) | K66: =IF(D66<3,FALSE,ISERROR(MATCH(J66,'Ontology and concepts per UC'!$A$2:$A$62,0))) -> FALSE | M66: hasExpectedValue:"1:187500"; hasSource:"Couce et al. 2011[1]; Baykal et al. 1998[3]"; | O66: FALSE | P66: 0 | Q66: 0 | R66: =NOT(ISERROR(SEARCH("hasSource",M66))) -> TRUE | S66: Prevalencia al nacimiento | T66: =IF(S66="","",VLOOKUP(S66,'Ontology and concepts per UC'!$F$2:$J$46,5,FALSE)) -> Parámetro epidemiológico | U66: {=(INDEX('Ontology and concepts per UC'!$G$2:$I$46,MATCH($S66,'Ontology and concepts per UC'!$F$2:$F$46,0),MATCH(LEFT($A66,3),'Ontology and concepts per UC'!$G$1:$I$1,0))=0)} -> FALSE | V66: =COUNTIF(W66:Z66,TRUE)>0 -> TRUE | W66: FALSE | X66: FALSE | Y66: FALSE | Z66: TRUE | AA66: Unsuitable value for property
A67: UC1-F1-P2-S1-M1 | B67: BD_Estadio_NoTratado | C67: EstadioEnfermedad | D67: =IF(ISBLANK(C67),0,LEN(C67)-LEN(SUBSTITUTE(C67,";",""))+1) -> 1 | E67: =IF(D67<2,C67,LEFT(C67,FIND(";",C67)-1)) -> EstadioEnfermedad | F67: =IF(D67<1,FALSE,ISERROR(MATCH(E67,'Ontology and concepts per UC'!$A$2:$A$62,0))) -> TRUE | G67: =IF(D67<2,"",MID(C67,LEN(E67)+3,LEN(C67)-FIND(";",C67)-1)) | H67: =IF(D67<3,G67,LEFT(G67,FIND(";",G67)-1)) | I67: =IF(D67<2,FALSE,ISERROR(MATCH(H67,'Ontology and concepts per UC'!$A$2:$A$62,0))) -> FALSE | J67: =IF(D67<3,"",RIGHT(G67,LEN(G67)-FIND(";",G67)-1)) | K67: =IF(D67<3,FALSE,ISERROR(MATCH(J67,'Ontology and concepts per UC'!$A$2:$A$62,0))) -> FALSE | L67: hasEpidemiologicalParameter:BD_Epid_IncidenciaGlobal; | M67: hasDescription:"Deficiencia profunda no tratada (actividad enzimática ≤10%) con manifestaciones neurológicas activas"; hasDescription:"Fase sintomática con afectación neurológica y metabólica activa"; | O67: FALSE | P67: 1 | Q67: 0 | R67: =NOT(ISERROR(SEARCH("hasSource",M67))) -> FALSE | S67: Otros | T67: =IF(S67="","",VLOOKUP(S67,'Ontology and concepts per UC'!$F$2:$J$46,5,FALSE)) -> Otros | U67: {=(INDEX('Ontology and concepts per UC'!$G$2:$I$46,MATCH($S67,'Ontology and concepts per UC'!$F$2:$F$46,0),MATCH(LEFT($A67,3),'Ontology and concepts per UC'!$G$1:$I$1,0))=0)} -> TRUE | V67: =COUNTIF(W67:Z67,TRUE)>0 -> TRUE | W67: TRUE | X67: FALSE | Y67: FALSE | Z67: FALSE | AA67: Class 'EstadioEnfermedad' undefined
A68: UC1-F1-P2-S1-M1 | B68: BD_Seguimiento_Parcial | C68: EstrategiaSeguimiento | D68: =IF(ISBLANK(C68),0,LEN(C68)-LEN(SUBSTITUTE(C68,";",""))+1) -> 1 | E68: =IF(D68<2,C68,LEFT(C68,FIND(";",C68)-1)) -> EstrategiaSeguimiento | F68: =IF(D68<1,FALSE,ISERROR(MATCH(E68,'Ontology and concepts per UC'!$A$2:$A$62,0))) -> TRUE | G68: =IF(D68<2,"",MID(C68,LEN(E68)+3,LEN(C68)-FIND(";",C68)-1)) | H68: =IF(D68<3,G68,LEFT(G68,FIND(";",G68)-1)) | I68: =IF(D68<2,FALSE,ISERROR(MATCH(H68,'Ontology and concepts per UC'!$A$2:$A$62,0))) -> FALSE | J68: =IF(D68<3,"",RIGHT(G68,LEN(G68)-FIND(";",G68)-1)) | K68: =IF(D68<3,FALSE,ISERROR(MATCH(J68,'Ontology and concepts per UC'!$A$2:$A$62,0))) -> FALSE | L68: appliesToDiseaseStage:BD_Estadio_Parcial; | M68: hasSource:"Ye et al. 2009[7]; Joshi et al. 1999[8]"; hasDescription:"Evaluación semestral: control metabólico y ajuste dosis biotina en situaciones de estrés. Screening audiológico bianual hasta adolescencia"; | O68: FALSE | P68: 1 | Q68: 1 | R68: =NOT(ISERROR(SEARCH("hasSource",M68))) -> TRUE | S68: Parcial | T68: =IF(S68="","",VLOOKUP(S68,'Ontology and concepts per UC'!$F$2:$J$46,5,FALSE)) -> Parcial | U68: {=(INDEX('Ontology and concepts per UC'!$G$2:$I$46,MATCH($S68,'Ontology and concepts per UC'!$F$2:$F$46,0),MATCH(LEFT($A68,3),'Ontology and concepts per UC'!$G$1:$I$1,0))=0)} -> FALSE | V68: =COUNTIF(W68:Z68,TRUE)>0 -> TRUE | W68: TRUE | X68: FALSE | Y68: FALSE | Z68: FALSE | AA68: Class 'EstrategiaSeguimiento' undefined; ObjectProp 'appliesToDiseaseStage' undefined
A69: UC1-F1-P2-S1-M1 | B69: BD_Seguimiento_Profundo | C69: EstrategiaSeguimiento | D69: =IF(ISBLANK(C69),0,LEN(C69)-LEN(SUBSTITUTE(C69,";",""))+1) -> 1 | E69: =IF(D69<2,C69,LEFT(C69,FIND(";",C69)-1)) -> EstrategiaSeguimiento | F69: =IF(D69<1,FALSE,ISERROR(MATCH(E69,'Ontology and concepts per UC'!$A$2:$A$62,0))) -> TRUE | G69: =IF(D69<2,"",MID(C69,LEN(E69)+3,LEN(C69)-FIND(";",C69)-1)) | H69: =IF(D69<3,G69,LEFT(G69,FIND(";",G69)-1)) | I69: =IF(D69<2,FALSE,ISERROR(MATCH(H69,'Ontology and concepts per UC'!$A$2:$A$62,0))) -> FALSE | J69: =IF(D69<3,"",RIGHT(G69,LEN(G69)-FIND(";",G69)-1)) | K69: =IF(D69<3,FALSE,ISERROR(MATCH(J69,'Ontology and concepts per UC'!$A$2:$A$62,0))) -> FALSE | L69: appliesToDiseaseStage:BD_Estadio_Profundo; | M69: hasDescription:"Monitorización trimestral: evaluación neurológica, auditiva y visual. Control bioquímico de metabolitos (3-HIA, MCC) y actividad enzimática cada 3 meses. EEG anual hasta estabilización"; hasSource:"Couce et al. 2011[1]; Weber et al. 2004[2]; Mslinger et al. 2003[6]"; | O69: FALSE | P69: 1 | Q69: 1 | R69: =NOT(ISERROR(SEARCH("hasSource",M69))) -> TRUE | S69: Seguimiento | T69: =IF(S69="","",VLOOKUP(S69,'Ontology and concepts per UC'!$F$2:$J$46,5,FALSE)) -> Tratamiento/seguimiento | U69: {=(INDEX('Ontology and concepts per UC'!$G$2:$I$46,MATCH($S69,'Ontology and concepts per UC'!$F$2:$F$46,0),MATCH(LEFT($A69,3),'Ontology and concepts per UC'!$G$1:$I$1,0))=0)} -> FALSE | V69: =COUNTIF(W69:Z69,TRUE)>0 -> TRUE | W69: TRUE | X69: FALSE | Y69: FALSE | Z69: FALSE | AA69: Class 'EstrategiaSeguimiento' undefined; ObjectProp 'appliesToDiseaseStage' undefined
A70: UC1-F1-P2-S1-M1 | B70: BD_Eval_Audiologica | C70: EvaluacionClinica | D70: =IF(ISBLANK(C70),0,LEN(C70)-LEN(SUBSTITUTE(C70,";",""))+1) -> 1 | E70: =IF(D70<2,C70,LEFT(C70,FIND(";",C70)-1)) -> EvaluacionClinica | F70: =IF(D70<1,FALSE,ISERROR(MATCH(E70,'Ontology and concepts per UC'!$A$2:$A$62,0))) -> TRUE | G70: =IF(D70<2,"",MID(C70,LEN(E70)+3,LEN(C70)-FIND(";",C70)-1)) | H70: =IF(D70<3,G70,LEFT(G70,FIND(";",G70)-1)) | I70: =IF(D70<2,FALSE,ISERROR(MATCH(H70,'Ontology and concepts per UC'!$A$2:$A$62,0))) -> FALSE | J70: =IF(D70<3,"",RIGHT(G70,LEN(G70)-FIND(";",G70)-1)) | K70: =IF(D70<3,FALSE,ISERROR(MATCH(J70,'Ontology and concepts per UC'!$A$2:$A$62,0))) -> FALSE | M70: hasDescription:"Potenciales evocados auditivos brainstem (BAEP) anuales durante primeros 5 años"; hasSource:"Wolf et al. 2002[5]; Genc et al. 2007[4]"; | O70: FALSE | P70: 1 | Q70: 0 | R70: =NOT(ISERROR(SEARCH("hasSource",M70))) -> TRUE | S70: Seguimiento | T70: =IF(S70="","",VLOOKUP(S70,'Ontology and concepts per UC'!$F$2:$J$46,5,FALSE)) -> Tratamiento/seguimiento | U70: {=(INDEX('Ontology and concepts per UC'!$G$2:$I$46,MATCH($S70,'Ontology and concepts per UC'!$F$2:$F$46,0),MATCH(LEFT($A70,3),'Ontology and concepts per UC'!$G$1:$I$1,0))=0)} -> FALSE | V70: =COUNTIF(W70:Z70,TRUE)>0 -> TRUE | W70: TRUE | X70: FALSE | Y70: FALSE | Z70: FALSE | AA70: Class 'EvaluacionClinica' undefined
A71: UC1-F1-P2-S1-M1 | B71: BD_Intervencion_CribadoNeonatal | C71: IntervencionCribado | D71: =IF(ISBLANK(C71),0,LEN(C71)-LEN(SUBSTITUTE(C71,";",""))+1) -> 1 | E71: =IF(D71<2,C71,LEFT(C71,FIND(";",C71)-1)) -> IntervencionCribado | F71: =IF(D71<1,FALSE,ISERROR(MATCH(E71,'Ontology and concepts per UC'!$A$2:$A$62,0))) -> TRUE | G71: =IF(D71<2,"",MID(C71,LEN(E71)+3,LEN(C71)-FIND(";",C71)-1)) | H71: =IF(D71<3,G71,LEFT(G71,FIND(";",G71)-1)) | I71: =IF(D71<2,FALSE,ISERROR(MATCH(H71,'Ontology and concepts per UC'!$A$2:$A$62,0))) -> FALSE | J71: =IF(D71<3,"",RIGHT(G71,LEN(G71)-FIND(";",G71)-1)) | K71: =IF(D71<3,FALSE,ISERROR(MATCH(J71,'Ontology and concepts per UC'!$A$2:$A$62,0))) -> FALSE | L71: previeneEstadio:BD_Estadio_NoTratado; | M71: hasEficacia:"Reducción del 95% en manifestaciones neurológicas con tratamiento antes de los 3 meses"; hasCostoUnitario:"2150€ por caso detectado (Ye et al. 2009)"; hasSource:"Couce et al. 2011[1]; Weber et al. 2004[5]"; hasDescription:"Ensayo enzimático fluorimétrico en sangre en papel para detección precoz"; | O71: FALSE | P71: 1 | Q71: 3 | R71: =NOT(ISERROR(SEARCH("hasSource",M71))) -> TRUE | S71: Caracterización cribado | T71: =IF(S71="","",VLOOKUP(S71,'Ontology and concepts per UC'!$F$2:$J$46,5,FALSE)) -> Parámetros de intervención | U71: {=(INDEX('Ontology and concepts per UC'!$G$2:$I$46,MATCH($S71,'Ontology and concepts per UC'!$F$2:$F$46,0),MATCH(LEFT($A71,3),'Ontology and concepts per UC'!$G$1:$I$1,0))=0)} -> FALSE | V71: =COUNTIF(W71:Z71,TRUE)>0 -> TRUE | W71: TRUE | X71: FALSE | Y71: FALSE | Z71: FALSE | AA71: Class 'IntervencionCribado' undefined; ObjectProp 'previeneEstadio' undefined; DataProp 'hasEficacia' undefined; DataProp 'hasCostoUnitario' undefined
A72: UC1-F1-P2-S1-M1 | B72: BD_Intervencion_Cribado | C72: IntervencionCribado; Intervencion | D72: =IF(ISBLANK(C72),0,LEN(C72)-LEN(SUBSTITUTE(C72,";",""))+1) -> 2 | E72: =IF(D72<2,C72,LEFT(C72,FIND(";",C72)-1)) -> IntervencionCribado | F72: =IF(D72<1,FALSE,ISERROR(MATCH(E72,'Ontology and concepts per UC'!$A$2:$A$62,0))) -> TRUE | G72: =IF(D72<2,"",MID(C72,LEN(E72)+3,LEN(C72)-FIND(";",C72)-1)) -> Intervencion | H72: =IF(D72<3,G72,LEFT(G72,FIND(";",G72)-1)) -> Intervencion | I72: =IF(D72<2,FALSE,ISERROR(MATCH(H72,'Ontology and concepts per UC'!$A$2:$A$62,0))) -> TRUE | J72: =IF(D72<3,"",RIGHT(G72,LEN(G72)-FIND(";",G72)-1)) | K72: =IF(D72<3,FALSE,ISERROR(MATCH(J72,'Ontology and concepts per UC'!$A$2:$A$62,0))) -> FALSE | L72: affectsDiseaseStage:BD_Estadio_NoTratado; | M72: hasEffect:"Reducción del 95% en manifestaciones neurológicas cuando se trata antes de los 3 meses"; hasCostoUnitario:"2150€ por caso detectado"; hasEficacia:"Reducción del 95% en manifestaciones neurológicas con tratamiento temprano"; hasDescription:"Cribado neonatal mediante ensayo enzimático fluorimétrico en papel"; | O72: FALSE | P72: 2 | Q72: 4 | R72: =NOT(ISERROR(SEARCH("hasSource",M72))) -> FALSE | S72: Intervención: Cribado | T72: =IF(S72="","",VLOOKUP(S72,'Ontology and concepts per UC'!$F$2:$J$46,5,FALSE)) -> Modelo Conceptual | U72: {=(INDEX('Ontology and concepts per UC'!$G$2:$I$46,MATCH($S72,'Ontology and concepts per UC'!$F$2:$F$46,0),MATCH(LEFT($A72,3),'Ontology and concepts per UC'!$G$1:$I$1,0))=0)} -> FALSE | V72: =COUNTIF(W72:Z72,TRUE)>0 -> TRUE | W72: TRUE | X72: FALSE | Y72: FALSE | Z72: FALSE | AA72: Class 'IntervencionCribado' undefined; Class 'Intervencion' undefined; ObjectProp 'affectsDiseaseStage' undefined; DataProp 'hasEffect' undefined; DataProp 'hasCostoUnitario' undefined; DataProp 'hasEficacia' undefined
A73: UC1-F1-P2-S1-M1 | B73: BD_Intervencion_Biotina | C73: IntervencionFarmacologica | D73: =IF(ISBLANK(C73),0,LEN(C73)-LEN(SUBSTITUTE(C73,";",""))+1) -> 1 | E73: =IF(D73<2,C73,LEFT(C73,FIND(";",C73)-1)) -> IntervencionFarmacologica | F73: =IF(D73<1,FALSE,ISERROR(MATCH(E73,'Ontology and concepts per UC'!$A$2:$A$62,0))) -> TRUE | G73: =IF(D73<2,"",MID(C73,LEN(E73)+3,LEN(C73)-FIND(";",C73)-1)) | H73: =IF(D73<3,G73,LEFT(G73,FIND(";",G73)-1)) | I73: =IF(D73<2,FALSE,ISERROR(MATCH(H73,'Ontology and concepts per UC'!$A$2:$A$62,0))) -> FALSE | J73: =IF(D73<3,"",RIGHT(G73,LEN(G73)-FIND(";",G73)-1)) | K73: =IF(D73<3,FALSE,ISERROR(MATCH(J73,'Ontology and concepts per UC'!$A$2:$A$62,0))) -> FALSE | L73: trataManifestacion:BD_Manif_Convulsiones; | M73: hasDescription:"Suplementación oral con biotina 10-30 mg/día"; hasDosis:"10-30 mg/día (Joshi et al. 1999[3]; Mslinger et al. 2003[2])"; hasEfectoBioquimico:"Restauración de actividad carboxilasa en 48-72 horas"; | O73: FALSE | P73: 1 | Q73: 3 | R73: =NOT(ISERROR(SEARCH("hasSource",M73))) -> FALSE | S73: Tratamiento base | T73: =IF(S73="","",VLOOKUP(S73,'Ontology and concepts per UC'!$F$2:$J$46,5,FALSE)) -> Tratamiento/seguimiento | U73: {=(INDEX('Ontology and concepts per UC'!$G$2:$I$46,MATCH($S73,'Ontology and concepts per UC'!$F$2:$F$46,0),MATCH(LEFT($A73,3),'Ontology and concepts per UC'!$G$1:$I$1,0))=0)} -> FALSE | V73: =COUNTIF(W73:Z73,TRUE)>0 -> TRUE | W73: TRUE | X73: FALSE | Y73: FALSE | Z73: TRUE | AA73: Class 'IntervencionFarmacologica' undefined; ObjectProp 'trataManifestacion' undefined; DataProp 'hasDosis' undefined; DataProp 'hasEfectoBioquimico' undefined; should not be an intervention
A74: UC1-F1-P2-S1-M1 | B74: BD_Manif_ConvulsionesAgudas | C74: ManifestacionAguda | D74: =IF(ISBLANK(C74),0,LEN(C74)-LEN(SUBSTITUTE(C74,";",""))+1) -> 1 | E74: =IF(D74<2,C74,LEFT(C74,FIND(";",C74)-1)) -> ManifestacionAguda | F74: =IF(D74<1,FALSE,ISERROR(MATCH(E74,'Ontology and concepts per UC'!$A$2:$A$62,0))) -> TRUE | G74: =IF(D74<2,"",MID(C74,LEN(E74)+3,LEN(C74)-FIND(";",C74)-1)) | H74: =IF(D74<3,G74,LEFT(G74,FIND(";",G74)-1)) | I74: =IF(D74<2,FALSE,ISERROR(MATCH(H74,'Ontology and concepts per UC'!$A$2:$A$62,0))) -> FALSE | J74: =IF(D74<3,"",RIGHT(G74,LEN(G74)-FIND(";",G74)-1)) | K74: =IF(D74<3,FALSE,ISERROR(MATCH(J74,'Ontology and concepts per UC'!$A$2:$A$62,0))) -> FALSE | M74: hasOnsetTime:"2"; hasDescription:"Convulsiones mioclónicas típicamente entre 2-4 meses no tratados"; | O74: FALSE | P74: 1 | Q74: 1 | R74: =NOT(ISERROR(SEARCH("hasSource",M74))) -> FALSE | S74: Manifestación: Convulsiones | T74: =IF(S74="","",VLOOKUP(S74,'Ontology and concepts per UC'!$F$2:$J$46,5,FALSE)) -> Modelo Conceptual | U74: {=(INDEX('Ontology and concepts per UC'!$G$2:$I$46,MATCH($S74,'Ontology and concepts per UC'!$F$2:$F$46,0),MATCH(LEFT($A74,3),'Ontology and concepts per UC'!$G$1:$I$1,0))=0)} -> FALSE | V74: =COUNTIF(W74:Z74,TRUE)>0 -> TRUE | W74: TRUE | X74: FALSE | Y74: FALSE | Z74: FALSE | AA74: Class 'ManifestacionAguda' undefined; DataProp 'hasOnsetTime' undefined
A75: UC1-F1-P2-S1-M1 | B75: BD_Manif_DermatitisAguda | C75: ManifestacionAguda | D75: =IF(ISBLANK(C75),0,LEN(C75)-LEN(SUBSTITUTE(C75,";",""))+1) -> 1 | E75: =IF(D75<2,C75,LEFT(C75,FIND(";",C75)-1)) -> ManifestacionAguda | F75: =IF(D75<1,FALSE,ISERROR(MATCH(E75,'Ontology and concepts per UC'!$A$2:$A$62,0))) -> TRUE | G75: =IF(D75<2,"",MID(C75,LEN(E75)+3,LEN(C75)-FIND(";",C75)-1)) | H75: =IF(D75<3,G75,LEFT(G75,FIND(";",G75)-1)) | I75: =IF(D75<2,FALSE,ISERROR(MATCH(H75,'Ontology and concepts per UC'!$A$2:$A$62,0))) -> FALSE | J75: =IF(D75<3,"",RIGHT(G75,LEN(G75)-FIND(";",G75)-1)) | K75: =IF(D75<3,FALSE,ISERROR(MATCH(J75,'Ontology and concepts per UC'!$A$2:$A$62,0))) -> FALSE | M75: hasOnsetTime:"3"; | O75: FALSE | P75: 1 | Q75: 1 | R75: =NOT(ISERROR(SEARCH("hasSource",M75))) -> FALSE | S75: Manifestación: Problemas en la piel | T75: =IF(S75="","",VLOOKUP(S75,'Ontology and concepts per UC'!$F$2:$J$46,5,FALSE)) -> Modelo Conceptual | U75: {=(INDEX('Ontology and concepts per UC'!$G$2:$I$46,MATCH($S75,'Ontology and concepts per UC'!$F$2:$F$46,0),MATCH(LEFT($A75,3),'Ontology and concepts per UC'!$G$1:$I$1,0))=0)} -> FALSE | V75: =COUNTIF(W75:Z75,TRUE)>0 -> TRUE | W75: TRUE | X75: FALSE | Y75: FALSE | Z75: FALSE | AA75: Class 'ManifestacionAguda' undefined; DataProp 'hasOnsetTime' undefined
A76: UC1-F1-P2-S1-M1 | B76: BD_Manif_Convulsiones | C76: ManifestacionClinica | D76: =IF(ISBLANK(C76),0,LEN(C76)-LEN(SUBSTITUTE(C76,";",""))+1) -> 1 | E76: =IF(D76<2,C76,LEFT(C76,FIND(";",C76)-1)) -> ManifestacionClinica | F76: =IF(D76<1,FALSE,ISERROR(MATCH(E76,'Ontology and concepts per UC'!$A$2:$A$62,0))) -> TRUE | G76: =IF(D76<2,"",MID(C76,LEN(E76)+3,LEN(C76)-FIND(";",C76)-1)) | H76: =IF(D76<3,G76,LEFT(G76,FIND(";",G76)-1)) | I76: =IF(D76<2,FALSE,ISERROR(MATCH(H76,'Ontology and concepts per UC'!$A$2:$A$62,0))) -> FALSE | J76: =IF(D76<3,"",RIGHT(G76,LEN(G76)-FIND(";",G76)-1)) | K76: =IF(D76<3,FALSE,ISERROR(MATCH(J76,'Ontology and concepts per UC'!$A$2:$A$62,0))) -> FALSE | L76: affectsUtility:BD_Manif_Convulsiones_U; | M76: hasSource:"Couce et al. 2011[1]; Weber et al. 2004[2]"; hasSource:"Weber et al. 2004[2]; Grünewald et al. 2003[3]"; hasDescription:"Convulsiones mioclónicas o tónico-clónicas, frecuentes en pacientes no tratados"; hasProbability:"0.78"; | O76: FALSE | P76: 1 | Q76: 2 | R76: =NOT(ISERROR(SEARCH("hasSource",M76))) -> TRUE | S76: Manifestación: Convulsiones | T76: =IF(S76="","",VLOOKUP(S76,'Ontology and concepts per UC'!$F$2:$J$46,5,FALSE)) -> Modelo Conceptual | U76: {=(INDEX('Ontology and concepts per UC'!$G$2:$I$46,MATCH($S76,'Ontology and concepts per UC'!$F$2:$F$46,0),MATCH(LEFT($A76,3),'Ontology and concepts per UC'!$G$1:$I$1,0))=0)} -> FALSE | V76: =COUNTIF(W76:Z76,TRUE)>0 -> TRUE | W76: TRUE | X76: FALSE | Y76: FALSE | Z76: FALSE | AA76: Class 'ManifestacionClinica' undefined; ObjectProp 'affectsUtility' undefined; DataProp 'hasProbability' undefined
A77: UC1-F1-P2-S1-M1 | B77: BD_Manif_ConvulsionesMioclonicas | C77: ManifestacionClinica | D77: =IF(ISBLANK(C77),0,LEN(C77)-LEN(SUBSTITUTE(C77,";",""))+1) -> 1 | E77: =IF(D77<2,C77,LEFT(C77,FIND(";",C77)-1)) -> ManifestacionClinica | F77: =IF(D77<1,FALSE,ISERROR(MATCH(E77,'Ontology and concepts per UC'!$A$2:$A$62,0))) -> TRUE | G77: =IF(D77<2,"",MID(C77,LEN(E77)+3,LEN(C77)-FIND(";",C77)-1)) | H77: =IF(D77<3,G77,LEFT(G77,FIND(";",G77)-1)) | I77: =IF(D77<2,FALSE,ISERROR(MATCH(H77,'Ontology and concepts per UC'!$A$2:$A$62,0))) -> FALSE | J77: =IF(D77<3,"",RIGHT(G77,LEN(G77)-FIND(";",G77)-1)) | K77: =IF(D77<3,FALSE,ISERROR(MATCH(J77,'Ontology and concepts per UC'!$A$2:$A$62,0))) -> FALSE | M77: hasDescription:"Convulsiones mioclónicas refractarias, frecuentes en crisis agudas no tratadas"; hasSource:"Couce et al. 2011[1]; Wolf et al. 2002[7]"; | O77: FALSE | P77: 1 | Q77: 0 | R77: =NOT(ISERROR(SEARCH("hasSource",M77))) -> TRUE | S77: Manifestación: Convulsiones | T77: =IF(S77="","",VLOOKUP(S77,'Ontology and concepts per UC'!$F$2:$J$46,5,FALSE)) -> Modelo Conceptual | U77: {=(INDEX('Ontology and concepts per UC'!$G$2:$I$46,MATCH($S77,'Ontology and concepts per UC'!$F$2:$F$46,0),MATCH(LEFT($A77,3),'Ontology and concepts per UC'!$G$1:$I$1,0))=0)} -> FALSE | V77: =COUNTIF(W77:Z77,TRUE)>0 -> TRUE | W77: TRUE | X77: FALSE | Y77: FALSE | Z77: FALSE | AA77: Class 'ManifestacionClinica' undefined
A78: UC1-F1-P2-S1-M1 | B78: BD_Manif_Dermatitis | C78: ManifestacionClinica | D78: =IF(ISBLANK(C78),0,LEN(C78)-LEN(SUBSTITUTE(C78,";",""))+1) -> 1 | E78: =IF(D78<2,C78,LEFT(C78,FIND(";",C78)-1)) -> ManifestacionClinica | F78: =IF(D78<1,FALSE,ISERROR(MATCH(E78,'Ontology and concepts per UC'!$A$2:$A$62,0))) -> TRUE | G78: =IF(D78<2,"",MID(C78,LEN(E78)+3,LEN(C78)-FIND(";",C78)-1)) | H78: =IF(D78<3,G78,LEFT(G78,FIND(";",G78)-1)) | I78: =IF(D78<2,FALSE,ISERROR(MATCH(H78,'Ontology and concepts per UC'!$A$2:$A$62,0))) -> FALSE | J78: =IF(D78<3,"",RIGHT(G78,LEN(G78)-FIND(";",G78)-1)) | K78: =IF(D78<3,FALSE,ISERROR(MATCH(J78,'Ontology and concepts per UC'!$A$2:$A$62,0))) -> FALSE | L78: affectsUtility:BD_Manif_Dermatitis_U; | M78: hasProbability:"0.45"; hasSource:"Salbert et al. 1993[5]; Mslinger et al. 2003[6]"; | O78: FALSE | P78: 1 | Q78: 2 | R78: =NOT(ISERROR(SEARCH("hasSource",M78))) -> TRUE | S78: Manifestación: Problemas en la piel | T78: =IF(S78="","",VLOOKUP(S78,'Ontology and concepts per UC'!$F$2:$J$46,5,FALSE)) -> Modelo Conceptual | U78: {=(INDEX('Ontology and concepts per UC'!$G$2:$I$46,MATCH($S78,'Ontology and concepts per UC'!$F$2:$F$46,0),MATCH(LEFT($A78,3),'Ontology and concepts per UC'!$G$1:$I$1,0))=0)} -> FALSE | V78: =COUNTIF(W78:Z78,TRUE)>0 -> TRUE | W78: TRUE | X78: FALSE | Y78: FALSE | Z78: FALSE | AA78: Class 'ManifestacionClinica' undefined; ObjectProp 'affectsUtility' undefined; DataProp 'hasProbability' undefined
A79: UC1-F1-P2-S1-M1 | B79: BD_Manif_DermatitisExudativa | C79: ManifestacionClinica | D79: =IF(ISBLANK(C79),0,LEN(C79)-LEN(SUBSTITUTE(C79,";",""))+1) -> 1 | E79: =IF(D79<2,C79,LEFT(C79,FIND(";",C79)-1)) -> ManifestacionClinica | F79: =IF(D79<1,FALSE,ISERROR(MATCH(E79,'Ontology and concepts per UC'!$A$2:$A$62,0))) -> TRUE | G79: =IF(D79<2,"",MID(C79,LEN(E79)+3,LEN(C79)-FIND(";",C79)-1)) | H79: =IF(D79<3,G79,LEFT(G79,FIND(";",G79)-1)) | I79: =IF(D79<2,FALSE,ISERROR(MATCH(H79,'Ontology and concepts per UC'!$A$2:$A$62,0))) -> FALSE | J79: =IF(D79<3,"",RIGHT(G79,LEN(G79)-FIND(";",G79)-1)) | K79: =IF(D79<3,FALSE,ISERROR(MATCH(J79,'Ontology and concepts per UC'!$A$2:$A$62,0))) -> FALSE | M79: hasSource:"Salbert et al. 1993[5]; Wolf 2001[7]"; hasDescription:"Dermatitis exudativa perioral con sobreinfección por Candida"; | O79: FALSE | P79: 1 | Q79: 0 | R79: =NOT(ISERROR(SEARCH("hasSource",M79))) -> TRUE | S79: Manifestación: Problemas en la piel | T79: =IF(S79="","",VLOOKUP(S79,'Ontology and concepts per UC'!$F$2:$J$46,5,FALSE)) -> Modelo Conceptual | U79: {=(INDEX('Ontology and concepts per UC'!$G$2:$I$46,MATCH($S79,'Ontology and concepts per UC'!$F$2:$F$46,0),MATCH(LEFT($A79,3),'Ontology and concepts per UC'!$G$1:$I$1,0))=0)} -> FALSE | V79: =COUNTIF(W79:Z79,TRUE)>0 -> TRUE | W79: TRUE | X79: FALSE | Y79: FALSE | Z79: FALSE | AA79: Class 'ManifestacionClinica' undefined
A80: UC1-F1-P2-S1-M1 | B80: BD_Manif_EstridorLaríngeo | C80: ManifestacionClinica | D80: =IF(ISBLANK(C80),0,LEN(C80)-LEN(SUBSTITUTE(C80,";",""))+1) -> 1 | E80: =IF(D80<2,C80,LEFT(C80,FIND(";",C80)-1)) -> ManifestacionClinica | F80: =IF(D80<1,FALSE,ISERROR(MATCH(E80,'Ontology and concepts per UC'!$A$2:$A$62,0))) -> TRUE | G80: =IF(D80<2,"",MID(C80,LEN(E80)+3,LEN(C80)-FIND(";",C80)-1)) | H80: =IF(D80<3,G80,LEFT(G80,FIND(";",G80)-1)) | I80: =IF(D80<2,FALSE,ISERROR(MATCH(H80,'Ontology and concepts per UC'!$A$2:$A$62,0))) -> FALSE | J80: =IF(D80<3,"",RIGHT(G80,LEN(G80)-FIND(";",G80)-1)) | K80: =IF(D80<3,FALSE,ISERROR(MATCH(J80,'Ontology and concepts per UC'!$A$2:$A$62,0))) -> FALSE | M80: hasDescription:"Estridor laríngeo y apnea central por hipoventilación"; hasSource:"Weber et al. 2004[2]; Dionisi-Vici et al. 1988[1]"; | O80: FALSE | P80: 1 | Q80: 0 | R80: =NOT(ISERROR(SEARCH("hasSource",M80))) -> TRUE | S80: Otras manifestaciones | T80: =IF(S80="","",VLOOKUP(S80,'Ontology and concepts per UC'!$F$2:$J$46,5,FALSE)) -> Modelo Conceptual | U80: {=(INDEX('Ontology and concepts per UC'!$G$2:$I$46,MATCH($S80,'Ontology and concepts per UC'!$F$2:$F$46,0),MATCH(LEFT($A80,3),'Ontology and concepts per UC'!$G$1:$I$1,0))=0)} -> FALSE | V80: =COUNTIF(W80:Z80,TRUE)>0 -> TRUE | W80: TRUE | X80: FALSE | Y80: FALSE | Z80: FALSE | AA80: Class 'ManifestacionClinica' undefined
A81: UC1-F1-P2-S1-M1 | B81: BD_Manif_Hipoacusia | C81: ManifestacionClinica | D81: =IF(ISBLANK(C81),0,LEN(C81)-LEN(SUBSTITUTE(C81,";",""))+1) -> 1 | E81: =IF(D81<2,C81,LEFT(C81,FIND(";",C81)-1)) -> ManifestacionClinica | F81: =IF(D81<1,FALSE,ISERROR(MATCH(E81,'Ontology and concepts per UC'!$A$2:$A$62,0))) -> TRUE | G81: =IF(D81<2,"",MID(C81,LEN(E81)+3,LEN(C81)-FIND(";",C81)-1)) | H81: =IF(D81<3,G81,LEFT(G81,FIND(";",G81)-1)) | I81: =IF(D81<2,FALSE,ISERROR(MATCH(H81,'Ontology and concepts per UC'!$A$2:$A$62,0))) -> FALSE | J81: =IF(D81<3,"",RIGHT(G81,LEN(G81)-FIND(";",G81)-1)) | K81: =IF(D81<3,FALSE,ISERROR(MATCH(J81,'Ontology and concepts per UC'!$A$2:$A$62,0))) -> FALSE | L81: affectsUtility:BD_Manif_Hipoacusia_U; | M81: hasPrevalencia:"55% en casos sintomáticos"; hasSource:"Genc et al. 2007[5]; Wolf et al. 2002[6]"; hasSource:"Genc et al. 2007[4]; Wolf et al. 2002[7]"; hasSource:"Wolf et al. 2002[5]; Grünewald et al. 2003[3]"; hasDescription:"Hipoacusia neurosensorial bilateral, prevalente en 55% de casos sintomáticos"; hasProbability:"0.55"; | O81: FALSE | P81: 1 | Q81: 3 | R81: =NOT(ISERROR(SEARCH("hasSource",M81))) -> TRUE | S81: Manifestación: Problemas de audición | T81: =IF(S81="","",VLOOKUP(S81,'Ontology and concepts per UC'!$F$2:$J$46,5,FALSE)) -> Modelo Conceptual | U81: {=(INDEX('Ontology and concepts per UC'!$G$2:$I$46,MATCH($S81,'Ontology and concepts per UC'!$F$2:$F$46,0),MATCH(LEFT($A81,3),'Ontology and concepts per UC'!$G$1:$I$1,0))=0)} -> FALSE | V81: =COUNTIF(W81:Z81,TRUE)>0 -> TRUE | W81: TRUE | X81: FALSE | Y81: FALSE | Z81: FALSE | AA81: Class 'ManifestacionClinica' undefined; ObjectProp 'affectsUtility' undefined; DataProp 'hasPrevalencia' undefined; DataProp 'hasProbability' undefined
A82: UC1-F1-P2-S1-M1 | B82: BD_Manif_Hipotonia | C82: ManifestacionClinica | D82: =IF(ISBLANK(C82),0,LEN(C82)-LEN(SUBSTITUTE(C82,";",""))+1) -> 1 | E82: =IF(D82<2,C82,LEFT(C82,FIND(";",C82)-1)) -> ManifestacionClinica | F82: =IF(D82<1,FALSE,ISERROR(MATCH(E82,'Ontology and concepts per UC'!$A$2:$A$62,0))) -> TRUE | G82: =IF(D82<2,"",MID(C82,LEN(E82)+3,LEN(C82)-FIND(";",C82)-1)) | H82: =IF(D82<3,G82,LEFT(G82,FIND(";",G82)-1)) | I82: =IF(D82<2,FALSE,ISERROR(MATCH(H82,'Ontology and concepts per UC'!$A$2:$A$62,0))) -> FALSE | J82: =IF(D82<3,"",RIGHT(G82,LEN(G82)-FIND(";",G82)-1)) | K82: =IF(D82<3,FALSE,ISERROR(MATCH(J82,'Ontology and concepts per UC'!$A$2:$A$62,0))) -> FALSE | M82: hasProbability:"0.68"; hasSource:"Grünewald et al. 2003[3]; Couce et al. 2011[1]"; | O82: FALSE | P82: 1 | Q82: 1 | R82: =NOT(ISERROR(SEARCH("hasSource",M82))) -> TRUE | S82: Manifestación: Hipotonía | T82: =IF(S82="","",VLOOKUP(S82,'Ontology and concepts per UC'!$F$2:$J$46,5,FALSE)) -> Modelo Conceptual | U82: {=(INDEX('Ontology and concepts per UC'!$G$2:$I$46,MATCH($S82,'Ontology and concepts per UC'!$F$2:$F$46,0),MATCH(LEFT($A82,3),'Ontology and concepts per UC'!$G$1:$I$1,0))=0)} -> FALSE | V82: =COUNTIF(W82:Z82,TRUE)>0 -> TRUE | W82: TRUE | X82: FALSE | Y82: FALSE | Z82: FALSE | AA82: Class 'ManifestacionClinica' undefined; DataProp 'hasProbability' undefined
A83: UC1-F1-P2-S1-M1 | B83: BD_Parcial_Alopecia | C83: ManifestacionClinica | D83: =IF(ISBLANK(C83),0,LEN(C83)-LEN(SUBSTITUTE(C83,";",""))+1) -> 1 | E83: =IF(D83<2,C83,LEFT(C83,FIND(";",C83)-1)) -> ManifestacionClinica | F83: =IF(D83<1,FALSE,ISERROR(MATCH(E83,'Ontology and concepts per UC'!$A$2:$A$62,0))) -> TRUE | G83: =IF(D83<2,"",MID(C83,LEN(E83)+3,LEN(C83)-FIND(";",C83)-1)) | H83: =IF(D83<3,G83,LEFT(G83,FIND(";",G83)-1)) | I83: =IF(D83<2,FALSE,ISERROR(MATCH(H83,'Ontology and concepts per UC'!$A$2:$A$62,0))) -> FALSE | J83: =IF(D83<3,"",RIGHT(G83,LEN(G83)-FIND(";",G83)-1)) | K83: =IF(D83<3,FALSE,ISERROR(MATCH(J83,'Ontology and concepts per UC'!$A$2:$A$62,0))) -> FALSE | M83: hasSource:"Couce et al. 2011[1]; Grünewald et al. 2003[3]"; hasProbability:"0.20"; | O83: FALSE | P83: 1 | Q83: 1 | R83: =NOT(ISERROR(SEARCH("hasSource",M83))) -> TRUE | S83: Parcial | T83: =IF(S83="","",VLOOKUP(S83,'Ontology and concepts per UC'!$F$2:$J$46,5,FALSE)) -> Parcial | U83: {=(INDEX('Ontology and concepts per UC'!$G$2:$I$46,MATCH($S83,'Ontology and concepts per UC'!$F$2:$F$46,0),MATCH(LEFT($A83,3),'Ontology and concepts per UC'!$G$1:$I$1,0))=0)} -> FALSE | V83: =COUNTIF(W83:Z83,TRUE)>0 -> TRUE | W83: TRUE | X83: FALSE | Y83: FALSE | Z83: FALSE | AA83: Class 'ManifestacionClinica' undefined; DataProp 'hasProbability' undefined
A84: UC1-F1-P2-S1-M1 | B84: BD_Parcial_Convulsiones | C84: ManifestacionClinica | D84: =IF(ISBLANK(C84),0,LEN(C84)-LEN(SUBSTITUTE(C84,";",""))+1) -> 1 | E84: =IF(D84<2,C84,LEFT(C84,FIND(";",C84)-1)) -> ManifestacionClinica | F84: =IF(D84<1,FALSE,ISERROR(MATCH(E84,'Ontology and concepts per UC'!$A$2:$A$62,0))) -> TRUE | G84: =IF(D84<2,"",MID(C84,LEN(E84)+3,LEN(C84)-FIND(";",C84)-1)) | H84: =IF(D84<3,G84,LEFT(G84,FIND(";",G84)-1)) | I84: =IF(D84<2,FALSE,ISERROR(MATCH(H84,'Ontology and concepts per UC'!$A$2:$A$62,0))) -> FALSE | J84: =IF(D84<3,"",RIGHT(G84,LEN(G84)-FIND(";",G84)-1)) | K84: =IF(D84<3,FALSE,ISERROR(MATCH(J84,'Ontology and concepts per UC'!$A$2:$A$62,0))) -> FALSE | M84: hasProbability:"0.05"; hasSource:"Couce et al. 2011[1]; Weber et al. 2004[2]"; | O84: FALSE | P84: 1 | Q84: 1 | R84: =NOT(ISERROR(SEARCH("hasSource",M84))) -> TRUE | S84: Parcial | T84: =IF(S84="","",VLOOKUP(S84,'Ontology and concepts per UC'!$F$2:$J$46,5,FALSE)) -> Parcial | U84: {=(INDEX('Ontology and concepts per UC'!$G$2:$I$46,MATCH($S84,'Ontology and concepts per UC'!$F$2:$F$46,0),MATCH(LEFT($A84,3),'Ontology and concepts per UC'!$G$1:$I$1,0))=0)} -> FALSE | V84: =COUNTIF(W84:Z84,TRUE)>0 -> TRUE | W84: TRUE | X84: FALSE | Y84: FALSE | Z84: FALSE | AA84: Class 'ManifestacionClinica' undefined; DataProp 'hasProbability' undefined
A85: UC1-F1-P2-S1-M1 | B85: BD_Parcial_Dermatitis | C85: ManifestacionClinica | D85: =IF(ISBLANK(C85),0,LEN(C85)-LEN(SUBSTITUTE(C85,";",""))+1) -> 1 | E85: =IF(D85<2,C85,LEFT(C85,FIND(";",C85)-1)) -> ManifestacionClinica | F85: =IF(D85<1,FALSE,ISERROR(MATCH(E85,'Ontology and concepts per UC'!$A$2:$A$62,0))) -> TRUE | G85: =IF(D85<2,"",MID(C85,LEN(E85)+3,LEN(C85)-FIND(";",C85)-1)) | H85: =IF(D85<3,G85,LEFT(G85,FIND(";",G85)-1)) | I85: =IF(D85<2,FALSE,ISERROR(MATCH(H85,'Ontology and concepts per UC'!$A$2:$A$62,0))) -> FALSE | J85: =IF(D85<3,"",RIGHT(G85,LEN(G85)-FIND(";",G85)-1)) | K85: =IF(D85<3,FALSE,ISERROR(MATCH(J85,'Ontology and concepts per UC'!$A$2:$A$62,0))) -> FALSE | M85: hasSource:"Salbert et al. 1993[5]; Joshi et al. 1999[7]"; hasProbability:"0.15"; | O85: FALSE | P85: 1 | Q85: 1 | R85: =NOT(ISERROR(SEARCH("hasSource",M85))) -> TRUE | S85: Parcial | T85: =IF(S85="","",VLOOKUP(S85,'Ontology and concepts per UC'!$F$2:$J$46,5,FALSE)) -> Parcial | U85: {=(INDEX('Ontology and concepts per UC'!$G$2:$I$46,MATCH($S85,'Ontology and concepts per UC'!$F$2:$F$46,0),MATCH(LEFT($A85,3),'Ontology and concepts per UC'!$G$1:$I$1,0))=0)} -> FALSE | V85: =COUNTIF(W85:Z85,TRUE)>0 -> TRUE | W85: TRUE | X85: FALSE | Y85: FALSE | Z85: FALSE | AA85: Class 'ManifestacionClinica' undefined; DataProp 'hasProbability' undefined
A86: UC1-F1-P2-S1-M1 | B86: BD_Parcial_Hipoacusia | C86: ManifestacionClinica | D86: =IF(ISBLANK(C86),0,LEN(C86)-LEN(SUBSTITUTE(C86,";",""))+1) -> 1 | E86: =IF(D86<2,C86,LEFT(C86,FIND(";",C86)-1)) -> ManifestacionClinica | F86: =IF(D86<1,FALSE,ISERROR(MATCH(E86,'Ontology and concepts per UC'!$A$2:$A$62,0))) -> TRUE | G86: =IF(D86<2,"",MID(C86,LEN(E86)+3,LEN(C86)-FIND(";",C86)-1)) | H86: =IF(D86<3,G86,LEFT(G86,FIND(";",G86)-1)) | I86: =IF(D86<2,FALSE,ISERROR(MATCH(H86,'Ontology and concepts per UC'!$A$2:$A$62,0))) -> FALSE | J86: =IF(D86<3,"",RIGHT(G86,LEN(G86)-FIND(";",G86)-1)) | K86: =IF(D86<3,FALSE,ISERROR(MATCH(J86,'Ontology and concepts per UC'!$A$2:$A$62,0))) -> FALSE | M86: hasSource:"Genc et al. 2007[4]; Wolf et al. 2002[5]"; hasProbability:"0.10"; | O86: FALSE | P86: 1 | Q86: 1 | R86: =NOT(ISERROR(SEARCH("hasSource",M86))) -> TRUE | S86: Parcial | T86: =IF(S86="","",VLOOKUP(S86,'Ontology and concepts per UC'!$F$2:$J$46,5,FALSE)) -> Parcial | U86: {=(INDEX('Ontology and concepts per UC'!$G$2:$I$46,MATCH($S86,'Ontology and concepts per UC'!$F$2:$F$46,0),MATCH(LEFT($A86,3),'Ontology and concepts per UC'!$G$1:$I$1,0))=0)} -> FALSE | V86: =COUNTIF(W86:Z86,TRUE)>0 -> TRUE | W86: TRUE | X86: FALSE | Y86: FALSE | Z86: FALSE | AA86: Class 'ManifestacionClinica' undefined; DataProp 'hasProbability' undefined
A87: UC1-F1-P2-S1-M1 | B87: BD_Manif_RetrasoDesarrollo | C87: ManifestacionClinica; ChronicManifestation | D87: =IF(ISBLANK(C87),0,LEN(C87)-LEN(SUBSTITUTE(C87,";",""))+1) -> 2 | E87: =IF(D87<2,C87,LEFT(C87,FIND(";",C87)-1)) -> ManifestacionClinica | F87: =IF(D87<1,FALSE,ISERROR(MATCH(E87,'Ontology and concepts per UC'!$A$2:$A$62,0))) -> TRUE | G87: =IF(D87<2,"",MID(C87,LEN(E87)+3,LEN(C87)-FIND(";",C87)-1)) -> ChronicManifestation | H87: =IF(D87<3,G87,LEFT(G87,FIND(";",G87)-1)) -> ChronicManifestation | I87: =IF(D87<2,FALSE,ISERROR(MATCH(H87,'Ontology and concepts per UC'!$A$2:$A$62,0))) -> FALSE | J87: =IF(D87<3,"",RIGHT(G87,LEN(G87)-FIND(";",G87)-1)) | K87: =IF(D87<3,FALSE,ISERROR(MATCH(J87,'Ontology and concepts per UC'!$A$2:$A$62,0))) -> FALSE | L87: affectsUtility:BD_Manif_RetrasoDesarrollo_U; | M87: hasIncidence:"60% en diagnósticos posteriores a 6 meses"; hasProbability:"0.60"; hasSource:"Mslinger et al. 2003[6]; Wolf et al. 2002[7]"; hasSource:"Weber et al. 2004[2]; Grünewald et al. 2003[3]"; hasSource:"Mslinger et al. 2003[6]; Joshi et al. 1999[7]"; hasDescription:"Retraso motor y cognitivo persistente tras tratamiento tardío"; | O87: FALSE | P87: 1 | Q87: 3 | R87: =NOT(ISERROR(SEARCH("hasSource",M87))) -> TRUE | S87: Manifestación: Retraso mental | T87: =IF(S87="","",VLOOKUP(S87,'Ontology and concepts per UC'!$F$2:$J$46,5,FALSE)) -> Modelo Conceptual | U87: {=(INDEX('Ontology and concepts per UC'!$G$2:$I$46,MATCH($S87,'Ontology and concepts per UC'!$F$2:$F$46,0),MATCH(LEFT($A87,3),'Ontology and concepts per UC'!$G$1:$I$1,0))=0)} -> FALSE | V87: =COUNTIF(W87:Z87,TRUE)>0 -> TRUE | W87: TRUE | X87: FALSE | Y87: FALSE | Z87: FALSE | AA87: Class 'ManifestacionClinica' undefined; ObjectProp 'affectsUtility' undefined; DataProp 'hasIncidence' undefined; DataProp 'hasProbability' undefined
A88: UC1-F1-P2-S1-M1 | B88: BD_Manif_AtrofiaOpticaCronica | C88: ManifestacionCronica | D88: =IF(ISBLANK(C88),0,LEN(C88)-LEN(SUBSTITUTE(C88,";",""))+1) -> 1 | E88: =IF(D88<2,C88,LEFT(C88,FIND(";",C88)-1)) -> ManifestacionCronica | F88: =IF(D88<1,FALSE,ISERROR(MATCH(E88,'Ontology and concepts per UC'!$A$2:$A$62,0))) -> TRUE | G88: =IF(D88<2,"",MID(C88,LEN(E88)+3,LEN(C88)-FIND(";",C88)-1)) | H88: =IF(D88<3,G88,LEFT(G88,FIND(";",G88)-1)) | I88: =IF(D88<2,FALSE,ISERROR(MATCH(H88,'Ontology and concepts per UC'!$A$2:$A$62,0))) -> FALSE | J88: =IF(D88<3,"",RIGHT(G88,LEN(G88)-FIND(";",G88)-1)) | K88: =IF(D88<3,FALSE,ISERROR(MATCH(J88,'Ontology and concepts per UC'!$A$2:$A$62,0))) -> FALSE | M88: hasChronicOnset:"9"; | O88: FALSE | P88: 1 | Q88: 1 | R88: =NOT(ISERROR(SEARCH("hasSource",M88))) -> FALSE | S88: Manifestación: Pérdida de visión | T88: =IF(S88="","",VLOOKUP(S88,'Ontology and concepts per UC'!$F$2:$J$46,5,FALSE)) -> Modelo Conceptual | U88: {=(INDEX('Ontology and concepts per UC'!$G$2:$I$46,MATCH($S88,'Ontology and concepts per UC'!$F$2:$F$46,0),MATCH(LEFT($A88,3),'Ontology and concepts per UC'!$G$1:$I$1,0))=0)} -> FALSE | V88: =COUNTIF(W88:Z88,TRUE)>0 -> TRUE | W88: TRUE | X88: FALSE | Y88: FALSE | Z88: FALSE | AA88: Class 'ManifestacionCronica' undefined; DataProp 'hasChronicOnset' undefined
A89: UC1-F1-P2-S1-M1 | B89: BD_Manif_HipoacusiaCronica | C89: ManifestacionCronica | D89: =IF(ISBLANK(C89),0,LEN(C89)-LEN(SUBSTITUTE(C89,";",""))+1) -> 1 | E89: =IF(D89<2,C89,LEFT(C89,FIND(";",C89)-1)) -> ManifestacionCronica | F89: =IF(D89<1,FALSE,ISERROR(MATCH(E89,'Ontology and concepts per UC'!$A$2:$A$62,0))) -> TRUE | G89: =IF(D89<2,"",MID(C89,LEN(E89)+3,LEN(C89)-FIND(";",C89)-1)) | H89: =IF(D89<3,G89,LEFT(G89,FIND(";",G89)-1)) | I89: =IF(D89<2,FALSE,ISERROR(MATCH(H89,'Ontology and concepts per UC'!$A$2:$A$62,0))) -> FALSE | J89: =IF(D89<3,"",RIGHT(G89,LEN(G89)-FIND(";",G89)-1)) | K89: =IF(D89<3,FALSE,ISERROR(MATCH(J89,'Ontology and concepts per UC'!$A$2:$A$62,0))) -> FALSE | M89: hasChronicOnset:"12"; hasDescription:"Hipoacusia neurosensorial bilateral progresiva tras 6-18 meses sin tratamiento"; hasSource:"Genc et al. 2007[5]; Wolf et al. 2002[6]"; | O89: FALSE | P89: 1 | Q89: 1 | R89: =NOT(ISERROR(SEARCH("hasSource",M89))) -> TRUE | S89: Manifestación: Problemas de audición | T89: =IF(S89="","",VLOOKUP(S89,'Ontology and concepts per UC'!$F$2:$J$46,5,FALSE)) -> Modelo Conceptual | U89: {=(INDEX('Ontology and concepts per UC'!$G$2:$I$46,MATCH($S89,'Ontology and concepts per UC'!$F$2:$F$46,0),MATCH(LEFT($A89,3),'Ontology and concepts per UC'!$G$1:$I$1,0))=0)} -> FALSE | V89: =COUNTIF(W89:Z89,TRUE)>0 -> TRUE | W89: TRUE | X89: FALSE | Y89: FALSE | Z89: FALSE | AA89: Class 'ManifestacionCronica' undefined; DataProp 'hasChronicOnset' undefined
A90: UC1-F1-P2-S1-M1 | B90: BD_Mutacion_G98d7i3 | C90: MutacionGenetica | D90: =IF(ISBLANK(C90),0,LEN(C90)-LEN(SUBSTITUTE(C90,";",""))+1) -> 1 | E90: =IF(D90<2,C90,LEFT(C90,FIND(";",C90)-1)) -> MutacionGenetica | F90: =IF(D90<1,FALSE,ISERROR(MATCH(E90,'Ontology and concepts per UC'!$A$2:$A$62,0))) -> TRUE | G90: =IF(D90<2,"",MID(C90,LEN(E90)+3,LEN(C90)-FIND(";",C90)-1)) | H90: =IF(D90<3,G90,LEFT(G90,FIND(";",G90)-1)) | I90: =IF(D90<2,FALSE,ISERROR(MATCH(H90,'Ontology and concepts per UC'!$A$2:$A$62,0))) -> FALSE | J90: =IF(D90<3,"",RIGHT(G90,LEN(G90)-FIND(";",G90)-1)) | K90: =IF(D90<3,FALSE,ISERROR(MATCH(J90,'Ontology and concepts per UC'!$A$2:$A$62,0))) -> FALSE | M90: hasFrecuencia:"31.8% en casos sintomáticos"; hasEffectoBioquimico:"Frameshift que genera terminación prematura (actividad 0%)"; | O90: FALSE | P90: 1 | Q90: 2 | R90: =NOT(ISERROR(SEARCH("hasSource",M90))) -> FALSE | S90: Otros | T90: =IF(S90="","",VLOOKUP(S90,'Ontology and concepts per UC'!$F$2:$J$46,5,FALSE)) -> Otros | U90: {=(INDEX('Ontology and concepts per UC'!$G$2:$I$46,MATCH($S90,'Ontology and concepts per UC'!$F$2:$F$46,0),MATCH(LEFT($A90,3),'Ontology and concepts per UC'!$G$1:$I$1,0))=0)} -> TRUE | V90: =COUNTIF(W90:Z90,TRUE)>0 -> TRUE | W90: TRUE | X90: FALSE | Y90: FALSE | Z90: FALSE | AA90: Class 'MutacionGenetica' undefined; DataProp 'hasFrecuencia' undefined; DataProp 'hasEffectoBioquimico' undefined
A91: UC1-F1-P2-S1-M1 | B91: BD_Param_FrecuenciaTrimestral | C91: ParametroSeguimiento | D91: =IF(ISBLANK(C91),0,LEN(C91)-LEN(SUBSTITUTE(C91,";",""))+1) -> 1 | E91: =IF(D91<2,C91,LEFT(C91,FIND(";",C91)-1)) -> ParametroSeguimiento | F91: =IF(D91<1,FALSE,ISERROR(MATCH(E91,'Ontology and concepts per UC'!$A$2:$A$62,0))) -> TRUE | G91: =IF(D91<2,"",MID(C91,LEN(E91)+3,LEN(C91)-FIND(";",C91)-1)) | H91: =IF(D91<3,G91,LEFT(G91,FIND(";",G91)-1)) | I91: =IF(D91<2,FALSE,ISERROR(MATCH(H91,'Ontology and concepts per UC'!$A$2:$A$62,0))) -> FALSE | J91: =IF(D91<3,"",RIGHT(G91,LEN(G91)-FIND(";",G91)-1)) | K91: =IF(D91<3,FALSE,ISERROR(MATCH(J91,'Ontology and concepts per UC'!$A$2:$A$62,0))) -> FALSE | M91: hasExpectedValue:"4 evaluaciones/año"; | O91: FALSE | P91: 1 | Q91: 0 | R91: =NOT(ISERROR(SEARCH("hasSource",M91))) -> FALSE | S91: Seguimiento | T91: =IF(S91="","",VLOOKUP(S91,'Ontology and concepts per UC'!$F$2:$J$46,5,FALSE)) -> Tratamiento/seguimiento | U91: {=(INDEX('Ontology and concepts per UC'!$G$2:$I$46,MATCH($S91,'Ontology and concepts per UC'!$F$2:$F$46,0),MATCH(LEFT($A91,3),'Ontology and concepts per UC'!$G$1:$I$1,0))=0)} -> FALSE | V91: =COUNTIF(W91:Z91,TRUE)>0 -> TRUE | W91: TRUE | X91: FALSE | Y91: FALSE | Z91: FALSE | AA91: Class 'ParametroSeguimiento' undefined
A92: UC1-F1-P2-S1-M1 | B92: BD_Protocolo_Emergencia | C92: ProtocoloIntervencion | D92: =IF(ISBLANK(C92),0,LEN(C92)-LEN(SUBSTITUTE(C92,";",""))+1) -> 1 | E92: =IF(D92<2,C92,LEFT(C92,FIND(";",C92)-1)) -> ProtocoloIntervencion | F92: =IF(D92<1,FALSE,ISERROR(MATCH(E92,'Ontology and concepts per UC'!$A$2:$A$62,0))) -> TRUE | G92: =IF(D92<2,"",MID(C92,LEN(E92)+3,LEN(C92)-FIND(";",C92)-1)) | H92: =IF(D92<3,G92,LEFT(G92,FIND(";",G92)-1)) | I92: =IF(D92<2,FALSE,ISERROR(MATCH(H92,'Ontology and concepts per UC'!$A$2:$A$62,0))) -> FALSE | J92: =IF(D92<3,"",RIGHT(G92,LEN(G92)-FIND(";",G92)-1)) | K92: =IF(D92<3,FALSE,ISERROR(MATCH(J92,'Ontology and concepts per UC'!$A$2:$A$62,0))) -> FALSE | M92: hasSource:"Grünewald et al. 2003[3]; Salbert et al. 1993[5]"; hasDescription:"Ajuste inmediato a 20 mg/día de biotina durante infecciones o estrés metabólico. Monitorización diaria de lactato"; | O92: FALSE | P92: 1 | Q92: 0 | R92: =NOT(ISERROR(SEARCH("hasSource",M92))) -> TRUE | S92: Otros | T92: =IF(S92="","",VLOOKUP(S92,'Ontology and concepts per UC'!$F$2:$J$46,5,FALSE)) -> Otros | U92: {=(INDEX('Ontology and concepts per UC'!$G$2:$I$46,MATCH($S92,'Ontology and concepts per UC'!$F$2:$F$46,0),MATCH(LEFT($A92,3),'Ontology and concepts per UC'!$G$1:$I$1,0))=0)} -> TRUE | V92: =COUNTIF(W92:Z92,TRUE)>0 -> TRUE | W92: TRUE | X92: FALSE | Y92: FALSE | Z92: TRUE | AA92: Class 'ProtocoloIntervencion' undefined; should not be an intervention
A93: UC1-F1-P2-S1-M1 | B93: BD_Param_Tiempo_ManifAgudas | C93: TemporalParameter | D93: =IF(ISBLANK(C93),0,LEN(C93)-LEN(SUBSTITUTE(C93,";",""))+1) -> 1 | E93: =IF(D93<2,C93,LEFT(C93,FIND(";",C93)-1)) -> TemporalParameter | F93: =IF(D93<1,FALSE,ISERROR(MATCH(E93,'Ontology and concepts per UC'!$A$2:$A$62,0))) -> TRUE | G93: =IF(D93<2,"",MID(C93,LEN(E93)+3,LEN(C93)-FIND(";",C93)-1)) | H93: =IF(D93<3,G93,LEFT(G93,FIND(";",G93)-1)) | I93: =IF(D93<2,FALSE,ISERROR(MATCH(H93,'Ontology and concepts per UC'!$A$2:$A$62,0))) -> FALSE | J93: =IF(D93<3,"",RIGHT(G93,LEN(G93)-FIND(";",G93)-1)) | K93: =IF(D93<3,FALSE,ISERROR(MATCH(J93,'Ontology and concepts per UC'!$A$2:$A$62,0))) -> FALSE | M93: hasExpectedValue:"3.5"; hasSource:"Couce et al. 2011[1]; Weber et al. 2004[2]"; hasDescription:"Inicio promedio de manifestaciones agudas tras 2-5 meses sin tratamiento"; | O93: FALSE | P93: 1 | Q93: 0 | R93: =NOT(ISERROR(SEARCH("hasSource",M93))) -> TRUE | S93: Riesgo:Otras | T93: =IF(S93="","",VLOOKUP(S93,'Ontology and concepts per UC'!$F$2:$J$46,5,FALSE)) -> Parámetros de progresión | U93: {=(INDEX('Ontology and concepts per UC'!$G$2:$I$46,MATCH($S93,'Ontology and concepts per UC'!$F$2:$F$46,0),MATCH(LEFT($A93,3),'Ontology and concepts per UC'!$G$1:$I$1,0))=0)} -> FALSE | V93: =COUNTIF(W93:Z93,TRUE)>0 -> TRUE | W93: TRUE | X93: FALSE | Y93: FALSE | Z93: FALSE | AA93: Class 'TemporalParameter' undefined
A94: UC1-F1-P2-S1-M1 | B94: BD_Progresion_ManifAgudas | C94: TemporalParameter | D94: =IF(ISBLANK(C94),0,LEN(C94)-LEN(SUBSTITUTE(C94,";",""))+1) -> 1 | E94: =IF(D94<2,C94,LEFT(C94,FIND(";",C94)-1)) -> TemporalParameter | F94: =IF(D94<1,FALSE,ISERROR(MATCH(E94,'Ontology and concepts per UC'!$A$2:$A$62,0))) -> TRUE | G94: =IF(D94<2,"",MID(C94,LEN(E94)+3,LEN(C94)-FIND(";",C94)-1)) | H94: =IF(D94<3,G94,LEFT(G94,FIND(";",G94)-1)) | I94: =IF(D94<2,FALSE,ISERROR(MATCH(H94,'Ontology and concepts per UC'!$A$2:$A$62,0))) -> FALSE | J94: =IF(D94<3,"",RIGHT(G94,LEN(G94)-FIND(";",G94)-1)) | K94: =IF(D94<3,FALSE,ISERROR(MATCH(J94,'Ontology and concepts per UC'!$A$2:$A$62,0))) -> FALSE | M94: hasSource:"Grünewald et al. 2003[3]; Wolf et al. 2002[6]"; hasDescription:"Aparición de síntomas neurológicos entre 2-5 meses sin tratamiento"; | O94: FALSE | P94: 1 | Q94: 0 | R94: =NOT(ISERROR(SEARCH("hasSource",M94))) -> TRUE | S94: Riesgo:Otras | T94: =IF(S94="","",VLOOKUP(S94,'Ontology and concepts per UC'!$F$2:$J$46,5,FALSE)) -> Parámetros de progresión | U94: {=(INDEX('Ontology and concepts per UC'!$G$2:$I$46,MATCH($S94,'Ontology and concepts per UC'!$F$2:$F$46,0),MATCH(LEFT($A94,3),'Ontology and concepts per UC'!$G$1:$I$1,0))=0)} -> FALSE | V94: =COUNTIF(W94:Z94,TRUE)>0 -> TRUE | W94: TRUE | X94: FALSE | Y94: FALSE | Z94: FALSE | AA94: Class 'TemporalParameter' undefined
A95: UC1-F1-P2-S1-M1 | B95: BD_EstadoSaludable_U | C95: UtilityParameter | D95: =IF(ISBLANK(C95),0,LEN(C95)-LEN(SUBSTITUTE(C95,";",""))+1) -> 1 | E95: =IF(D95<2,C95,LEFT(C95,FIND(";",C95)-1)) -> UtilityParameter | F95: =IF(D95<1,FALSE,ISERROR(MATCH(E95,'Ontology and concepts per UC'!$A$2:$A$62,0))) -> TRUE | G95: =IF(D95<2,"",MID(C95,LEN(E95)+3,LEN(C95)-FIND(";",C95)-1)) | H95: =IF(D95<3,G95,LEFT(G95,FIND(";",G95)-1)) | I95: =IF(D95<2,FALSE,ISERROR(MATCH(H95,'Ontology and concepts per UC'!$A$2:$A$62,0))) -> FALSE | J95: =IF(D95<3,"",RIGHT(G95,LEN(G95)-FIND(";",G95)-1)) | K95: =IF(D95<3,FALSE,ISERROR(MATCH(J95,'Ontology and concepts per UC'!$A$2:$A$62,0))) -> FALSE | M95: hasExpectedValue:"1.0"; | O95: FALSE | P95: 1 | Q95: 0 | R95: =NOT(ISERROR(SEARCH("hasSource",M95))) -> FALSE | S95: Población: utilidad | T95: =IF(S95="","",VLOOKUP(S95,'Ontology and concepts per UC'!$F$2:$J$46,5,FALSE)) -> Modelo Conceptual | U95: {=(INDEX('Ontology and concepts per UC'!$G$2:$I$46,MATCH($S95,'Ontology and concepts per UC'!$F$2:$F$46,0),MATCH(LEFT($A95,3),'Ontology and concepts per UC'!$G$1:$I$1,0))=0)} -> FALSE | V95: =COUNTIF(W95:Z95,TRUE)>0 -> TRUE | W95: TRUE | X95: FALSE | Y95: FALSE | Z95: FALSE | AA95: Class 'UtilityParameter' undefined
A96: UC1-F1-P2-S1-M1 | B96: BD_Manif_Convulsiones_U | C96: UtilityParameter; DisutilityParameter | D96: =IF(ISBLANK(C96),0,LEN(C96)-LEN(SUBSTITUTE(C96,";",""))+1) -> 2 | E96: =IF(D96<2,C96,LEFT(C96,FIND(";",C96)-1)) -> UtilityParameter | F96: =IF(D96<1,FALSE,ISERROR(MATCH(E96,'Ontology and concepts per UC'!$A$2:$A$62,0))) -> TRUE | G96: =IF(D96<2,"",MID(C96,LEN(E96)+3,LEN(C96)-FIND(";",C96)-1)) -> DisutilityParameter | H96: =IF(D96<3,G96,LEFT(G96,FIND(";",G96)-1)) -> DisutilityParameter | I96: =IF(D96<2,FALSE,ISERROR(MATCH(H96,'Ontology and concepts per UC'!$A$2:$A$62,0))) -> TRUE | J96: =IF(D96<3,"",RIGHT(G96,LEN(G96)-FIND(";",G96)-1)) | K96: =IF(D96<3,FALSE,ISERROR(MATCH(J96,'Ontology and concepts per UC'!$A$2:$A$62,0))) -> FALSE | M96: hasSource:"Grünewald et al. 2003[3]; Wolf et al. 2002[6]"; hasSource:"Wolf et al. 2002[5]; Ye et al. 2009[7]"; hasSource:"Wolf et al. 2002[7]; Grünewald et al. 2003[3]"; hasSource:"Grünewald et al. 2003[3]; Salbert et al. 1993[4]"; hasExpectedValue:"0.65"; | O96: FALSE | P96: 2 | Q96: 0 | R96: =NOT(ISERROR(SEARCH("hasSource",M96))) -> TRUE | S96: Utilidad: Convulsiones | T96: =IF(S96="","",VLOOKUP(S96,'Ontology and concepts per UC'!$F$2:$J$46,5,FALSE)) -> Utilidad | U96: {=(INDEX('Ontology and concepts per UC'!$G$2:$I$46,MATCH($S96,'Ontology and concepts per UC'!$F$2:$F$46,0),MATCH(LEFT($A96,3),'Ontology and concepts per UC'!$G$1:$I$1,0))=0)} -> FALSE | V96: =COUNTIF(W96:Z96,TRUE)>0 -> TRUE | W96: TRUE | X96: FALSE | Y96: FALSE | Z96: TRUE | AA96: Class 'UtilityParameter' undefined; Class 'DisutilityParameter' undefined; unsuitable value for property
A97: UC1-F1-P2-S1-M1 | B97: BD_Estadio_Parcial | D97: =IF(ISBLANK(C97),0,LEN(C97)-LEN(SUBSTITUTE(C97,";",""))+1) -> 0 | E97: =IF(D97<2,C97,LEFT(C97,FIND(";",C97)-1)) -> 0 | F97: =IF(D97<1,FALSE,ISERROR(MATCH(E97,'Ontology and concepts per UC'!$A$2:$A$62,0))) -> FALSE | G97: =IF(D97<2,"",MID(C97,LEN(E97)+3,LEN(C97)-FIND(";",C97)-1)) | H97: =IF(D97<3,G97,LEFT(G97,FIND(";",G97)-1)) | I97: =IF(D97<2,FALSE,ISERROR(MATCH(H97,'Ontology and concepts per UC'!$A$2:$A$62,0))) -> FALSE | J97: =IF(D97<3,"",RIGHT(G97,LEN(G97)-FIND(";",G97)-1)) | K97: =IF(D97<3,FALSE,ISERROR(MATCH(J97,'Ontology and concepts per UC'!$A$2:$A$62,0))) -> FALSE | O97: TRUE | P97: 0 | Q97: 0 | R97: =NOT(ISERROR(SEARCH("hasSource",M97))) -> FALSE | S97: Parcial | T97: =IF(S97="","",VLOOKUP(S97,'Ontology and concepts per UC'!$F$2:$J$46,5,FALSE)) -> Parcial | U97: {=(INDEX('Ontology and concepts per UC'!$G$2:$I$46,MATCH($S97,'Ontology and concepts per UC'!$F$2:$F$46,0),MATCH(LEFT($A97,3),'Ontology and concepts per UC'!$G$1:$I$1,0))=0)} -> FALSE | V97: =COUNTIF(W97:Z97,TRUE)>0 -> TRUE | W97: TRUE | X97: FALSE | Y97: FALSE | Z97: FALSE | AA97: No Class assigned
A98: UC1-F1-P2-S1-M1 | B98: BD_Estadio_Profundo | D98: =IF(ISBLANK(C98),0,LEN(C98)-LEN(SUBSTITUTE(C98,";",""))+1) -> 0 | E98: =IF(D98<2,C98,LEFT(C98,FIND(";",C98)-1)) -> 0 | F98: =IF(D98<1,FALSE,ISERROR(MATCH(E98,'Ontology and concepts per UC'!$A$2:$A$62,0))) -> FALSE | G98: =IF(D98<2,"",MID(C98,LEN(E98)+3,LEN(C98)-FIND(";",C98)-1)) | H98: =IF(D98<3,G98,LEFT(G98,FIND(";",G98)-1)) | I98: =IF(D98<2,FALSE,ISERROR(MATCH(H98,'Ontology and concepts per UC'!$A$2:$A$62,0))) -> FALSE | J98: =IF(D98<3,"",RIGHT(G98,LEN(G98)-FIND(";",G98)-1)) | K98: =IF(D98<3,FALSE,ISERROR(MATCH(J98,'Ontology and concepts per UC'!$A$2:$A$62,0))) -> FALSE | O98: TRUE | P98: 0 | Q98: 0 | R98: =NOT(ISERROR(SEARCH("hasSource",M98))) -> FALSE | S98: Otros | T98: =IF(S98="","",VLOOKUP(S98,'Ontology and concepts per UC'!$F$2:$J$46,5,FALSE)) -> Otros | U98: {=(INDEX('Ontology and concepts per UC'!$G$2:$I$46,MATCH($S98,'Ontology and concepts per UC'!$F$2:$F$46,0),MATCH(LEFT($A98,3),'Ontology and concepts per UC'!$G$1:$I$1,0))=0)} -> TRUE | V98: =COUNTIF(W98:Z98,TRUE)>0 -> TRUE | W98: TRUE | X98: FALSE | Y98: FALSE | Z98: FALSE | AA98: No Class assigned
A99: UC1-F1-P2-S1-M2 | B99: DBP_Manif_Alopecia | C99: AcuteManifestation | D99: =IF(ISBLANK(C99),0,LEN(C99)-LEN(SUBSTITUTE(C99,";",""))+1) -> 1 | E99: =IF(D99<2,C99,LEFT(C99,FIND(";",C99)-1)) -> AcuteManifestation | F99: =IF(D99<1,FALSE,ISERROR(MATCH(E99,'Ontology and concepts per UC'!$A$2:$A$62,0))) -> FALSE | G99: =IF(D99<2,"",MID(C99,LEN(E99)+3,LEN(C99)-FIND(";",C99)-1)) | H99: =IF(D99<3,G99,LEFT(G99,FIND(";",G99)-1)) | I99: =IF(D99<2,FALSE,ISERROR(MATCH(H99,'Ontology and concepts per UC'!$A$2:$A$62,0))) -> FALSE | J99: =IF(D99<3,"",RIGHT(G99,LEN(G99)-FIND(";",G99)-1)) | K99: =IF(D99<3,FALSE,ISERROR(MATCH(J99,'Ontology and concepts per UC'!$A$2:$A$62,0))) -> FALSE | M99: hasSource:"1999-Biotinidase_deficiency_a_treatable_genetic_disorder_in_the_Saudi_population.pdf"; hasSource:"2011-Clinical_and_genetic_findings_in_patients_with_biotinidase_deficiency_detected_through_newb.pdf"; hasDescription:"Alopecia parcial o total, a menudo asociada a dermatitis."; hasDescription:"Alopecia parcial o total, de aparición rápida, en ocasiones reversible con tratamiento."; | O99: FALSE | P99: 0 | Q99: 0 | R99: =NOT(ISERROR(SEARCH("hasSource",M99))) -> TRUE | S99: Otras manifestaciones | T99: =IF(S99="","",VLOOKUP(S99,'Ontology and concepts per UC'!$F$2:$J$46,5,FALSE)) -> Modelo Conceptual | U99: {=(INDEX('Ontology and concepts per UC'!$G$2:$I$46,MATCH($S99,'Ontology and concepts per UC'!$F$2:$F$46,0),MATCH(LEFT($A99,3),'Ontology and concepts per UC'!$G$1:$I$1,0))=0)} -> FALSE | V99: =COUNTIF(W99:Z99,TRUE)>0 -> FALSE | W99: FALSE | X99: FALSE | Y99: FALSE | Z99: FALSE
A100: UC1-F1-P2-S1-M2 | B100: DBP_Manif_Ataxia | C100: AcuteManifestation | D100: =IF(ISBLANK(C100),0,LEN(C100)-LEN(SUBSTITUTE(C100,";",""))+1) -> 1 | E100: =IF(D100<2,C100,LEFT(C100,FIND(";",C100)-1)) -> AcuteManifestation | F100: =IF(D100<1,FALSE,ISERROR(MATCH(E100,'Ontology and concepts per UC'!$A$2:$A$62,0))) -> FALSE | G100: =IF(D100<2,"",MID(C100,LEN(E100)+3,LEN(C100)-FIND(";",C100)-1)) | H100: =IF(D100<3,G100,LEFT(G100,FIND(";",G100)-1)) | I100: =IF(D100<2,FALSE,ISERROR(MATCH(H100,'Ontology and concepts per UC'!$A$2:$A$62,0))) -> FALSE | J100: =IF(D100<3,"",RIGHT(G100,LEN(G100)-FIND(";",G100)-1)) | K100: =IF(D100<3,FALSE,ISERROR(MATCH(J100,'Ontology and concepts per UC'!$A$2:$A$62,0))) -> FALSE | M100: hasDescription:"Ataxia y alteraciones de la coordinación motora."; hasDescription:"Ataxia y alteraciones de la coordinación motora, descritas en episodios agudos."; hasSource:"2011-Clinical_and_genetic_findings_in_patients_with_biotinidase_deficiency_detected_through_newb.pdf"; | O100: FALSE | P100: 0 | Q100: 0 | R100: =NOT(ISERROR(SEARCH("hasSource",M100))) -> TRUE | S100: Otras manifestaciones | T100: =IF(S100="","",VLOOKUP(S100,'Ontology and concepts per UC'!$F$2:$J$46,5,FALSE)) -> Modelo Conceptual | U100: {=(INDEX('Ontology and concepts per UC'!$G$2:$I$46,MATCH($S100,'Ontology and concepts per UC'!$F$2:$F$46,0),MATCH(LEFT($A100,3),'Ontology and concepts per UC'!$G$1:$I$1,0))=0)} -> FALSE | V100: =COUNTIF(W100:Z100,TRUE)>0 -> FALSE | W100: FALSE | X100: FALSE | Y100: FALSE | Z100: FALSE
...

Sheet Backup (porsi)
A1: Test ID | B1: URI | C1: Classes | D1: ObjectProperties | E1: DataProperties | F1: Hallucination | G1: Error OWL | H1: Related concept | I1: Group of concepts | J1: Comments
A2: UC1-F1-P1-S1-M1 | B2: #BTD_BiotinTreatment_AnnualCost | C2: CostParameter | E2: #hasDescription: Coste anual del tratamiento con biotina (5-10 mg/día); #hasUnit: EUR; #hasExpectedValue: 730; | F2: FALSE | G2: TRUE | H2: Coste tratamiento | I2: {=IF(H2="","",VLOOKUP(H2,_xludf.HSTACK(#REF!,#REF!),2,FALSE))} -> #NAME?
A3: UC1-F1-P1-S1-M1 | B3: #BTD_DiagnosticTest_Cost | C3: CostParameter | E3: #hasExpectedValue: 150; #hasDescription: Coste de la prueba diagnóstica confirmatoria; | F3: FALSE | G3: TRUE | H3: Coste de diagnóstico | I3: {=IF(H3="","",VLOOKUP(H3,_xludf.HSTACK(#REF!,#REF!),2,FALSE))} -> #NAME?
A4: UC1-F1-P1-S1-M1 | B4: #BTD_Disease | C4: RareDisease, Disease | D4: #hasEpidemiologicalParameter: #BTD_Incidence; #hasDisutilityCombinationMethod: #AdditiveDisutility; #hasFollowUpStrategy: #BTD_FollowUp_AnnualMonitoring; | E4: #hasSource: Wolf B. Disorders of biotin metabolism. In: Scriver CR et al., eds. The metabolic and molecular bases of inherited disease, 7th ed. 2001; #hasDescription: Deficiencia de biotinidasa; | F4: FALSE | G4: FALSE | H4: Enfermedad | I4: {=IF(H4="","",VLOOKUP(H4,_xludf.HSTACK(#REF!,#REF!),2,FALSE))} -> #NAME?
A5: UC1-F1-P1-S1-M1 | B5: #BTD_Disease_Partial | C5: Disease | D5: #isSubtypeOf: #BTD_Disease; | E5: #hasDescription: Deficiencia parcial de biotinidasa (actividad enzimática 10-30% del valor normal); | F5: FALSE | G5: FALSE | I5: {=IF(H5="","",VLOOKUP(H5,_xludf.HSTACK(#REF!,#REF!),2,FALSE))}
A6: UC1-F1-P1-S1-M1 | B6: #BTD_Disease_Profound | C6: Disease | D6: #hasFeature: #BTD_Manif_Hypotonia; #hasFeature: #BTD_Manif_DevelopmentalDelay; #hasFeature: #BTD_Manif_HearingLoss; #hasFeature: #BTD_Manif_SkinProblems; #isSubtypeOf: #BTD_Disease; #hasFeature: #BTD_Manif_OpticAtrophy; #hasFeature: #BTD_Manif_Seizures; | E6: #hasDescription: Deficiencia profunda de biotinidasa (actividad enzimática menor del 10% del valor normal); | F6: FALSE | G6: TRUE | H6: Enfermedad | I6: {=IF(H6="","",VLOOKUP(H6,_xludf.HSTACK(#REF!,#REF!),2,FALSE))} -> #NAME? | J6: Debería haber usado el concepto de Development, pero es coherente. Se inventó el concepto "hasfeature"
A7: UC1-F1-P1-S1-M1 | B7: #BTD_FollowUp_AnnualMonitoring | C7: FollowUpStrategy | F7: FALSE | G7: FALSE | H7: Seguimiento | I7: {=IF(H7="","",VLOOKUP(H7,_xludf.HSTACK(#REF!,#REF!),2,FALSE))} -> #NAME?
A8: UC1-F1-P1-S1-M1 | B8: #BTD_Incidence | C8: EpidemiologicalParameter, SecondOrderUncertaintyParameter | E8: #hasSource: Wolf B. Worldwide survey of neonatal screening for biotinidase deficiency. J Inherit Metab Dis 1991;14:923-927; #hasExpectedValue: 0.0000125; #hasDescription: Incidencia de la deficiencia profunda de biotinidasa; | F8: FALSE | G8: FALSE | H8: Prevalencia al nacimiento | I8: {=IF(H8="","",VLOOKUP(H8,_xludf.HSTACK(#REF!,#REF!),2,FALSE))} -> #NAME?
A9: UC1-F1-P1-S1-M1 | B9: #BTD_Intervention_BiotinTreatment | C9: Intervention | D9: #hasTreatmentCost: #BTD_BiotinTreatment_AnnualCost; | E9: #hasDescription: Tratamiento con biotina oral (5-30 mg/día); | F9: FALSE | G9: FALSE | H9: Tratamiento base | I9: {=IF(H9="","",VLOOKUP(H9,_xludf.HSTACK(#REF!,#REF!),2,FALSE))} -> #NAME? | J9: Identificado erróneamente como intervención
A10: UC1-F1-P1-S1-M1 | B10: #BTD_Intervention_ClinicalDiagnosis | C10: Intervention | E10: #hasDescription: Detección clínica de la deficiencia de biotinidasa tras aparición de síntomas; | F10: FALSE | G10: FALSE | H10: Intervención: No cribado | I10: {=IF(H10="","",VLOOKUP(H10,_xludf.HSTACK(#REF!,#REF!),2,FALSE))} -> #NAME?
A11: UC1-F1-P1-S1-M1 | B11: #BTD_Intervention_Screening | C11: Intervention | D11: #modifies: #BTD_Manif_HearingLoss_Prob_WithoutTreatment; | E11: #hasDescription: Cribado neonatal de la deficiencia de biotinidasa mediante ensayo enzimático o fluorimétrico semicuantitativo; | F11: FALSE | G11: FALSE | H11: Intervención: Cribado | I11: {=IF(H11="","",VLOOKUP(H11,_xludf.HSTACK(#REF!,#REF!),2,FALSE))} -> #NAME?
A12: UC1-F1-P1-S1-M1 | B12: #BTD_Manif_Combined_U | C12: UtilityParameter | E12: #hasDescription: Desutilidad anual para casos graves con múltiples síntomas; #appliesOneTime: false; #hasExpectedValue: 0.49; | F12: FALSE | G12: TRUE | I12: {=IF(H12="","",VLOOKUP(H12,_xludf.HSTACK(#REF!,#REF!),2,FALSE))}
A13: UC1-F1-P1-S1-M1 | B13: #BTD_Manif_DevelopmentalDelay | C13: Manifestation | E13: #hasDescription: Retraso del desarrollo psicomotor; | F13: FALSE | G13: FALSE | H13: Manifestación: Retraso mental | I13: {=IF(H13="","",VLOOKUP(H13,_xludf.HSTACK(#REF!,#REF!),2,FALSE))} -> #NAME?
A14: UC1-F1-P1-S1-M1 | B14: #BTD_Manif_DevelopmentalDelay_Prob_LateTraeatment | C14: Parameter | E14: #hasDescription: Probabilidad de retraso del desarrollo persistente con tratamiento tardío; #hasExpectedValue: 0.27; #hasSource: Moslinger D et al. Clinical and neuropsychological outcome in 33 patients with biotinidase deficiency ascertained by nationwide newborn screening and family studies in Austria. Eur J Pediatr 2001;160:277-282; | F14: TRUE | G14: FALSE | H14: Riesgo: Retraso mental | I14: {=IF(H14="","",VLOOKUP(H14,_xludf.HSTACK(#REF!,#REF!),2,FALSE))} -> #NAME? | J14: No encuentro ese valor en la fuente
A15: UC1-F1-P1-S1-M1 | B15: #BTD_Manif_DevelopmentalDelay_Prob_WithoutTreatment | C15: Parameter | E15: #hasDescription: Probabilidad de desarrollar retraso del desarrollo sin tratamiento; #hasExpectedValue: 0.60; #hasSource: Moslinger D et al. Clinical and neuropsychological outcome in 33 patients with biotinidase deficiency ascertained by nationwide newborn screening and family studies in Austria. Eur J Pediatr 2001;160:277-282; | F15: TRUE | G15: FALSE | H15: Riesgo: Retraso mental | I15: {=IF(H15="","",VLOOKUP(H15,_xludf.HSTACK(#REF!,#REF!),2,FALSE))} -> #NAME? | J15: No encuentro ese valor en la fuente
A16: UC1-F1-P1-S1-M1 | B16: #BTD_Manif_DevelopmentalDelay_U | C16: UtilityParameter | E16: #hasDescription: Desutilidad anual asociada a retraso del desarrollo; #appliesOneTime: false; #hasExpectedValue: 0.29; | F16: FALSE | G16: TRUE | H16: Utilidad: Retraso mental | I16: {=IF(H16="","",VLOOKUP(H16,_xludf.HSTACK(#REF!,#REF!),2,FALSE))} -> #NAME? | J16: Posible alucinación. Sin fuente
A17: UC1-F1-P1-S1-M1 | B17: #BTD_Manif_HearingLoss | C17: Manifestation | E17: #hasDescription: Pérdida auditiva neurosensorial; | F17: FALSE | G17: FALSE | H17: Manifestación: Problemas de audición | I17: {=IF(H17="","",VLOOKUP(H17,_xludf.HSTACK(#REF!,#REF!),2,FALSE))} -> #NAME?
A18: UC1-F1-P1-S1-M1 | B18: #BTD_Manif_HearingLoss_Prob_LateTraeatment | C18: Parameter | E18: #hasDescription: Probabilidad de pérdida auditiva persistente con tratamiento tardío; #hasExpectedValue: 0.36; #hasSource: Weber P et al. Outcome in patients with profound biotinidase deficiency: relevance of newborn screening. Dev Med Child Neurol 2004;46:481-4; | F18: TRUE | G18: FALSE | H18: Riesgo: Problemas de audición | I18: {=IF(H18="","",VLOOKUP(H18,_xludf.HSTACK(#REF!,#REF!),2,FALSE))} -> #NAME? | J18: No encuentro ese valor en la fuente
A19: UC1-F1-P1-S1-M1 | B19: #BTD_Manif_HearingLoss_Prob_WithoutTreatment | C19: Parameter | E19: #hasSource: Wolf B, Spencer R, Gleason T. Hearing loss is a common feature of symptomatic children with profound biotinidase deficiency. J Pediatr 2002;140:242-246; #hasDescription: Probabilidad de desarrollar pérdida auditiva sin tratamiento; #hasSource: Wolf B et al. Hearing loss is a common feature... J Pediatr 2002;140:242-246; #hasExpectedValue: 0.55; #hasExpectedValue: 0.75; | F19: TRUE | G19: TRUE | H19: Riesgo: Problemas de audición | I19: {=IF(H19="","",VLOOKUP(H19,_xludf.HSTACK(#REF!,#REF!),2,FALSE))} -> #NAME? | J19: Incluye dos valores esperados. Uno de ellos parece coincidir con el de la fuente, pero no se podría usar así
A20: UC1-F1-P1-S1-M1 | B20: #BTD_Manif_HearingLoss_U | C20: UtilityParameter | E20: #hasExpectedValue: 0.18; #hasDescription: Desutilidad anual asociada a pérdida auditiva neurosensorial; #appliesOneTime: false; | F20: FALSE | G20: TRUE | H20: Utilidad: Problemas de audición | I20: {=IF(H20="","",VLOOKUP(H20,_xludf.HSTACK(#REF!,#REF!),2,FALSE))} -> #NAME? | J20: Posible alucinación. Sin fuente
A21: UC1-F1-P1-S1-M1 | B21: #BTD_Manif_Hypotonia | C21: Manifestation | E21: #hasDescription: Hipotonía muscular; | F21: FALSE | G21: FALSE | H21: Manifestación: Hipotonía | I21: {=IF(H21="","",VLOOKUP(H21,_xludf.HSTACK(#REF!,#REF!),2,FALSE))} -> #NAME?
A22: UC1-F1-P1-S1-M1 | B22: #BTD_Manif_OpticAtrophy | C22: Manifestation | E22: #hasDescription: Atrofia óptica; | F22: FALSE | G22: FALSE | H22: Manifestación: Pérdida de visión | I22: {=IF(H22="","",VLOOKUP(H22,_xludf.HSTACK(#REF!,#REF!),2,FALSE))} -> #NAME?
A23: UC1-F1-P1-S1-M1 | B23: #BTD_Manif_OpticAtrophy_Prob_LateTraeatment | C23: Parameter | E23: #hasExpectedValue: 0.20; #hasSource: Salbert BA, Astruc J, Wolf B. Ophthalmologic findings in biotinidase deficiency. Ophthalmologica 1993;206:177-181; #hasDescription: Probabilidad de atrofia óptica persistente con tratamiento tardío; | F23: TRUE | G23: FALSE | H23: Riesgo: Pérdida de visión | I23: {=IF(H23="","",VLOOKUP(H23,_xludf.HSTACK(#REF!,#REF!),2,FALSE))} -> #NAME? | J23: No se puede encontrar el valor en esas fuentes
A24: UC1-F1-P1-S1-M1 | B24: #BTD_Manif_OpticAtrophy_Prob_WithoutTreatment | C24: Parameter | E24: #hasSource: Salbert BA, Astruc J, Wolf B. Ophthalmologic findings in biotinidase deficiency. Ophthalmologica 1993;206:177-181; #hasDescription: Probabilidad de desarrollar atrofia óptica sin tratamiento; #hasExpectedValue: 0.30; | F24: TRUE | G24: FALSE | H24: Riesgo: Pérdida de visión | I24: {=IF(H24="","",VLOOKUP(H24,_xludf.HSTACK(#REF!,#REF!),2,FALSE))} -> #NAME? | J24: No se puede encontrar el valor en esas fuentes
A25: UC1-F1-P1-S1-M1 | B25: #BTD_Manif_OpticAtrophy_U | C25: UtilityParameter | E25: #hasExpectedValue: 0.23; #appliesOneTime: false; #hasDescription: Desutilidad anual asociada a atrofia óptica; | F25: FALSE | G25: TRUE | H25: Utilidad: Pérdida de visión | I25: {=IF(H25="","",VLOOKUP(H25,_xludf.HSTACK(#REF!,#REF!),2,FALSE))} -> #NAME? | J25: Posible alucinación. Sin fuente
A26: UC1-F1-P1-S1-M1 | B26: #BTD_Manif_Seizures | C26: Manifestation | E26: #hasDescription: Convulsiones refractarias a tratamiento anticonvulsivo; | F26: FALSE | G26: FALSE | H26: Manifestación: Convulsiones | I26: {=IF(H26="","",VLOOKUP(H26,_xludf.HSTACK(#REF!,#REF!),2,FALSE))} -> #NAME?
A27: UC1-F1-P1-S1-M1 | B27: #BTD_Manif_Seizures_Prob_WithoutTreatment | C27: Parameter | E27: #hasDescription: Probabilidad de desarrollar convulsiones sin tratamiento; #hasSource: Weber P et al. Outcome in patients with profound biotinidase deficiency: relevance of newborn screening. Dev Med Child Neurol 2004;46:481-4; #hasExpectedValue: 0.70; | F27: TRUE | G27: FALSE | H27: Riesgo: Convulsiones | I27: {=IF(H27="","",VLOOKUP(H27,_xludf.HSTACK(#REF!,#REF!),2,FALSE))} -> #NAME? | J27: No encuentro ese valor en la fuente
A28: UC1-F1-P1-S1-M1 | B28: #BTD_Manif_Seizures_U | C28: UtilityParameter | E28: #hasDescription: Desutilidad anual asociada a convulsiones refractarias; #appliesOneTime: false; #hasExpectedValue: 0.32; | F28: FALSE | G28: TRUE | H28: Utilidad: Convulsiones | I28: {=IF(H28="","",VLOOKUP(H28,_xludf.HSTACK(#REF!,#REF!),2,FALSE))} -> #NAME? | J28: Posible alucinación. Sin fuente
A29: UC1-F1-P1-S1-M1 | B29: #BTD_Manif_SkinProblems | C29: Manifestation | E29: #hasDescription: Problemas cutáneos (erupciones, alopecia); | F29: FALSE | G29: FALSE | H29: Manifestación: Problemas en la piel | I29: {=IF(H29="","",VLOOKUP(H29,_xludf.HSTACK(#REF!,#REF!),2,FALSE))} -> #NAME?
A30: UC1-F1-P1-S1-M1 | B30: #BTD_Normal_U | C30: UtilityParameter | E30: #hasExpectedValue: 1.0; #hasDescription: Utilidad de vida normal sin síntomas; | F30: FALSE | G30: TRUE | H30: Población: utilidad | I30: {=IF(H30="","",VLOOKUP(H30,_xludf.HSTACK(#REF!,#REF!),2,FALSE))} -> #NAME?
A31: UC1-F1-P1-S1-M1 | B31: #BTD_Population_Newborns_ES | C31: Population | D31: #hasSubpopulation: #GeneralPopulation; | E31: #hasMinAge: 0; #hasGeographicalContext: España; #hasMaxAge: 1; #hasDescription: Recién nacidos en España durante un año natural; | F31: TRUE | G31: FALSE | H31: Población | I31: {=IF(H31="","",VLOOKUP(H31,_xludf.HSTACK(#REF!,#REF!),2,FALSE))} -> #NAME? | J31: Se inventó una subpoblación que no existe en la ontología
A32: UC1-F1-P1-S1-M1 | B32: #BTD_Screening_Cost | C32: CostParameter | E32: #hasDescription: Coste del cribado neonatal por recién nacido; #hasExpectedValue: 3.50; #hasUnit: EUR; | F32: FALSE | G32: TRUE | H32: Coste cribado | I32: {=IF(H32="","",VLOOKUP(H32,_xludf.HSTACK(#REF!,#REF!),2,FALSE))} -> #NAME?
A33: UC1-F1-P1-S1-M1 | B33: #BTD_Screening_Sensitivity | C33: DeterministicParameter, Parameter | E33: #hasExpectedValue: 0.99; #hasDescription: Sensibilidad del cribado neonatal para la deficiencia de biotinidasa; | F33: TRUE | G33: FALSE | H33: Caracterización cribado | I33: {=IF(H33="","",VLOOKUP(H33,_xludf.HSTACK(#REF!,#REF!),2,FALSE))} -> #NAME? | J33: Posible alucinación: no puedo encontrar ese valor
A34: UC1-F1-P1-S1-M1 | B34: #BTD_Screening_Specificity | C34: Parameter | E34: #hasDescription: Especificidad del cribado neonatal para la deficiencia de biotinidasa; #hasExpectedValue: 0.998; | F34: FALSE | G34: FALSE | H34: Especificidad | I34: {=IF(H34="","",VLOOKUP(H34,_xludf.HSTACK(#REF!,#REF!),2,FALSE))} -> #NAME?
A35: UC1-F1-P1-S2-M1 | B35: #CribadoNeonatalBiotinidasa | C35: ScreeningIntervention | D35: #hasSpecificity: #Param_EspecificidadCribado; #hasCost: #CosteCribadoUnitario; #hasSensitivity: #Param_SensibilidadCribado; | F35: FALSE | G35: FALSE | H35: Intervención: Cribado | I35: {=IF(H35="","",VLOOKUP(H35,_xludf.HSTACK(#REF!,#REF!),2,FALSE))} -> #NAME?
A36: UC1-F1-P1-S2-M1 | B36: #DeficienciaBiotinidasa | C36: RareDisease | D36: #hasManifestation: #Manif_ErupcionCutanea; #hasManifestation: #Manif_Convulsiones; #hasDiagnosisCost: #CosteDiagnostico; #hasEpidemiologicalParameter: #Param_Prevalencia; | E36: #hasRefToSNOMED: 253260006; | F36: TRUE | G36: FALSE | H36: Enfermedad | I36: {=IF(H36="","",VLOOKUP(H36,_xludf.HSTACK(#REF!,#REF!),2,FALSE))} -> #NAME? | J36: La referencia a SNOMED no existe
A37: UC1-F1-P1-S2-M1 | B37: #DeteccionClinicaBiotinidasa | C37: DiagnosisIntervention | F37: FALSE | G37: FALSE | H37: Intervención: No cribado | I37: {=IF(H37="","",VLOOKUP(H37,_xludf.HSTACK(#REF!,#REF!),2,FALSE))} -> #NAME?
A38: UC1-F1-P1-S2-M1 | B38: #Manif_Convulsiones | C38: AcuteManifestation | F38: FALSE | G38: FALSE | H38: Manifestación: Convulsiones | I38: {=IF(H38="","",VLOOKUP(H38,_xludf.HSTACK(#REF!,#REF!),2,FALSE))} -> #NAME?
A39: UC1-F1-P1-S2-M1 | B39: #Manif_ErupcionCutanea | C39: ChronicManifestation | F39: FALSE | G39: FALSE | H39: Manifestación: Problemas en la piel | I39: {=IF(H39="","",VLOOKUP(H39,_xludf.HSTACK(#REF!,#REF!),2,FALSE))} -> #NAME?
A40: UC1-F1-P1-S2-M1 | B40: #Param_EspecificidadCribado | C40: DeterministicParameter | E40: #hasExpectedValue: 0.995; | F40: FALSE | G40: FALSE | H40: Especificidad | I40: {=IF(H40="","",VLOOKUP(H40,_xludf.HSTACK(#REF!,#REF!),2,FALSE))} -> #NAME?
A41: UC1-F1-P1-S2-M1 | B41: #Param_Prevalencia | C41: EpidemiologicalParameter | E41: #hasExpectedValue: 1.0E-4; #hasSource: Wolf B. (1991) J Inherit Metab Dis 14(4):513-26; | F41: FALSE | G41: FALSE | H41: Prevalencia al nacimiento | I41: {=IF(H41="","",VLOOKUP(H41,_xludf.HSTACK(#REF!,#REF!),2,FALSE))} -> #NAME?
A42: UC1-F1-P1-S2-M1 | B42: #Param_SensibilidadCribado | C42: DeterministicParameter | E42: #hasExpectedValue: 0.998; | F42: TRUE | G42: FALSE | H42: Caracterización cribado | I42: {=IF(H42="","",VLOOKUP(H42,_xludf.HSTACK(#REF!,#REF!),2,FALSE))} -> #NAME? | J42: Posible alucinación: no puedo encontrar ese valor
A43: UC1-F1-P1-S2-M1 | B43: #PoblacionRecienNacidosEspaña | C43: Population | E43: #hasGeographicalContext: España; #hasSize: 450000; | F43: FALSE | G43: FALSE | H43: Población | I43: {=IF(H43="","",VLOOKUP(H43,_xludf.HSTACK(#REF!,#REF!),2,FALSE))} -> #NAME?
A44: UC1-F1-P1-S2-M1 | B44: #PrevalenciaBiotinidasa | C44: EpidemiologicalParameter | F44: FALSE | G44: FALSE | H44: Prevalencia al nacimiento | I44: {=IF(H44="","",VLOOKUP(H44,_xludf.HSTACK(#REF!,#REF!),2,FALSE))} -> #NAME? | J44: Aunque totalmente vacía
A45: UC1-F1-P1-S2-M1 | B45: #Utilidad_Convulsiones | C45: Utility | E45: #hasExpectedValue: -0.35; | F45: FALSE | G45: FALSE | H45: Utilidad: Convulsiones | I45: {=IF(H45="","",VLOOKUP(H45,_xludf.HSTACK(#REF!,#REF!),2,FALSE))} -> #NAME? | J45: Posible alucinación. Sin fuente
A46: UC1-F1-P1-S2-M1 | B46: #Utilidad_ErupcionCutanea | C46: Utility | E46: #hasExpectedValue: -0.15; | F46: FALSE | G46: FALSE | H46: Utilidad: Problemas en la piel | I46: {=IF(H46="","",VLOOKUP(H46,_xludf.HSTACK(#REF!,#REF!),2,FALSE))} -> #NAME? | J46: Posible alucinación. Sin fuente
A47: UC1-F1-P2-S1-M1 | B47: #BD_Enfermedad | C47: EnfermedadMetabolica, Enfermedad | D47: #hasDiseaseStage: #BD_Parcial_Enfermedad; #hasManifestation: #BD_Manif_AtrofiaOptica; #hasManifestation: #BD_Manif_Leucoencefalopatia; #hasManifestation: #BD_Manif_ConvulsionesMioclonicas; #hasManifestation: #BD_Manif_DermatitisExudativa; #hasManifestation: #BD_Manif_EstridorLaríngeo; #hasManifestation: #BD_Manif_Dermatitis; #hasManifestation: #BD_Manif_Hipotonia; #hasManifestation: #BD_Manif_Hipoacusia; #hasManifestation: #BD_Manif_ConvulsionesAgudas; #hasManifestation: #BD_Manif_RetrasoDesarrollo; #hasManifestation: #BD_Manif_Convulsiones; #hasManifestation: #BD_Manif_HipoacusiaCronica; #hasManifestation: #BD_Manif_HipoacusiaNeurosensorial; | E47: #hasInheritance: Autosómica recesiva; #hasOMIM: 253260; #hasDescription: Deficiencia profunda de biotinidasa (OMIM 253260), trastorno autosómico recesivo del metabolismo de la biotina; | F47: FALSE | G47: TRUE | H47: Enfermedad | I47: {=IF(H47="","",VLOOKUP(H47,_xludf.HSTACK(#REF!,#REF!),2,FALSE))} -> #NAME?
A48: UC1-F1-P2-S1-M1 | B48: #BD_Epid_Incidencia | C48: EpidemiologicalParameter | E48: #hasSource: Wolf 1995[4]; Baykal et al. 1998[3]; #hasExpectedValue: 1:60000; | F48: FALSE | G48: FALSE | H48: Prevalencia al nacimiento | I48: {=IF(H48="","",VLOOKUP(H48,_xludf.HSTACK(#REF!,#REF!),2,FALSE))} -> #NAME?
A49: UC1-F1-P2-S1-M1 | B49: #BD_Epid_IncidenciaGlobal | C49: EpidemiologicalParameter | E49: #hasSource: Couce et al. 2011[1]; Wolf 1995[4]; #hasExpectedValue: 1:60000; | F49: FALSE | G49: FALSE | H49: Prevalencia al nacimiento | I49: {=IF(H49="","",VLOOKUP(H49,_xludf.HSTACK(#REF!,#REF!),2,FALSE))} -> #NAME?
A50: UC1-F1-P2-S1-M1 | B50: #BD_Estadio_NoTratado | C50: EstadioEnfermedad | D50: #hasEpidemiologicalParameter: #BD_Epid_IncidenciaGlobal; | E50: #hasDescription: Fase sintomática con afectación neurológica y metabólica activa; #hasDescription: Deficiencia profunda no tratada (actividad enzimática ≤10%) con manifestaciones neurológicas activas; | F50: FALSE | G50: TRUE | I50: {=IF(H50="","",VLOOKUP(H50,_xludf.HSTACK(#REF!,#REF!),2,FALSE))}
A51: UC1-F1-P2-S1-M1 | B51: #BD_Estadio_Parcial | F51: FALSE | G51: TRUE | I51: {=IF(H51="","",VLOOKUP(H51,_xludf.HSTACK(#REF!,#REF!),2,FALSE))}
A52: UC1-F1-P2-S1-M1 | B52: #BD_Estadio_Profundo | F52: FALSE | G52: TRUE | I52: {=IF(H52="","",VLOOKUP(H52,_xludf.HSTACK(#REF!,#REF!),2,FALSE))}
A53: UC1-F1-P2-S1-M1 | B53: #BD_EstadoSaludable_U | C53: UtilityParameter | E53: #hasExpectedValue: 1.0; | F53: FALSE | G53: TRUE | H53: Población: utilidad | I53: {=IF(H53="","",VLOOKUP(H53,_xludf.HSTACK(#REF!,#REF!),2,FALSE))} -> #NAME?
A54: UC1-F1-P2-S1-M1 | B54: #BD_Eval_Audiologica | C54: EvaluacionClinica | E54: #hasSource: Wolf et al. 2002[5]; Genc et al. 2007[4]; #hasDescription: Potenciales evocados auditivos brainstem (BAEP) anuales durante primeros 5 años; | F54: FALSE | G54: TRUE | H54: Seguimiento | I54: {=IF(H54="","",VLOOKUP(H54,_xludf.HSTACK(#REF!,#REF!),2,FALSE))} -> #NAME?
A55: UC1-F1-P2-S1-M1 | B55: #BD_Intervencion_Biotina | C55: IntervencionFarmacologica | D55: #trataManifestacion: #BD_Manif_Convulsiones; | E55: #hasDescription: Suplementación oral con biotina 10-30 mg/día; #hasEfectoBioquimico: Restauración de actividad carboxilasa en 48-72 horas; #hasDosis: 10-30 mg/día (Joshi et al. 1999[3]; Mslinger et al. 2003[2]); | F55: FALSE | G55: TRUE | H55: Tratamiento base | I55: {=IF(H55="","",VLOOKUP(H55,_xludf.HSTACK(#REF!,#REF!),2,FALSE))} -> #NAME?
A56: UC1-F1-P2-S1-M1 | B56: #BD_Intervencion_Biotina_Efectividad | C56: EfficacyParameter | E56: #hasExpectedValue: Resolución síntomas en 1-4 semanas (Genc et al. 2007[7]); #hasSource: Grünewald et al. 2003[6]; Wolf et al. 2002[5]; | F56: FALSE | G56: TRUE | I56: {=IF(H56="","",VLOOKUP(H56,_xludf.HSTACK(#REF!,#REF!),2,FALSE))}
A57: UC1-F1-P2-S1-M1 | B57: #BD_Intervencion_Cribado | C57: Intervencion, IntervencionCribado | D57: #affectsDiseaseStage: #BD_Estadio_NoTratado; | E57: #hasCostoUnitario: 2150€ por caso detectado; #hasEficacia: Reducción del 95% en manifestaciones neurológicas con tratamiento temprano; #hasDescription: Cribado neonatal mediante ensayo enzimático fluorimétrico en papel; #hasEffect: Reducción del 95% en manifestaciones neurológicas cuando se trata antes de los 3 meses; | F57: TRUE | G57: TRUE | H57: Intervención: Cribado | I57: {=IF(H57="","",VLOOKUP(H57,_xludf.HSTACK(#REF!,#REF!),2,FALSE))} -> #NAME?
A58: UC1-F1-P2-S1-M1 | B58: #BD_Intervencion_CribadoNeonatal | C58: IntervencionCribado | D58: #previeneEstadio: #BD_Estadio_NoTratado; | E58: #hasEficacia: Reducción del 95% en manifestaciones neurológicas con tratamiento antes de los 3 meses; #hasCostoUnitario: 2150€ por caso detectado (Ye et al. 2009); #hasDescription: Ensayo enzimático fluorimétrico en sangre en papel para detección precoz; #hasSource: Couce et al. 2011[1]; Weber et al. 2004[5]; | F58: TRUE | G58: TRUE | H58: Caracterización cribado | I58: {=IF(H58="","",VLOOKUP(H58,_xludf.HSTACK(#REF!,#REF!),2,FALSE))} -> #NAME? | J58: Posible alucinación: no puedo encontrar ese valor
A59: UC1-F1-P2-S1-M1 | B59: #BD_Manif_AtrofiaOptica | C59: ManifestacionClinica, ChronicManifestation | D59: #affectsUtility: #BD_Manif_AtrofiaOptica_U; | E59: #hasDescription: Atrofia óptica progresiva con pérdida de agudeza visual; #hasProbability: 0.36; #hasSource: Salbert et al. 1993[5]; Weber et al. 2004[2]; #hasSource: Salbert et al. 1993[5]; Ye et al. 2009[7]; #hasSource: Salbert et al. 1993[5]; Ye et al. 2009[6]; #hasDescription: Atrofia óptica bilateral progresiva con pérdida aguda de visión; | F59: TRUE | G59: TRUE | H59: Manifestación: Pérdida de visión | I59: {=IF(H59="","",VLOOKUP(H59,_xludf.HSTACK(#REF!,#REF!),2,FALSE))} -> #NAME? | J59: Se lio con las fuentes
A60: UC1-F1-P2-S1-M1 | B60: #BD_Manif_AtrofiaOpticaCronica | C60: ManifestacionCronica | E60: #hasChronicOnset: 9; | F60: FALSE | G60: TRUE | H60: Manifestación: Pérdida de visión | I60: {=IF(H60="","",VLOOKUP(H60,_xludf.HSTACK(#REF!,#REF!),2,FALSE))} -> #NAME?
A61: UC1-F1-P2-S1-M1 | B61: #BD_Manif_AtrofiaOptica_U | C61: DisutilityParameter | E61: #hasSource: Salbert et al. 1993[5]; Weber et al. 2004[2]; #hasExpectedValue: 0.55; | F61: TRUE | G61: TRUE | H61: Utilidad: Pérdida de visión | I61: {=IF(H61="","",VLOOKUP(H61,_xludf.HSTACK(#REF!,#REF!),2,FALSE))} -> #NAME? | J61: El valor no aparece en la fuente
A62: UC1-F1-P2-S1-M1 | B62: #BD_Manif_Convulsiones | C62: ManifestacionClinica | D62: #affectsUtility: #BD_Manif_Convulsiones_U; | E62: #hasSource: Weber et al. 2004[2]; Grünewald et al. 2003[3]; #hasSource: Couce et al. 2011[1]; Weber et al. 2004[2]; #hasDescription: Convulsiones mioclónicas o tónico-clónicas, frecuentes en pacientes no tratados; #hasProbability: 0.78; | F62: TRUE | G62: TRUE | H62: Manifestación: Convulsiones | I62: {=IF(H62="","",VLOOKUP(H62,_xludf.HSTACK(#REF!,#REF!),2,FALSE))} -> #NAME?
A63: UC1-F1-P2-S1-M1 | B63: #BD_Manif_ConvulsionesAgudas | C63: ManifestacionAguda | E63: #hasDescription: Convulsiones mioclónicas típicamente entre 2-4 meses no tratados; #hasOnsetTime: 2; | F63: FALSE | G63: TRUE | H63: Manifestación: Convulsiones | I63: {=IF(H63="","",VLOOKUP(H63,_xludf.HSTACK(#REF!,#REF!),2,FALSE))} -> #NAME?
A64: UC1-F1-P2-S1-M1 | B64: #BD_Manif_ConvulsionesMioclonicas | C64: ManifestacionClinica | E64: #hasDescription: Convulsiones mioclónicas refractarias, frecuentes en crisis agudas no tratadas; #hasSource: Couce et al. 2011[1]; Wolf et al. 2002[7]; | F64: FALSE | G64: TRUE | H64: Manifestación: Convulsiones | I64: {=IF(H64="","",VLOOKUP(H64,_xludf.HSTACK(#REF!,#REF!),2,FALSE))} -> #NAME?
A65: UC1-F1-P2-S1-M1 | B65: #BD_Manif_Convulsiones_U | C65: UtilityParameter, DisutilityParameter | E65: #hasSource: Grünewald et al. 2003[3]; Salbert et al. 1993[4]; #hasSource: Wolf et al. 2002[7]; Grünewald et al. 2003[3]; #hasSource: Grünewald et al. 2003[3]; Wolf et al. 2002[6]; #hasExpectedValue: 0.65; #hasSource: Wolf et al. 2002[5]; Ye et al. 2009[7]; | F65: TRUE | G65: TRUE | H65: Utilidad: Convulsiones | I65: {=IF(H65="","",VLOOKUP(H65,_xludf.HSTACK(#REF!,#REF!),2,FALSE))} -> #NAME? | J65: El valor no aparece en la fuente
A66: UC1-F1-P2-S1-M1 | B66: #BD_Manif_Dermatitis | C66: ManifestacionClinica | D66: #affectsUtility: #BD_Manif_Dermatitis_U; | E66: #hasSource: Salbert et al. 1993[5]; Mslinger et al. 2003[6]; #hasProbability: 0.45; | F66: TRUE | G66: TRUE | H66: Manifestación: Problemas en la piel | I66: {=IF(H66="","",VLOOKUP(H66,_xludf.HSTACK(#REF!,#REF!),2,FALSE))} -> #NAME?
A67: UC1-F1-P2-S1-M1 | B67: #BD_Manif_DermatitisAguda | C67: ManifestacionAguda | E67: #hasOnsetTime: 3; | F67: FALSE | G67: TRUE | H67: Manifestación: Problemas en la piel | I67: {=IF(H67="","",VLOOKUP(H67,_xludf.HSTACK(#REF!,#REF!),2,FALSE))} -> #NAME?
A68: UC1-F1-P2-S1-M1 | B68: #BD_Manif_DermatitisExudativa | C68: ManifestacionClinica | E68: #hasDescription: Dermatitis exudativa perioral con sobreinfección por Candida; #hasSource: Salbert et al. 1993[5]; Wolf 2001[7]; | F68: FALSE | G68: TRUE | H68: Manifestación: Problemas en la piel | I68: {=IF(H68="","",VLOOKUP(H68,_xludf.HSTACK(#REF!,#REF!),2,FALSE))} -> #NAME?
A69: UC1-F1-P2-S1-M1 | B69: #BD_Manif_Dermatitis_U | C69: DisutilityParameter | E69: #hasSource: Salbert et al. 1993[5]; Wolf et al. 2002[6]; #hasExpectedValue: 0.30; | F69: TRUE | G69: TRUE | H69: Utilidad: Problemas en la piel | I69: {=IF(H69="","",VLOOKUP(H69,_xludf.HSTACK(#REF!,#REF!),2,FALSE))} -> #NAME? | J69: El valor no aparece en la fuente
A70: UC1-F1-P2-S1-M1 | B70: #BD_Manif_EstridorLaríngeo | C70: ManifestacionClinica | E70: #hasSource: Weber et al. 2004[2]; Dionisi-Vici et al. 1988[1]; #hasDescription: Estridor laríngeo y apnea central por hipoventilación; | F70: FALSE | G70: TRUE | I70: {=IF(H70="","",VLOOKUP(H70,_xludf.HSTACK(#REF!,#REF!),2,FALSE))}
A71: UC1-F1-P2-S1-M1 | B71: #BD_Manif_Hipoacusia | C71: ManifestacionClinica | D71: #affectsUtility: #BD_Manif_Hipoacusia_U; | E71: #hasSource: Genc et al. 2007[4]; Wolf et al. 2002[7]; #hasPrevalencia: 55% en casos sintomáticos; #hasProbability: 0.55; #hasDescription: Hipoacusia neurosensorial bilateral, prevalente en 55% de casos sintomáticos; #hasSource: Genc et al. 2007[5]; Wolf et al. 2002[6]; #hasSource: Wolf et al. 2002[5]; Grünewald et al. 2003[3]; | F71: TRUE | G71: TRUE | H71: Manifestación: Problemas de audición | I71: {=IF(H71="","",VLOOKUP(H71,_xludf.HSTACK(#REF!,#REF!),2,FALSE))} -> #NAME?
A72: UC1-F1-P2-S1-M1 | B72: #BD_Manif_HipoacusiaCronica | C72: ManifestacionCronica | E72: #hasChronicOnset: 12; #hasSource: Genc et al. 2007[5]; Wolf et al. 2002[6]; #hasDescription: Hipoacusia neurosensorial bilateral progresiva tras 6-18 meses sin tratamiento; | F72: FALSE | G72: TRUE | H72: Manifestación: Problemas de audición | I72: {=IF(H72="","",VLOOKUP(H72,_xludf.HSTACK(#REF!,#REF!),2,FALSE))} -> #NAME?
A73: UC1-F1-P2-S1-M1 | B73: #BD_Manif_HipoacusiaNeurosensorial | C73: ChronicManifestation | E73: #hasSource: Genc et al. 2007[4]; Wolf et al. 2002[5]; Weber et al. 2004[2]; #hasDescription: Hipoacusia neurosensorial bilateral irreversible, presente en 55% de casos sintomáticos; | F73: FALSE | G73: FALSE | H73: Manifestación: Problemas de audición | I73: {=IF(H73="","",VLOOKUP(H73,_xludf.HSTACK(#REF!,#REF!),2,FALSE))} -> #NAME?
A74: UC1-F1-P2-S1-M1 | B74: #BD_Manif_Hipoacusia_Incidencia | C74: EpidemiologicalParameter | E74: #hasSource: Genc et al. 2007[4]; Wolf et al. 2002[7]; #hasExpectedValue: 0.55; | F74: FALSE | G74: FALSE | H74: Riesgo: Problemas de audición | I74: {=IF(H74="","",VLOOKUP(H74,_xludf.HSTACK(#REF!,#REF!),2,FALSE))} -> #NAME?
A75: UC1-F1-P2-S1-M1 | B75: #BD_Manif_Hipoacusia_U | C75: UtilityParameter, DisutilityParameter | E75: #hasSource: Genc et al. 2007[4]; Wolf et al. 2002[5]; #hasSource: Genc et al. 2007[4]; Wolf et al. 2002[6]; #hasExpectedValue: 0.45; | F75: TRUE | G75: TRUE | H75: Utilidad: Problemas de audición | I75: {=IF(H75="","",VLOOKUP(H75,_xludf.HSTACK(#REF!,#REF!),2,FALSE))} -> #NAME? | J75: El valor no aparece en la fuente
A76: UC1-F1-P2-S1-M1 | B76: #BD_Manif_Hipotonia | C76: ManifestacionClinica | E76: #hasSource: Grünewald et al. 2003[3]; Couce et al. 2011[1]; #hasProbability: 0.68; | F76: FALSE | G76: TRUE | H76: Manifestación: Hipotonía | I76: {=IF(H76="","",VLOOKUP(H76,_xludf.HSTACK(#REF!,#REF!),2,FALSE))} -> #NAME?
A77: UC1-F1-P2-S1-M1 | B77: #BD_Manif_Leucoencefalopatia | C77: ChronicManifestation | E77: #hasDescription: Alteraciones difusas de la sustancia blanca en resonancia magnética; #hasSource: Grünewald et al. 2003[3]; Couce et al. 2011[1]; | F77: FALSE | G77: FALSE | H77: Manifestación: Hipotonía | I77: {=IF(H77="","",VLOOKUP(H77,_xludf.HSTACK(#REF!,#REF!),2,FALSE))} -> #NAME?
A78: UC1-F1-P2-S1-M1 | B78: #BD_Manif_RetrasoDesarrollo | C78: ChronicManifestation, ManifestacionClinica | D78: #affectsUtility: #BD_Manif_RetrasoDesarrollo_U; | E78: #hasProbability: 0.60; #hasSource: Mslinger et al. 2003[6]; Joshi et al. 1999[7]; #hasSource: Mslinger et al. 2003[6]; Wolf et al. 2002[7]; #hasDescription: Retraso motor y cognitivo persistente tras tratamiento tardío; #hasIncidence: 60% en diagnósticos posteriores a 6 meses; #hasSource: Weber et al. 2004[2]; Grünewald et al. 2003[3]; | F78: TRUE | G78: TRUE | H78: Manifestación: Retraso mental | I78: {=IF(H78="","",VLOOKUP(H78,_xludf.HSTACK(#REF!,#REF!),2,FALSE))} -> #NAME?
A79: UC1-F1-P2-S1-M1 | B79: #BD_Manif_RetrasoDesarrollo_U | C79: DisutilityParameter | E79: #hasSource: Joshi et al. 1999[7]; Couce et al. 2011[1]; #hasExpectedValue: 0.70; | F79: TRUE | G79: TRUE | H79: Utilidad: Retraso mental | I79: {=IF(H79="","",VLOOKUP(H79,_xludf.HSTACK(#REF!,#REF!),2,FALSE))} -> #NAME? | J79: El valor no aparece en la fuente
A80: UC1-F1-P2-S1-M1 | B80: #BD_Mutacion_G98d7i3 | C80: MutacionGenetica | E80: #hasEffectoBioquimico: Frameshift que genera terminación prematura (actividad 0%); #hasFrecuencia: 31.8% en casos sintomáticos; | F80: FALSE | G80: TRUE | I80: {=IF(H80="","",VLOOKUP(H80,_xludf.HSTACK(#REF!,#REF!),2,FALSE))}
A81: UC1-F1-P2-S1-M1 | B81: #BD_Param_FrecuenciaTrimestral | C81: ParametroSeguimiento | E81: #hasExpectedValue: 4 evaluaciones/año; | F81: FALSE | G81: TRUE | H81: Seguimiento | I81: {=IF(H81="","",VLOOKUP(H81,_xludf.HSTACK(#REF!,#REF!),2,FALSE))} -> #NAME?
A82: UC1-F1-P2-S1-M1 | B82: #BD_Param_Tiempo_ManifAgudas | C82: TemporalParameter | E82: #hasExpectedValue: 3.5; #hasSource: Couce et al. 2011[1]; Weber et al. 2004[2]; #hasDescription: Inicio promedio de manifestaciones agudas tras 2-5 meses sin tratamiento; | F82: FALSE | G82: TRUE | I82: {=IF(H82="","",VLOOKUP(H82,_xludf.HSTACK(#REF!,#REF!),2,FALSE))}
A83: UC1-F1-P2-S1-M1 | B83: #BD_Parcial_Alopecia | C83: ManifestacionClinica | E83: #hasSource: Couce et al. 2011[1]; Grünewald et al. 2003[3]; #hasProbability: 0.20; | F83: FALSE | G83: TRUE | I83: {=IF(H83="","",VLOOKUP(H83,_xludf.HSTACK(#REF!,#REF!),2,FALSE))}
A84: UC1-F1-P2-S1-M1 | B84: #BD_Parcial_Convulsiones | C84: ManifestacionClinica | E84: #hasSource: Couce et al. 2011[1]; Weber et al. 2004[2]; #hasProbability: 0.05; | F84: FALSE | G84: TRUE | I84: {=IF(H84="","",VLOOKUP(H84,_xludf.HSTACK(#REF!,#REF!),2,FALSE))}
A85: UC1-F1-P2-S1-M1 | B85: #BD_Parcial_Dermatitis | C85: ManifestacionClinica | E85: #hasProbability: 0.15; #hasSource: Salbert et al. 1993[5]; Joshi et al. 1999[7]; | F85: FALSE | G85: TRUE | I85: {=IF(H85="","",VLOOKUP(H85,_xludf.HSTACK(#REF!,#REF!),2,FALSE))}
A86: UC1-F1-P2-S1-M1 | B86: #BD_Parcial_Enfermedad | C86: Enfermedad | D86: #hasManifestation: #BD_Parcial_Alopecia; #hasManifestation: #BD_Parcial_Dermatitis; #hasManifestation: #BD_Parcial_Convulsiones; #hasManifestation: #BD_Parcial_Hipoacusia; | E86: #hasSource: Couce et al. 2011[1]; Mslinger et al. 2003[6]; #hasDescription: Deficiencia parcial de biotinidasa (actividad enzimática 10-30%); | F86: FALSE | G86: TRUE | I86: {=IF(H86="","",VLOOKUP(H86,_xludf.HSTACK(#REF!,#REF!),2,FALSE))}
A87: UC1-F1-P2-S1-M1 | B87: #BD_Parcial_Hipoacusia | C87: ManifestacionClinica | E87: #hasProbability: 0.10; #hasSource: Genc et al. 2007[4]; Wolf et al. 2002[5]; | F87: FALSE | G87: TRUE | I87: {=IF(H87="","",VLOOKUP(H87,_xludf.HSTACK(#REF!,#REF!),2,FALSE))}
A88: UC1-F1-P2-S1-M1 | B88: #BD_Parcial_Incidencia | C88: EpidemiologicalParameter | E88: #hasSource: Couce et al. 2011[1]; #hasExpectedValue: 1:43,575; | F88: FALSE | G88: FALSE | I88: {=IF(H88="","",VLOOKUP(H88,_xludf.HSTACK(#REF!,#REF!),2,FALSE))}
A89: UC1-F1-P2-S1-M1 | B89: #BD_Profunda_Incidencia | C89: EpidemiologicalParameter | E89: #hasSource: Couce et al. 2011[1]; Baykal et al. 1998[3]; #hasExpectedValue: 1:187500; | F89: TRUE | G89: FALSE | H89: Prevalencia al nacimiento | I89: {=IF(H89="","",VLOOKUP(H89,_xludf.HSTACK(#REF!,#REF!),2,FALSE))} -> #NAME?
A90: UC1-F1-P2-S1-M1 | B90: #BD_Progresion_ManifAgudas | C90: TemporalParameter | E90: #hasDescription: Aparición de síntomas neurológicos entre 2-5 meses sin tratamiento; #hasSource: Grünewald et al. 2003[3]; Wolf et al. 2002[6]; | F90: FALSE | G90: TRUE | I90: {=IF(H90="","",VLOOKUP(H90,_xludf.HSTACK(#REF!,#REF!),2,FALSE))}
A91: UC1-F1-P2-S1-M1 | B91: #BD_Progresion_Temporal | C91: DiseaseProgressionModel | D91: #hasChronicPhase: #BD_Manif_HipoacusiaCronica; #hasAcutePhase: #BD_Param_Tiempo_ManifAgudas; | F91: FALSE | G91: TRUE | I91: {=IF(H91="","",VLOOKUP(H91,_xludf.HSTACK(#REF!,#REF!),2,FALSE))}
A92: UC1-F1-P2-S1-M1 | B92: #BD_Protocolo_Emergencia | C92: ProtocoloIntervencion | E92: #hasSource: Grünewald et al. 2003[3]; Salbert et al. 1993[5]; #hasDescription: Ajuste inmediato a 20 mg/día de biotina durante infecciones o estrés metabólico. Monitorización diaria de lactato; | F92: FALSE | G92: TRUE | I92: {=IF(H92="","",VLOOKUP(H92,_xludf.HSTACK(#REF!,#REF!),2,FALSE))}
A93: UC1-F1-P2-S1-M1 | B93: #BD_Seguimiento_Parcial | C93: EstrategiaSeguimiento | D93: #appliesToDiseaseStage: #BD_Estadio_Parcial; | E93: #hasSource: Ye et al. 2009[7]; Joshi et al. 1999[8]; #hasDescription: Evaluación semestral: control metabólico y ajuste dosis biotina en situaciones de estrés. Screening audiológico bianual hasta adolescencia; | F93: FALSE | G93: TRUE | I93: {=IF(H93="","",VLOOKUP(H93,_xludf.HSTACK(#REF!,#REF!),2,FALSE))}
A94: UC1-F1-P2-S1-M1 | B94: #BD_Seguimiento_Profundo | C94: EstrategiaSeguimiento | D94: #appliesToDiseaseStage: #BD_Estadio_Profundo; | E94: #hasSource: Couce et al. 2011[1]; Weber et al. 2004[2]; Mslinger et al. 2003[6]; #hasDescription: Monitorización trimestral: evaluación neurológica, auditiva y visual. Control bioquímico de metabolitos (3-HIA, MCC) y actividad enzimática cada 3 meses. EEG anual hasta estabilización; | F94: FALSE | G94: TRUE | H94: Seguimiento | I94: {=IF(H94="","",VLOOKUP(H94,_xludf.HSTACK(#REF!,#REF!),2,FALSE))} -> #NAME?
A95: UC1-F1-P2-S2-M1 | B95: #BTD_ClinicalDetection_Delay | C95: TransitionParameter | E95: #hasExpectedValue: 180; #hasSource: Retraso diagnóstico promedio de 6 meses[4][11]; | F95: FALSE | G95: TRUE | I95: {=IF(H95="","",VLOOKUP(H95,_xludf.HSTACK(#REF!,#REF!),2,FALSE))}
A96: UC1-F1-P2-S2-M1 | B96: #BTD_Cost_BiotinTreatment_Annual | C96: CostParameter | E96: #hasDescription: Annual cost of biotin treatment for biotinidase deficiency; | F96: FALSE | G96: TRUE | H96: Coste tratamiento | I96: {=IF(H96="","",VLOOKUP(H96,_xludf.HSTACK(#REF!,#REF!),2,FALSE))} -> #NAME?
A97: UC1-F1-P2-S2-M1 | B97: #BTD_Cost_Diagnosis | C97: CostParameter | E97: #hasDescription: Cost of diagnostic confirmation for biotinidase deficiency; | F97: FALSE | G97: TRUE | H97: Coste de diagnóstico | I97: {=IF(H97="","",VLOOKUP(H97,_xludf.HSTACK(#REF!,#REF!),2,FALSE))} -> #NAME?
A98: UC1-F1-P2-S2-M1 | B98: #BTD_Cost_Screening | C98: CostParameter | E98: #hasDescription: Cost of neonatal screening for biotinidase deficiency; | F98: FALSE | G98: TRUE | H98: Coste cribado | I98: {=IF(H98="","",VLOOKUP(H98,_xludf.HSTACK(#REF!,#REF!),2,FALSE))} -> #NAME?
A99: UC1-F1-P2-S2-M1 | B99: #BTD_Cost_Untreated_Annual | C99: CostParameter | E99: #hasDescription: Annual healthcare cost for untreated biotinidase deficiency; | F99: FALSE | G99: TRUE | H99: Coste tratamiento | I99: {=IF(H99="","",VLOOKUP(H99,_xludf.HSTACK(#REF!,#REF!),2,FALSE))} -> #NAME?
A100: UC1-F1-P2-S2-M1 | B100: #BTD_CriticalWindow_Treatment | C100: EpidemiologicalParameter | E100: #hasExpectedValue: 30; #hasSource: Máximo 30 días tras inicio de síntomas[8][10]; #hasDescription: Ventana terapéutica para prevenir secuelas; | F100: FALSE | G100: FALSE | I100: {=IF(H100="","",VLOOKUP(H100,_xludf.HSTACK(#REF!,#REF!),2,FALSE))}
...

Sheet Analysis per seeked concept
B1: UC1-F1-P1-S1-M1 | C1: UC1-F1-P1-S2-M1 | D1: UC1-F1-P2-S1-M1 | E1: UC1-F1-P2-S2-M1 | F1: UC1-F1-P2-S1-M2 | G1: UC1-F1-P2-S2-M2 | H1: UC2-F1-P1-S1-M1 | I1: UC2-F1-P2-S1-M1 | J1: UC2-F1-P1-S1-M2 | K1: UC2-F1-P2-S1-M2 | L1: UC3-F1-P1-S1-M1 | M1: UC3-F1-P2-S1-M1 | N1: UC3-F1-P1-S1-M2 | O1: UC3-F1-P2-S1-M2 | P1: UC1-F3-P1-S1-M2 | Q1: UC1-F3-P1-S2-M2 | R1: UC1-F3-P2-S1-M2 | S1: UC1-F3-P2-S2-M2 | T1: UC1-F2-P1-S1-M2 | U1: UC1-F2-P1-S2-M2 | V1: UC1-F2-P2-S1-M2 | W1: UC1-F2-P2-S2-M2 | X1: UC2-F2-P1-S1-M2 | Y1: UC2-F2-P2-S1-M2 | Z1: UC2-F3-P1-S1-M2 | AA1: UC2-F3-P2-S1-M2 | AB1: UC3-F2-P1-S1-M2 | AC1: UC3-F2-P2-S1-M2 | AD1: UC3-F3-P1-S1-M2 | AE1: UC3-F3-P2-S1-M2
A2: Éxito | B2: =IF(COUNTA(B$3:B$47)>0,COUNTIF(B$3:B$47,"Yes")/(COUNTIF(B$3:B$47,"Yes")+COUNTIF(B$3:B$47,"No")),"") -> 0.80555556 | C2: =IF(COUNTA(C$3:C$47)>0,COUNTIF(C$3:C$47,"Yes")/(COUNTIF(C$3:C$47,"Yes")+COUNTIF(C$3:C$47,"No")),"") -> 0.41935484 | D2: =IF(COUNTA(D$3:D$47)>0,COUNTIF(D$3:D$47,"Yes")/(COUNTIF(D$3:D$47,"Yes")+COUNTIF(D$3:D$47,"No")),"") -> 0.67647059 | E2: =IF(COUNTA(E$3:E$47)>0,COUNTIF(E$3:E$47,"Yes")/(COUNTIF(E$3:E$47,"Yes")+COUNTIF(E$3:E$47,"No")),"") -> 0.82051282 | F2: =IF(COUNTA(F$3:F$47)>0,COUNTIF(F$3:F$47,"Yes")/(COUNTIF(F$3:F$47,"Yes")+COUNTIF(F$3:F$47,"No")),"") -> 0.80555556 | G2: =IF(COUNTA(G$3:G$47)>0,COUNTIF(G$3:G$47,"Yes")/(COUNTIF(G$3:G$47,"Yes")+COUNTIF(G$3:G$47,"No")),"") -> 0.79411765 | H2: =IF(COUNTA(H$3:H$47)>0,COUNTIF(H$3:H$47,"Yes")/(COUNTIF(H$3:H$47,"Yes")+COUNTIF(H$3:H$47,"No")),"") -> 1 | I2: =IF(COUNTA(I$3:I$47)>0,COUNTIF(I$3:I$47,"Yes")/(COUNTIF(I$3:I$47,"Yes")+COUNTIF(I$3:I$47,"No")),"") -> 1 | ... AE2: =IF(COUNTA(AE$3:AE$47)>0,COUNTIF(AE$3:AE$47,"Yes")/(COUNTIF(AE$3:AE$47,"Yes")+COUNTIF(AE$3:AE$47,"No")),"") -> 0.83870968
A3: Coste de diagnóstico | B3: {=CHOOSE(INDEX('Ontology and concepts per UC'!$G$2:$I$46,MATCH($A3,'Ontology and concepts per UC'!$F$2:$F$46,0),MATCH(LEFT(B$1,3),'Ontology and concepts per UC'!$G$1:$I$1,0))+1,"NA",IF(COUNTIFS(Validation!$A:$A,B$1,Validation!$S:$S,$A3)>0,"Yes","No"),IF(COUNTIFS(Validation!$A:$A,B$1,Validation!$S:$S,$A3)>0,"Yes","NA"))} -> Yes | C3: {=CHOOSE(INDEX('Ontology and concepts per UC'!$G$2:$I$46,MATCH($A3,'Ontology and concepts per UC'!$F$2:$F$46,0),MATCH(LEFT(C$1,3),'Ontology and concepts per UC'!$G$1:$I$1,0))+1,"NA",IF(COUNTIFS(Validation!$A:$A,C$1,Validation!$S:$S,$A3)>0,"Yes","No"),IF(COUNTIFS(Validation!$A:$A,C$1,Validation!$S:$S,$A3)>0,"Yes","NA"))} -> Yes | D3: {=CHOOSE(INDEX('Ontology and concepts per UC'!$G$2:$I$46,MATCH($A3,'Ontology and concepts per UC'!$F$2:$F$46,0),MATCH(LEFT(D$1,3),'Ontology and concepts per UC'!$G$1:$I$1,0))+1,"NA",IF(COUNTIFS(Validation!$A:$A,D$1,Validation!$S:$S,$A3)>0,"Yes","No"),IF(COUNTIFS(Validation!$A:$A,D$1,Validation!$S:$S,$A3)>0,"Yes","NA"))} -> NA | E3: {=CHOOSE(INDEX('Ontology and concepts per UC'!$G$2:$I$46,MATCH($A3,'Ontology and concepts per UC'!$F$2:$F$46,0),MATCH(LEFT(E$1,3),'Ontology and concepts per UC'!$G$1:$I$1,0))+1,"NA",IF(COUNTIFS(Validation!$A:$A,E$1,Validation!$S:$S,$A3)>0,"Yes","No"),IF(COUNTIFS(Validation!$A:$A,E$1,Validation!$S:$S,$A3)>0,"Yes","NA"))} -> Yes | F3: {=CHOOSE(INDEX('Ontology and concepts per UC'!$G$2:$I$46,MATCH($A3,'Ontology and concepts per UC'!$F$2:$F$46,0),MATCH(LEFT(F$1,3),'Ontology and concepts per UC'!$G$1:$I$1,0))+1,"NA",IF(COUNTIFS(Validation!$A:$A,F$1,Validation!$S:$S,$A3)>0,"Yes","No"),IF(COUNTIFS(Validation!$A:$A,F$1,Validation!$S:$S,$A3)>0,"Yes","NA"))} -> NA | G3: {=CHOOSE(INDEX('Ontology and concepts per UC'!$G$2:$I$46,MATCH($A3,'Ontology and concepts per UC'!$F$2:$F$46,0),MATCH(LEFT(G$1,3),'Ontology and concepts per UC'!$G$1:$I$1,0))+1,"NA",IF(COUNTIFS(Validation!$A:$A,G$1,Validation!$S:$S,$A3)>0,"Yes","No"),IF(COUNTIFS(Validation!$A:$A,G$1,Validation!$S:$S,$A3)>0,"Yes","NA"))} -> NA | H3: {=CHOOSE(INDEX('Ontology and concepts per UC'!$G$2:$I$46,MATCH($A3,'Ontology and concepts per UC'!$F$2:$F$46,0),MATCH(LEFT(H$1,3),'Ontology and concepts per UC'!$G$1:$I$1,0))+1,"NA",IF(COUNTIFS(Validation!$A:$A,H$1,Validation!$S:$S,$A3)>0,"Yes","No"),IF(COUNTIFS(Validation!$A:$A,H$1,Validation!$S:$S,$A3)>0,"Yes","NA"))} -> NA | I3: {=CHOOSE(INDEX('Ontology and concepts per UC'!$G$2:$I$46,MATCH($A3,'Ontology and concepts per UC'!$F$2:$F$46,0),MATCH(LEFT(I$1,3),'Ontology and concepts per UC'!$G$1:$I$1,0))+1,"NA",IF(COUNTIFS(Validation!$A:$A,I$1,Validation!$S:$S,$A3)>0,"Yes","No"),IF(COUNTIFS(Validation!$A:$A,I$1,Validation!$S:$S,$A3)>0,"Yes","NA"))} -> NA | ... AE3: {=CHOOSE(INDEX('Ontology and concepts per UC'!$G$2:$I$46,MATCH($A3,'Ontology and concepts per UC'!$F$2:$F$46,0),MATCH(LEFT(AE$1,3),'Ontology and concepts per UC'!$G$1:$I$1,0))+1,"NA",IF(COUNTIFS(Validation!$A:$A,AE$1,Validation!$S:$S,$A3)>0,"Yes","No"),IF(COUNTIFS(Validation!$A:$A,AE$1,Validation!$S:$S,$A3)>0,"Yes","NA"))} -> NA
A4: Coste de seguimiento | B4: {=CHOOSE(INDEX('Ontology and concepts per UC'!$G$2:$I$46,MATCH($A4,'Ontology and concepts per UC'!$F$2:$F$46,0),MATCH(LEFT(B$1,3),'Ontology and concepts per UC'!$G$1:$I$1,0))+1,"NA",IF(COUNTIFS(Validation!$A:$A,B$1,Validation!$S:$S,$A4)>0,"Yes","No"),IF(COUNTIFS(Validation!$A:$A,B$1,Validation!$S:$S,$A4)>0,"Yes","NA"))} -> NA | C4: {=CHOOSE(INDEX('Ontology and concepts per UC'!$G$2:$I$46,MATCH($A4,'Ontology and concepts per UC'!$F$2:$F$46,0),MATCH(LEFT(C$1,3),'Ontology and concepts per UC'!$G$1:$I$1,0))+1,"NA",IF(COUNTIFS(Validation!$A:$A,C$1,Validation!$S:$S,$A4)>0,"Yes","No"),IF(COUNTIFS(Validation!$A:$A,C$1,Validation!$S:$S,$A4)>0,"Yes","NA"))} -> NA | D4: {=CHOOSE(INDEX('Ontology and concepts per UC'!$G$2:$I$46,MATCH($A4,'Ontology and concepts per UC'!$F$2:$F$46,0),MATCH(LEFT(D$1,3),'Ontology and concepts per UC'!$G$1:$I$1,0))+1,"NA",IF(COUNTIFS(Validation!$A:$A,D$1,Validation!$S:$S,$A4)>0,"Yes","No"),IF(COUNTIFS(Validation!$A:$A,D$1,Validation!$S:$S,$A4)>0,"Yes","NA"))} -> NA | E4: {=CHOOSE(INDEX('Ontology and concepts per UC'!$G$2:$I$46,MATCH($A4,'Ontology and concepts per UC'!$F$2:$F$46,0),MATCH(LEFT(E$1,3),'Ontology and concepts per UC'!$G$1:$I$1,0))+1,"NA",IF(COUNTIFS(Validation!$A:$A,E$1,Validation!$S:$S,$A4)>0,"Yes","No"),IF(COUNTIFS(Validation!$A:$A,E$1,Validation!$S:$S,$A4)>0,"Yes","NA"))} -> NA | F4: {=CHOOSE(INDEX('Ontology and concepts per UC'!$G$2:$I$46,MATCH($A4,'Ontology and concepts per UC'!$F$2:$F$46,0),MATCH(LEFT(F$1,3),'Ontology and concepts per UC'!$G$1:$I$1,0))+1,"NA",IF(COUNTIFS(Validation!$A:$A,F$1,Validation!$S:$S,$A4)>0,"Yes","No"),IF(COUNTIFS(Validation!$A:$A,F$1,Validation!$S:$S,$A4)>0,"Yes","NA"))} -> NA | G4: {=CHOOSE(INDEX('Ontology and concepts per UC'!$G$2:$I$46,MATCH($A4,'Ontology and concepts per UC'!$F$2:$F$46,0),MATCH(LEFT(G$1,3),'Ontology and concepts per UC'!$G$1:$I$1,0))+1,"NA",IF(COUNTIFS(Validation!$A:$A,G$1,Validation!$S:$S,$A4)>0,"Yes","No"),IF(COUNTIFS(Validation!$A:$A,G$1,Validation!$S:$S,$A4)>0,"Yes","NA"))} -> NA | H4: {=CHOOSE(INDEX('Ontology and concepts per UC'!$G$2:$I$46,MATCH($A4,'Ontology and concepts per UC'!$F$2:$F$46,0),MATCH(LEFT(H$1,3),'Ontology and concepts per UC'!$G$1:$I$1,0))+1,"NA",IF(COUNTIFS(Validation!$A:$A,H$1,Validation!$S:$S,$A4)>0,"Yes","No"),IF(COUNTIFS(Validation!$A:$A,H$1,Validation!$S:$S,$A4)>0,"Yes","NA"))} -> NA | I4: {=CHOOSE(INDEX('Ontology and concepts per UC'!$G$2:$I$46,MATCH($A4,'Ontology and concepts per UC'!$F$2:$F$46,0),MATCH(LEFT(I$1,3),'Ontology and concepts per UC'!$G$1:$I$1,0))+1,"NA",IF(COUNTIFS(Validation!$A:$A,I$1,Validation!$S:$S,$A4)>0,"Yes","No"),IF(COUNTIFS(Validation!$A:$A,I$1,Validation!$S:$S,$A4)>0,"Yes","NA"))} -> NA | ... AE4: {=CHOOSE(INDEX('Ontology and concepts per UC'!$G$2:$I$46,MATCH($A4,'Ontology and concepts per UC'!$F$2:$F$46,0),MATCH(LEFT(AE$1,3),'Ontology and concepts per UC'!$G$1:$I$1,0))+1,"NA",IF(COUNTIFS(Validation!$A:$A,AE$1,Validation!$S:$S,$A4)>0,"Yes","No"),IF(COUNTIFS(Validation!$A:$A,AE$1,Validation!$S:$S,$A4)>0,"Yes","NA"))} -> NA
A5: Coste específico manifestación | B5: {=CHOOSE(INDEX('Ontology and concepts per UC'!$G$2:$I$46,MATCH($A5,'Ontology and concepts per UC'!$F$2:$F$46,0),MATCH(LEFT(B$1,3),'Ontology and concepts per UC'!$G$1:$I$1,0))+1,"NA",IF(COUNTIFS(Validation!$A:$A,B$1,Validation!$S:$S,$A5)>0,"Yes","No"),IF(COUNTIFS(Validation!$A:$A,B$1,Validation!$S:$S,$A5)>0,"Yes","NA"))} -> NA | C5: {=CHOOSE(INDEX('Ontology and concepts per UC'!$G$2:$I$46,MATCH($A5,'Ontology and concepts per UC'!$F$2:$F$46,0),MATCH(LEFT(C$1,3),'Ontology and concepts per UC'!$G$1:$I$1,0))+1,"NA",IF(COUNTIFS(Validation!$A:$A,C$1,Validation!$S:$S,$A5)>0,"Yes","No"),IF(COUNTIFS(Validation!$A:$A,C$1,Validation!$S:$S,$A5)>0,"Yes","NA"))} -> NA | D5: {=CHOOSE(INDEX('Ontology and concepts per UC'!$G$2:$I$46,MATCH($A5,'Ontology and concepts per UC'!$F$2:$F$46,0),MATCH(LEFT(D$1,3),'Ontology and concepts per UC'!$G$1:$I$1,0))+1,"NA",IF(COUNTIFS(Validation!$A:$A,D$1,Validation!$S:$S,$A5)>0,"Yes","No"),IF(COUNTIFS(Validation!$A:$A,D$1,Validation!$S:$S,$A5)>0,"Yes","NA"))} -> NA | E5: {=CHOOSE(INDEX('Ontology and concepts per UC'!$G$2:$I$46,MATCH($A5,'Ontology and concepts per UC'!$F$2:$F$46,0),MATCH(LEFT(E$1,3),'Ontology and concepts per UC'!$G$1:$I$1,0))+1,"NA",IF(COUNTIFS(Validation!$A:$A,E$1,Validation!$S:$S,$A5)>0,"Yes","No"),IF(COUNTIFS(Validation!$A:$A,E$1,Validation!$S:$S,$A5)>0,"Yes","NA"))} -> NA | F5: {=CHOOSE(INDEX('Ontology and concepts per UC'!$G$2:$I$46,MATCH($A5,'Ontology and concepts per UC'!$F$2:$F$46,0),MATCH(LEFT(F$1,3),'Ontology and concepts per UC'!$G$1:$I$1,0))+1,"NA",IF(COUNTIFS(Validation!$A:$A,F$1,Validation!$S:$S,$A5)>0,"Yes","No"),IF(COUNTIFS(Validation!$A:$A,F$1,Validation!$S:$S,$A5)>0,"Yes","NA"))} -> NA | G5: {=CHOOSE(INDEX('Ontology and concepts per UC'!$G$2:$I$46,MATCH($A5,'Ontology and concepts per UC'!$F$2:$F$46,0),MATCH(LEFT(G$1,3),'Ontology and concepts per UC'!$G$1:$I$1,0))+1,"NA",IF(COUNTIFS(Validation!$A:$A,G$1,Validation!$S:$S,$A5)>0,"Yes","No"),IF(COUNTIFS(Validation!$A:$A,G$1,Validation!$S:$S,$A5)>0,"Yes","NA"))} -> NA | H5: {=CHOOSE(INDEX('Ontology and concepts per UC'!$G$2:$I$46,MATCH($A5,'Ontology and concepts per UC'!$F$2:$F$46,0),MATCH(LEFT(H$1,3),'Ontology and concepts per UC'!$G$1:$I$1,0))+1,"NA",IF(COUNTIFS(Validation!$A:$A,H$1,Validation!$S:$S,$A5)>0,"Yes","No"),IF(COUNTIFS(Validation!$A:$A,H$1,Validation!$S:$S,$A5)>0,"Yes","NA"))} -> NA | I5: {=CHOOSE(INDEX('Ontology and concepts per UC'!$G$2:$I$46,MATCH($A5,'Ontology and concepts per UC'!$F$2:$F$46,0),MATCH(LEFT(I$1,3),'Ontology and concepts per UC'!$G$1:$I$1,0))+1,"NA",IF(COUNTIFS(Validation!$A:$A,I$1,Validation!$S:$S,$A5)>0,"Yes","No"),IF(COUNTIFS(Validation!$A:$A,I$1,Validation!$S:$S,$A5)>0,"Yes","NA"))} -> NA | ... AE5: {=CHOOSE(INDEX('Ontology and concepts per UC'!$G$2:$I$46,MATCH($A5,'Ontology and concepts per UC'!$F$2:$F$46,0),MATCH(LEFT(AE$1,3),'Ontology and concepts per UC'!$G$1:$I$1,0))+1,"NA",IF(COUNTIFS(Validation!$A:$A,AE$1,Validation!$S:$S,$A5)>0,"Yes","No"),IF(COUNTIFS(Validation!$A:$A,AE$1,Validation!$S:$S,$A5)>0,"Yes","NA"))} -> NA
A6: Coste cribado | B6: {=CHOOSE(INDEX('Ontology and concepts per UC'!$G$2:$I$46,MATCH($A6,'Ontology and concepts per UC'!$F$2:$F$46,0),MATCH(LEFT(B$1,3),'Ontology and concepts per UC'!$G$1:$I$1,0))+1,"NA",IF(COUNTIFS(Validation!$A:$A,B$1,Validation!$S:$S,$A6)>0,"Yes","No"),IF(COUNTIFS(Validation!$A:$A,B$1,Validation!$S:$S,$A6)>0,"Yes","NA"))} -> Yes | C6: {=CHOOSE(INDEX('Ontology and concepts per UC'!$G$2:$I$46,MATCH($A6,'Ontology and concepts per UC'!$F$2:$F$46,0),MATCH(LEFT(C$1,3),'Ontology and concepts per UC'!$G$1:$I$1,0))+1,"NA",IF(COUNTIFS(Validation!$A:$A,C$1,Validation!$S:$S,$A6)>0,"Yes","No"),IF(COUNTIFS(Validation!$A:$A,C$1,Validation!$S:$S,$A6)>0,"Yes","NA"))} -> Yes | D6: {=CHOOSE(INDEX('Ontology and concepts per UC'!$G$2:$I$46,MATCH($A6,'Ontology and concepts per UC'!$F$2:$F$46,0),MATCH(LEFT(D$1,3),'Ontology and concepts per UC'!$G$1:$I$1,0))+1,"NA",IF(COUNTIFS(Validation!$A:$A,D$1,Validation!$S:$S,$A6)>0,"Yes","No"),IF(COUNTIFS(Validation!$A:$A,D$1,Validation!$S:$S,$A6)>0,"Yes","NA"))} -> NA | E6: {=CHOOSE(INDEX('Ontology and concepts per UC'!$G$2:$I$46,MATCH($A6,'Ontology and concepts per UC'!$F$2:$F$46,0),MATCH(LEFT(E$1,3),'Ontology and concepts per UC'!$G$1:$I$1,0))+1,"NA",IF(COUNTIFS(Validation!$A:$A,E$1,Validation!$S:$S,$A6)>0,"Yes","No"),IF(COUNTIFS(Validation!$A:$A,E$1,Validation!$S:$S,$A6)>0,"Yes","NA"))} -> Yes | F6: {=CHOOSE(INDEX('Ontology and concepts per UC'!$G$2:$I$46,MATCH($A6,'Ontology and concepts per UC'!$F$2:$F$46,0),MATCH(LEFT(F$1,3),'Ontology and concepts per UC'!$G$1:$I$1,0))+1,"NA",IF(COUNTIFS(Validation!$A:$A,F$1,Validation!$S:$S,$A6)>0,"Yes","No"),IF(COUNTIFS(Validation!$A:$A,F$1,Validation!$S:$S,$A6)>0,"Yes","NA"))} -> NA | G6: {=CHOOSE(INDEX('Ontology and concepts per UC'!$G$2:$I$46,MATCH($A6,'Ontology and concepts per UC'!$F$2:$F$46,0),MATCH(LEFT(G$1,3),'Ontology and concepts per UC'!$G$1:$I$1,0))+1,"NA",IF(COUNTIFS(Validation!$A:$A,G$1,Validation!$S:$S,$A6)>0,"Yes","No"),IF(COUNTIFS(Validation!$A:$A,G$1,Validation!$S:$S,$A6)>0,"Yes","NA"))} -> NA | H6: {=CHOOSE(INDEX('Ontology and concepts per UC'!$G$2:$I$46,MATCH($A6,'Ontology and concepts per UC'!$F$2:$F$46,0),MATCH(LEFT(H$1,3),'Ontology and concepts per UC'!$G$1:$I$1,0))+1,"NA",IF(COUNTIFS(Validation!$A:$A,H$1,Validation!$S:$S,$A6)>0,"Yes","No"),IF(COUNTIFS(Validation!$A:$A,H$1,Validation!$S:$S,$A6)>0,"Yes","NA"))} -> NA | I6: {=CHOOSE(INDEX('Ontology and concepts per UC'!$G$2:$I$46,MATCH($A6,'Ontology and concepts per UC'!$F$2:$F$46,0),MATCH(LEFT(I$1,3),'Ontology and concepts per UC'!$G$1:$I$1,0))+1,"NA",IF(COUNTIFS(Validation!$A:$A,I$1,Validation!$S:$S,$A6)>0,"Yes","No"),IF(COUNTIFS(Validation!$A:$A,I$1,Validation!$S:$S,$A6)>0,"Yes","NA"))} -> NA | ... AE6: {=CHOOSE(INDEX('Ontology and concepts per UC'!$G$2:$I$46,MATCH($A6,'Ontology and concepts per UC'!$F$2:$F$46,0),MATCH(LEFT(AE$1,3),'Ontology and concepts per UC'!$G$1:$I$1,0))+1,"NA",IF(COUNTIFS(Validation!$A:$A,AE$1,Validation!$S:$S,$A6)>0,"Yes","No"),IF(COUNTIFS(Validation!$A:$A,AE$1,Validation!$S:$S,$A6)>0,"Yes","NA"))} -> NA
A7: Coste tratamiento | B7: {=CHOOSE(INDEX('Ontology and concepts per UC'!$G$2:$I$46,MATCH($A7,'Ontology and concepts per UC'!$F$2:$F$46,0),MATCH(LEFT(B$1,3),'Ontology and concepts per UC'!$G$1:$I$1,0))+1,"NA",IF(COUNTIFS(Validation!$A:$A,B$1,Validation!$S:$S,$A7)>0,"Yes","No"),IF(COUNTIFS(Validation!$A:$A,B$1,Validation!$S:$S,$A7)>0,"Yes","NA"))} -> Yes | C7: {=CHOOSE(INDEX('Ontology and concepts per UC'!$G$2:$I$46,MATCH($A7,'Ontology and concepts per UC'!$F$2:$F$46,0),MATCH(LEFT(C$1,3),'Ontology and concepts per UC'!$G$1:$I$1,0))+1,"NA",IF(COUNTIFS(Validation!$A:$A,C$1,Validation!$S:$S,$A7)>0,"Yes","No"),IF(COUNTIFS(Validation!$A:$A,C$1,Validation!$S:$S,$A7)>0,"Yes","NA"))} -> NA | D7: {=CHOOSE(INDEX('Ontology and concepts per UC'!$G$2:$I$46,MATCH($A7,'Ontology and concepts per UC'!$F$2:$F$46,0),MATCH(LEFT(D$1,3),'Ontology and concepts per UC'!$G$1:$I$1,0))+1,"NA",IF(COUNTIFS(Validation!$A:$A,D$1,Validation!$S:$S,$A7)>0,"Yes","No"),IF(COUNTIFS(Validation!$A:$A,D$1,Validation!$S:$S,$A7)>0,"Yes","NA"))} -> NA | E7: {=CHOOSE(INDEX('Ontology and concepts per UC'!$G$2:$I$46,MATCH($A7,'Ontology and concepts per UC'!$F$2:$F$46,0),MATCH(LEFT(E$1,3),'Ontology and concepts per UC'!$G$1:$I$1,0))+1,"NA",IF(COUNTIFS(Validation!$A:$A,E$1,Validation!$S:$S,$A7)>0,"Yes","No"),IF(COUNTIFS(Validation!$A:$A,E$1,Validation!$S:$S,$A7)>0,"Yes","NA"))} -> Yes | F7: {=CHOOSE(INDEX('Ontology and concepts per UC'!$G$2:$I$46,MATCH($A7,'Ontology and concepts per UC'!$F$2:$F$46,0),MATCH(LEFT(F$1,3),'Ontology and concepts per UC'!$G$1:$I$1,0))+1,"NA",IF(COUNTIFS(Validation!$A:$A,F$1,Validation!$S:$S,$A7)>0,"Yes","No"),IF(COUNTIFS(Validation!$A:$A,F$1,Validation!$S:$S,$A7)>0,"Yes","NA"))} -> NA | G7: {=CHOOSE(INDEX('Ontology and concepts per UC'!$G$2:$I$46,MATCH($A7,'Ontology and concepts per UC'!$F$2:$F$46,0),MATCH(LEFT(G$1,3),'Ontology and concepts per UC'!$G$1:$I$1,0))+1,"NA",IF(COUNTIFS(Validation!$A:$A,G$1,Validation!$S:$S,$A7)>0,"Yes","No"),IF(COUNTIFS(Validation!$A:$A,G$1,Validation!$S:$S,$A7)>0,"Yes","NA"))} -> NA | H7: {=CHOOSE(INDEX('Ontology and concepts per UC'!$G$2:$I$46,MATCH($A7,'Ontology and concepts per UC'!$F$2:$F$46,0),MATCH(LEFT(H$1,3),'Ontology and concepts per UC'!$G$1:$I$1,0))+1,"NA",IF(COUNTIFS(Validation!$A:$A,H$1,Validation!$S:$S,$A7)>0,"Yes","No"),IF(COUNTIFS(Validation!$A:$A,H$1,Validation!$S:$S,$A7)>0,"Yes","NA"))} -> NA | I7: {=CHOOSE(INDEX('Ontology and concepts per UC'!$G$2:$I$46,MATCH($A7,'Ontology and concepts per UC'!$F$2:$F$46,0),MATCH(LEFT(I$1,3),'Ontology and concepts per UC'!$G$1:$I$1,0))+1,"NA",IF(COUNTIFS(Validation!$A:$A,I$1,Validation!$S:$S,$A7)>0,"Yes","No"),IF(COUNTIFS(Validation!$A:$A,I$1,Validation!$S:$S,$A7)>0,"Yes","NA"))} -> NA | ... AE7: {=CHOOSE(INDEX('Ontology and concepts per UC'!$G$2:$I$46,MATCH($A7,'Ontology and concepts per UC'!$F$2:$F$46,0),MATCH(LEFT(AE$1,3),'Ontology and concepts per UC'!$G$1:$I$1,0))+1,"NA",IF(COUNTIFS(Validation!$A:$A,AE$1,Validation!$S:$S,$A7)>0,"Yes","No"),IF(COUNTIFS(Validation!$A:$A,AE$1,Validation!$S:$S,$A7)>0,"Yes","NA"))} -> NA
A8: Población | B8: {=CHOOSE(INDEX('Ontology and concepts per UC'!$G$2:$I$46,MATCH($A8,'Ontology and concepts per UC'!$F$2:$F$46,0),MATCH(LEFT(B$1,3),'Ontology and concepts per UC'!$G$1:$I$1,0))+1,"NA",IF(COUNTIFS(Validation!$A:$A,B$1,Validation!$S:$S,$A8)>0,"Yes","No"),IF(COUNTIFS(Validation!$A:$A,B$1,Validation!$S:$S,$A8)>0,"Yes","NA"))} -> Yes | C8: {=CHOOSE(INDEX('Ontology and concepts per UC'!$G$2:$I$46,MATCH($A8,'Ontology and concepts per UC'!$F$2:$F$46,0),MATCH(LEFT(C$1,3),'Ontology and concepts per UC'!$G$1:$I$1,0))+1,"NA",IF(COUNTIFS(Validation!$A:$A,C$1,Validation!$S:$S,$A8)>0,"Yes","No"),IF(COUNTIFS(Validation!$A:$A,C$1,Validation!$S:$S,$A8)>0,"Yes","NA"))} -> Yes | D8: {=CHOOSE(INDEX('Ontology and concepts per UC'!$G$2:$I$46,MATCH($A8,'Ontology and concepts per UC'!$F$2:$F$46,0),MATCH(LEFT(D$1,3),'Ontology and concepts per UC'!$G$1:$I$1,0))+1,"NA",IF(COUNTIFS(Validation!$A:$A,D$1,Validation!$S:$S,$A8)>0,"Yes","No"),IF(COUNTIFS(Validation!$A:$A,D$1,Validation!$S:$S,$A8)>0,"Yes","NA"))} -> No | E8: {=CHOOSE(INDEX('Ontology and concepts per UC'!$G$2:$I$46,MATCH($A8,'Ontology and concepts per UC'!$F$2:$F$46,0),MATCH(LEFT(E$1,3),'Ontology and concepts per UC'!$G$1:$I$1,0))+1,"NA",IF(COUNTIFS(Validation!$A:$A,E$1,Validation!$S:$S,$A8)>0,"Yes","No"),IF(COUNTIFS(Validation!$A:$A,E$1,Validation!$S:$S,$A8)>0,"Yes","NA"))} -> No | F8: {=CHOOSE(INDEX('Ontology and concepts per UC'!$G$2:$I$46,MATCH($A8,'Ontology and concepts per UC'!$F$2:$F$46,0),MATCH(LEFT(F$1,3),'Ontology and concepts per UC'!$G$1:$I$1,0))+1,"NA",IF(COUNTIFS(Validation!$A:$A,F$1,Validation!$S:$S,$A8)>0,"Yes","No"),IF(COUNTIFS(Validation!$A:$A,F$1,Validation!$S:$S,$A8)>0,"Yes","NA"))} -> No | G8: {=CHOOSE(INDEX('Ontology and concepts per UC'!$G$2:$I$46,MATCH($A8,'Ontology and concepts per UC'!$F$2:$F$46,0),MATCH(LEFT(G$1,3),'Ontology and concepts per UC'!$G$1:$I$1,0))+1,"NA",IF(COUNTIFS(Validation!$A:$A,G$1,Validation!$S:$S,$A8)>0,"Yes","No"),IF(COUNTIFS(Validation!$A:$A,G$1,Validation!$S:$S,$A8)>0,"Yes","NA"))} -> No | H8: {=CHOOSE(INDEX('Ontology and concepts per UC'!$G$2:$I$46,MATCH($A8,'Ontology and concepts per UC'!$F$2:$F$46,0),MATCH(LEFT(H$1,3),'Ontology and concepts per UC'!$G$1:$I$1,0))+1,"NA",IF(COUNTIFS(Validation!$A:$A,H$1,Validation!$S:$S,$A8)>0,"Yes","No"),IF(COUNTIFS(Validation!$A:$A,H$1,Validation!$S:$S,$A8)>0,"Yes","NA"))} -> NA | I8: {=CHOOSE(INDEX('Ontology and concepts per UC'!$G$2:$I$46,MATCH($A8,'Ontology and concepts per UC'!$F$2:$F$46,0),MATCH(LEFT(I$1,3),'Ontology and concepts per UC'!$G$1:$I$1,0))+1,"NA",IF(COUNTIFS(Validation!$A:$A,I$1,Validation!$S:$S,$A8)>0,"Yes","No"),IF(COUNTIFS(Validation!$A:$A,I$1,Validation!$S:$S,$A8)>0,"Yes","NA"))} -> NA | ... AE8: {=CHOOSE(INDEX('Ontology and concepts per UC'!$G$2:$I$46,MATCH($A8,'Ontology and concepts per UC'!$F$2:$F$46,0),MATCH(LEFT(AE$1,3),'Ontology and concepts per UC'!$G$1:$I$1,0))+1,"NA",IF(COUNTIFS(Validation!$A:$A,AE$1,Validation!$S:$S,$A8)>0,"Yes","No"),IF(COUNTIFS(Validation!$A:$A,AE$1,Validation!$S:$S,$A8)>0,"Yes","NA"))} -> No
A9: Población: edad | B9: {=CHOOSE(INDEX('Ontology and concepts per UC'!$G$2:$I$46,MATCH($A9,'Ontology and concepts per UC'!$F$2:$F$46,0),MATCH(LEFT(B$1,3),'Ontology and concepts per UC'!$G$1:$I$1,0))+1,"NA",IF(COUNTIFS(Validation!$A:$A,B$1,Validation!$S:$S,$A9)>0,"Yes","No"),IF(COUNTIFS(Validation!$A:$A,B$1,Validation!$S:$S,$A9)>0,"Yes","NA"))} -> NA | C9: {=CHOOSE(INDEX('Ontology and concepts per UC'!$G$2:$I$46,MATCH($A9,'Ontology and concepts per UC'!$F$2:$F$46,0),MATCH(LEFT(C$1,3),'Ontology and concepts per UC'!$G$1:$I$1,0))+1,"NA",IF(COUNTIFS(Validation!$A:$A,C$1,Validation!$S:$S,$A9)>0,"Yes","No"),IF(COUNTIFS(Validation!$A:$A,C$1,Validation!$S:$S,$A9)>0,"Yes","NA"))} -> NA | D9: {=CHOOSE(INDEX('Ontology and concepts per UC'!$G$2:$I$46,MATCH($A9,'Ontology and concepts per UC'!$F$2:$F$46,0),MATCH(LEFT(D$1,3),'Ontology and concepts per UC'!$G$1:$I$1,0))+1,"NA",IF(COUNTIFS(Validation!$A:$A,D$1,Validation!$S:$S,$A9)>0,"Yes","No"),IF(COUNTIFS(Validation!$A:$A,D$1,Validation!$S:$S,$A9)>0,"Yes","NA"))} -> NA | E9: {=CHOOSE(INDEX('Ontology and concepts per UC'!$G$2:$I$46,MATCH($A9,'Ontology and concepts per UC'!$F$2:$F$46,0),MATCH(LEFT(E$1,3),'Ontology and concepts per UC'!$G$1:$I$1,0))+1,"NA",IF(COUNTIFS(Validation!$A:$A,E$1,Validation!$S:$S,$A9)>0,"Yes","No"),IF(COUNTIFS(Validation!$A:$A,E$1,Validation!$S:$S,$A9)>0,"Yes","NA"))} -> NA | F9: {=CHOOSE(INDEX('Ontology and concepts per UC'!$G$2:$I$46,MATCH($A9,'Ontology and concepts per UC'!$F$2:$F$46,0),MATCH(LEFT(F$1,3),'Ontology and concepts per UC'!$G$1:$I$1,0))+1,"NA",IF(COUNTIFS(Validation!$A:$A,F$1,Validation!$S:$S,$A9)>0,"Yes","No"),IF(COUNTIFS(Validation!$A:$A,F$1,Validation!$S:$S,$A9)>0,"Yes","NA"))} -> NA | G9: {=CHOOSE(INDEX('Ontology and concepts per UC'!$G$2:$I$46,MATCH($A9,'Ontology and concepts per UC'!$F$2:$F$46,0),MATCH(LEFT(G$1,3),'Ontology and concepts per UC'!$G$1:$I$1,0))+1,"NA",IF(COUNTIFS(Validation!$A:$A,G$1,Validation!$S:$S,$A9)>0,"Yes","No"),IF(COUNTIFS(Validation!$A:$A,G$1,Validation!$S:$S,$A9)>0,"Yes","NA"))} -> NA | H9: {=CHOOSE(INDEX('Ontology and concepts per UC'!$G$2:$I$46,MATCH($A9,'Ontology and concepts per UC'!$F$2:$F$46,0),MATCH(LEFT(H$1,3),'Ontology and concepts per UC'!$G$1:$I$1,0))+1,"NA",IF(COUNTIFS(Validation!$A:$A,H$1,Validation!$S:$S,$A9)>0,"Yes","No"),IF(COUNTIFS(Validation!$A:$A,H$1,Validation!$S:$S,$A9)>0,"Yes","NA"))} -> NA | I9: {=CHOOSE(INDEX('Ontology and concepts per UC'!$G$2:$I$46,MATCH($A9,'Ontology and concepts per UC'!$F$2:$F$46,0),MATCH(LEFT(I$1,3),'Ontology and concepts per UC'!$G$1:$I$1,0))+1,"NA",IF(COUNTIFS(Validation!$A:$A,I$1,Validation!$S:$S,$A9)>0,"Yes","No"),IF(COUNTIFS(Validation!$A:$A,I$1,Validation!$S:$S,$A9)>0,"Yes","NA"))} -> NA | ... AE9: {=CHOOSE(INDEX('Ontology and concepts per UC'!$G$2:$I$46,MATCH($A9,'Ontology and concepts per UC'!$F$2:$F$46,0),MATCH(LEFT(AE$1,3),'Ontology and concepts per UC'!$G$1:$I$1,0))+1,"NA",IF(COUNTIFS(Validation!$A:$A,AE$1,Validation!$S:$S,$A9)>0,"Yes","No"),IF(COUNTIFS(Validation!$A:$A,AE$1,Validation!$S:$S,$A9)>0,"Yes","NA"))} -> NA
